Workbook

Sheet Form responses 1
A1: Timestamp | B1: Email address | C1: Which country are you affiliated to? (use Switzerland instead of CH) | D1: Did you or your country contribute to one of the deliverables (or a closely related one)? (Indicate all, we will then follow up) (April 2020 until October 2022) | E1: Did you or your country contribute to one of the MoU objectives (or a closely related one)? (Indicate all, we will then follow up) (April 20 to Oct 22) | F1: Were you (co-) author of a COST related publication (incl. submitted pre-prints (e.g. arxiv.org))? | G1: Were you or your country involved in other projects resulting from Action activities? (If yes, we will follow up with more details later) | H1: Were you or your country involved in other outputs/ achievements resulting from Action activities? (e.g. a patent, standards, white paper) | I1: Did you create any other impact related to COST FinAI? | J1: Did you contribute to activities that are advancing the careers, skills and network of researchers, including ECIs(for example: joint supervision of graduate and PhD students, research exchanges not funded by the Action, collaborations, Training Schools with ECTS accreditation, joint projects and jobs prospects). | K1: Did you participate in other dissemination activities? (E.g. participation to non-Action meetings, e.g. EU Parliament, meetings with policy makers, experts in the field, regional authorities.) | L1: Were you involved in any other activities undertaken to ensure exploitation (use, in particular in a commercial context) of the Action's achievements. | M1: Score | N1: Which working group do you belong to? | O1: Anything else you think is relevant to the COST report from April 20 to Oct 22? Please add any other achievements, outcomes, cooperations, etc. | P1: Were you involved in any proposals/ projects?
A2: 44752.81 | B2: lleshlleshaj@feut.edu.al | C2: Albania | D2: A discussion paper for possible approaches to building a statistically valid back-testing framework, Methodological discussion paper on the design of stress tests for the evaluation of AI and ML models under shifting financial conditions to improve the robustness of models | E2: Significantly improve the gender equality in the fields of the Action. | F2: No | H2: No | J2: No | K2: Yes | L2: No | M2: 0 | N2: WG 1 | P2: No
A3: 44756.976 | B3: eliona.gremi@uniel.edu.al | C3: Albania | D3: No | E3: Create an excellent network of researchers in Europe with lasting collaboration beyond the lifetime of the Action., Transfer knowledge in terms of expertise, scientific tools and human resources across the different disciplines and between academia and industry. | F3: No | H3: No | J3: No | K3: No | L3: Yes | M3: 0 | N3: WG 1, WG 2, WG 3 | P3: No
A4: 44772.589 | B4: tidjani.chemseddine@gmail.com | C4: Algeria | D4: No | E4: Disseminate to the public and share with regulators the results on investment product performance evaluation., Bridging the gap between practitioners from the finance industry, academics and regulators by setting up a common knowledge exchange platform., Transfer knowledge in terms of expertise, scientific tools and human resources across the different disciplines and between academia and industry. | F4: Yes | H4: No | J4: Yes | K4: Yes | L4: No | M4: 0 | N4: WG 2 | O4: Cost action can be considered as a resource for diverse human capacities from all over the world. Cost action can establish and reinforce collaborations between Europe and TCC countries. | P4: Yes
A5: 44736.475 | B5: ronald.hochreiter@wu.ac.at | C5: Austria | D5: Anything else useful for the COST Action, not mentioned below, An edited volume containing scientific achievements of the Action | E5: Anything else useful and related to the below topics, To develop blended approaches to evaluate innovative financial services and their providers, especially in the FinTech domain, building on Machine Learning methods, focussing on prediction (early warning) of operational fragility, fraudulent and illegal behaviour ranging from appropriation of loaned funds to money-laundering activities., The development of conceptual and methodological tools for establishing when blackbox models are admissible and, to the extent possible, making them more transparent and/or replacing them with interpretable and explainable models., To receive input from regulators and practitioners' communities and to validate results with regard to increasing transparency of artificial intelligence applications., Disseminate to the public and share with regulators the results on investment product performance evaluation., Create an excellent network of researchers in Europe with lasting collaboration beyond the lifetime of the Action., Bridging the gap between practitioners from the finance industry, academics and regulators by setting up a common knowledge exchange platform., Transfer knowledge in terms of expertise, scientific tools and human resources across the different disciplines and between academia and industry., Disseminate the results of the Action's activities to the scientific community, European institutions and to the general public. | F5: No | H5: No | J5: No | K5: Yes | L5: Yes | M5: 0 | N5: WG 1, WG 2, WG 3 | P5: Yes
A6: 44746.816 | B6: aivanisev@net.efzg.hr | C6: Croatia | D6: Anything else useful for the COST Action, not mentioned below | E6: Anything else useful and related to the below topics, Create an excellent network of researchers in Europe with lasting collaboration beyond the lifetime of the Action., Bridging the gap between practitioners from the finance industry, academics and regulators by setting up a common knowledge exchange platform., Disseminate the results of the Action's activities to the scientific community, European institutions and to the general public. | F6: No | H6: No | J6: No | K6: No | L6: No | M6: 0 | N6: WG 1, WG 3 | O6: Organisation of a conference related to COST FinAI topics of interest, which has served as a knowledge exchange platform between researchers, practitioners and regulators | P6: No
A7: 44796.414 | B7: svlahjeric@gmail.com | C7: Croatia | D7: Anything else useful for the COST Action, not mentioned below | E7: Create an excellent network of researchers in Europe with lasting collaboration beyond the lifetime of the Action., Bringing technological, quantitative and economic researchers together, to tackle future research that can only be done in an interdisciplinary setting, and getting actively involved in the blockchain and FinTech communities across Europe, to constantly monitor developments, get input and disseminate results., Transfer knowledge in terms of expertise, scientific tools and human resources across the different disciplines and between academia and industry. | F7: No | H7: No | J7: No | K7: Yes | L7: No | M7: 0 | N7: WG 2 | P7: No
A8: 44752.788 | B8: georgiou.i@unic.ac.cy | C8: Cyprus | D8: No | E8: No, Anything else useful and related to the below topics, Bringing technological, quantitative and economic researchers together, to tackle future research that can only be done in an interdisciplinary setting, and getting actively involved in the blockchain and FinTech communities across Europe, to constantly monitor developments, get input and disseminate results., Overcome the siloing of research topics by country and achieve geographical and demographical diversity, with special attention to COST Inclusiveness Target countries., Significantly improve the gender equality in the fields of the Action. | F8: No | H8: No | J8: No | K8: No | L8: No | M8: 0 | N8: WG 1 | P8: Yes
A9: 44736.427 | B9: petr.hajek@upce.cz | C9: Czech Republic | D9: Anything else useful for the COST Action, not mentioned below | E9: No | F9: No | H9: Yes | J9: Yes | K9: Yes | L9: No | M9: 0 | N9: WG 2 | P9: Yes
A10: 44796.432 | B10: luislore@ucm.es | C10: España | D10: A discussion paper for possible approaches to building a statistically valid back-testing framework | E10: Maximize the job opportunities for PhD students and Early Career Investigators., Disseminate the results of the Action's activities to the scientific community, European institutions and to the general public. | F10: Yes | H10: Yes | J10: Yes | K10: No | L10: No | M10: 0 | N10: WG 2 | P10: Yes
A11: 44736.803 | B11: laivi.laidroo@taltech.ee | C11: Estonia | D11: No | E11: No | F11: No | H11: No | J11: No | K11: Yes | L11: Yes | M11: 0 | N11: WG 1 | P11: No
A12: 44753.418 | B12: innar.liiv@taltech.ee | C12: Estonia | D12: Anything else useful for the COST Action, not mentioned below | E12: To develop blended approaches to evaluate innovative financial services and their providers, especially in the FinTech domain, building on Machine Learning methods, focussing on prediction (early warning) of operational fragility, fraudulent and illegal behaviour ranging from appropriation of loaned funds to money-laundering activities., The development of conceptual and methodological tools for establishing when blackbox models are admissible and, to the extent possible, making them more transparent and/or replacing them with interpretable and explainable models., To receive input from regulators and practitioners' communities and to validate results with regard to increasing transparency of artificial intelligence applications., Create an excellent network of researchers in Europe with lasting collaboration beyond the lifetime of the Action., Bringing technological, quantitative and economic researchers together, to tackle future research that can only be done in an interdisciplinary setting, and getting actively involved in the blockchain and FinTech communities across Europe, to constantly monitor developments, get input and disseminate results., Transfer knowledge in terms of expertise, scientific tools and human resources across the different disciplines and between academia and industry., Overcome the siloing of research topics by country and achieve geographical and demographical diversity, with special attention to COST Inclusiveness Target countries., Disseminate the results of the Action's activities to the scientific community, European institutions and to the general public. | F12: Yes | H12: No | J12: No | K12: Yes | L12: Yes | M12: 0 | N12: WG 3 | O12: Published a book, COST action is mentioned: https://link.springer.com/book/10.1007/978-981-16-2418-6 | P12: No
A13: 44735.473 | B13: roman.matkovskyy@rennes-sb.com | C13: France | D13: A database which contains data on crowdfunding/P2P platform features useful for rating platform integrity and to predict fraud, A position paper and roadmap on mitigating risks connected with the increased use of digital assets | E13: Bringing technological, quantitative and economic researchers together, to tackle future research that can only be done in an interdisciplinary setting, and getting actively involved in the blockchain and FinTech communities across Europe, to constantly monitor developments, get input and disseminate results., Transfer knowledge in terms of expertise, scientific tools and human resources across the different disciplines and between academia and industry., Disseminate the results of the Action's activities to the scientific community, European institutions and to the general public. | F13: Yes | H13: No | I13: Yes | J13: Yes | K13: Yes | L13: No | M13: 0 | N13: WG 1, WG 2 | O13: rather explanation of the previous points: databases on KIVA Paper: Jalan, A., Matkovskyy, R., and Poti, V. (2022). "Shall the winning last? A study of recent bubbles and persistence." Finance Research Letters 45, 102162 Bringing technological, quantitative and economic researchers... and dissemination : the cryptocurrency investment conference jointly with WG1 meeting at Rennes School of business, April 2022 Transfer knowledge in terms of expertise...: Can I put a round table and a panel on crypto and DeFi at AFFI conference in May 2022, Saint Malo? Other : contribution to the network extension, mentioning our COST Actions in different meetings; joint supervision of a PhD student,
A14: 44749.087 | B14: elias.tsigaridas@inria.fr | C14: France | D14: A database which contains pre-ICO documentation and post-ICO performance (ROI and, A database which contains data on crowdfunding/P2P platform features useful for rating platform integrity and to predict fraud, Report on good examples and best practices for a transparent finance industry with guidelines to improve transparency, An internal database of collected (scraped) financial time series from exchanges and regional consolidation platforms optimised for accessibility to all partners, Key software (codes, packages) developed by each of the Working Groups in line with their objectives | E14: Anything else useful and related to the below topics, To develop blended approaches to evaluate innovative financial services and their providers, especially in the FinTech domain, building on Machine Learning methods, focussing on prediction (early warning) of operational fragility, fraudulent and illegal behaviour ranging from appropriation of loaned funds to money-laundering activities., The development of conceptual and methodological tools for establishing when blackbox models are admissible and, to the extent possible, making them more transparent and/or replacing them with interpretable and explainable models., Pruning and improvement of the vast array of performance attribution models by contributing to the development of methodologies for reducing the false discovery rate in financial research and applied financial investment management., Transfer knowledge in terms of expertise, scientific tools and human resources across the different disciplines and between academia and industry., Establish an inclusive community of researchers on methodological and technological themes in Machine Learning and Artificial Intelligence, to promote Early Career Investigators and increase their visibility., Maximize the job opportunities for PhD students and Early Career Investigators., Disseminate the results of the Action's activities to the scientific community, European institutions and to the general public., Significantly improve the gender equality in the fields of the Action. | F14: Yes | H14: Yes | J14: Yes | K14: No | L14: Yes | M14: 0 | N14: WG 1 | P14: Yes
A15: 44736.417 | B15: haerdle@hu-berlin.de | C15: Germany | D15: Anything else useful for the COST Action, not mentioned below, A database which contains pre-ICO documentation and post-ICO performance (ROI and, Discussion papers (DP) on the methodology for evaluating/rating ICOs and crowdfunding/P2P platforms and for detection/early warning about fraud/illegal behaviour with emphasis on the application of AI tools, A position paper and roadmap on mitigating risks connected with the increased use of digital assets, A discussion paper for possible approaches to building a statistically valid back-testing framework, Position papers, aimed at regulators and policy-makers, on methodology (with examples of formal criteria) for testing AI techniques in real-time, An internal database of collected (scraped) financial time series from exchanges and regional consolidation platforms optimised for accessibility to all partners, Methodological discussion papers on AI models to generate “failed trials” of investment product producers and on quantitative strategies with the usage of the promising field of network data analysis exchanges and regional consolidation platforms optimised for accessibility to all partners, Key software (codes, packages) developed by each of the Working Groups in line with their objectives, Handbook and/or wiki page describing potential approaches to tackle risk management issues related to blockchain assets and crowdfunding/P2P lending, An edited volume containing scientific achievements of the Action | E15: Anything else useful and related to the below topics, The development of conceptual and methodological tools for establishing when blackbox models are admissible and, to the extent possible, making them more transparent and/or replacing them with interpretable and explainable models., To receive input from regulators and practitioners' communities and to validate results with regard to increasing transparency of artificial intelligence applications., Pruning and improvement of the vast array of performance attribution models by contributing to the development of methodologies for reducing the false discovery rate in financial research and applied financial investment management., Disseminate to the public and share with regulators the results on investment product performance evaluation., Creation of the first European platform comparing the out-of-sample performance of banks' investment products, insurance-linked investment products and asset management products available to the general public., Create an excellent network of researchers in Europe with lasting collaboration beyond the lifetime of the Action., Bringing technological, quantitative and economic researchers together, to tackle future research that can only be done in an interdisciplinary setting, and getting actively involved in the blockchain and FinTech communities across Europe, to constantly monitor developments, get input and disseminate results., Transfer knowledge in terms of expertise, scientific tools and human resources across the different disciplines and between academia and industry., Overcome the siloing of research topics by country and achieve geographical and demographical diversity, with special attention to COST Inclusiveness Target countries., Maximize the job opportunities for PhD students and Early Career Investigators., Disseminate the results of the Action's activities to the scientific community, European institutions and to the general public., Significantly improve the gender equality in the fields of the Action. | F15: Yes | H15: Yes | J15: Yes | K15: Yes | L15: Yes | M15: 0 | N15: WG 1 | P15: Yes
A16: 44748.498 | B16: allapetukhina@icloud.com | C16: Germany | D16: Anything else useful for the COST Action, not mentioned below | E16: Create an excellent network of researchers in Europe with lasting collaboration beyond the lifetime of the Action., Bringing technological, quantitative and economic researchers together, to tackle future research that can only be done in an interdisciplinary setting, and getting actively involved in the blockchain and FinTech communities across Europe, to constantly monitor developments, get input and disseminate results., Bridging the gap between practitioners from the finance industry, academics and regulators by setting up a common knowledge exchange platform., Maximize the job opportunities for PhD students and Early Career Investigators., Significantly improve the gender equality in the fields of the Action. | F16: Yes | H16: No | J16: No | K16: Yes | L16: No | M16: 0 | N16: WG 1 | O16: Germany (Härdle)&Romania(D Pele, V Strat): Quantinar start - P2P knowledge platform supported by FinAI | P16: Yes
A17: 44729.578 | B17: veniarakelian@yahoo.com | C17: Greece | D17: A discussion paper for possible approaches to building a statistically valid back-testing framework, Report on good examples and best practices for a transparent finance industry with guidelines to improve transparency | E17: To develop blended approaches to evaluate innovative financial services and their providers, especially in the FinTech domain, building on Machine Learning methods, focussing on prediction (early warning) of operational fragility, fraudulent and illegal behaviour ranging from appropriation of loaned funds to money-laundering activities., The development of conceptual and methodological tools for establishing when blackbox models are admissible and, to the extent possible, making them more transparent and/or replacing them with interpretable and explainable models., To receive input from regulators and practitioners' communities and to validate results with regard to increasing transparency of artificial intelligence applications., Create an excellent network of researchers in Europe with lasting collaboration beyond the lifetime of the Action. | F17: Yes | G17: No | H17: Yes | I17: Yes | J17: Yes | K17: Yes | L17: No | M17: 0 | N17: WG 3
A18: 44749.723 | B18: tolis.chal@gmail.com | C18: Greece | D18: A position paper and roadmap on mitigating risks connected with the increased use of digital assets, Methodological discussion paper on the design of stress tests for the evaluation of AI and ML models under shifting financial conditions to improve the robustness of models | E18: Overcome the siloing of research topics by country and achieve geographical and demographical diversity, with special attention to COST Inclusiveness Target countries., Prepare competitive European researchers for a fruitful career in an international environment through intensive use of Short Term Scientific Missions (STSM) and joint educational programs with industrial partners., Maximize the job opportunities for PhD students and Early Career Investigators. | F18: No | H18: No | J18: No | K18: Yes | L18: No | M18: 0 | N18: WG 1, WG 3 | P18: No
A19: 44809.467 | B19: veniarakelian@yahoo.com | C19: Greece | D19: Discussion papers (DP) on the methodology for evaluating/rating ICOs and crowdfunding/P2P platforms and for detection/early warning about fraud/illegal behaviour with emphasis on the application of AI tools, Methodological discussion paper on the design of stress tests for the evaluation of AI and ML models under shifting financial conditions to improve the robustness of models, Key software (codes, packages) developed by each of the Working Groups in line with their objectives | E19: To develop blended approaches to evaluate innovative financial services and their providers, especially in the FinTech domain, building on Machine Learning methods, focussing on prediction (early warning) of operational fragility, fraudulent and illegal behaviour ranging from appropriation of loaned funds to money-laundering activities., The development of conceptual and methodological tools for establishing when blackbox models are admissible and, to the extent possible, making them more transparent and/or replacing them with interpretable and explainable models., To receive input from regulators and practitioners' communities and to validate results with regard to increasing transparency of artificial intelligence applications., Pruning and improvement of the vast array of performance attribution models by contributing to the development of methodologies for reducing the false discovery rate in financial research and applied financial investment management., Disseminate to the public and share with regulators the results on investment product performance evaluation., Create an excellent network of researchers in Europe with lasting collaboration beyond the lifetime of the Action., Bringing technological, quantitative and economic researchers together, to tackle future research that can only be done in an interdisciplinary setting, and getting actively involved in the blockchain and FinTech communities across Europe, to constantly monitor developments, get input and disseminate results., Bridging the gap between practitioners from the finance industry, academics and regulators by setting up a common knowledge exchange platform., Transfer knowledge in terms of expertise, scientific tools and human resources across the different disciplines and between academia and industry., Establish an inclusive community of researchers on methodological and technological themes in Machine Learning and Artificial Intelligence, to promote Early Career Investigators and increase their visibility., Overcome the siloing of research topics by country and achieve geographical and demographical diversity, with special attention to COST Inclusiveness Target countries., Prepare competitive European researchers for a fruitful career in an international environment through intensive use of Short Term Scientific Missions (STSM) and joint educational programs with industrial partners., Maximize the job opportunities for PhD students and Early Career Investigators., Disseminate the results of the Action's activities to the scientific community, European institutions and to the general public. | F19: Yes | H19: No | J19: Yes | K19: Yes | L19: Yes | M19: 0 | N19: WG 3 | O19: Close collaboration with Currency Research https://www.linkedin.com/company/currencyresearch/ | P19: Yes
A20: 44760.568 | B20: trimborn.econometrics@gmail.com | C20: Hong Kong | D20: Anything else useful for the COST Action, not mentioned below, Key software (codes, packages) developed by each of the Working Groups in line with their objectives | E20: Anything else useful and related to the below topics, To develop blended approaches to evaluate innovative financial services and their providers, especially in the FinTech domain, building on Machine Learning methods, focussing on prediction (early warning) of operational fragility, fraudulent and illegal behaviour ranging from appropriation of loaned funds to money-laundering activities., Create an excellent network of researchers in Europe with lasting collaboration beyond the lifetime of the Action. | F20: No | H20: No | J20: No | K20: No | L20: Yes | M20: 0 | N20: WG 1, WG 2, WG 3 | P20: No
A21: 44752.826 | B21: molnarba@inf.elte.hu | C21: Hungary | D21: Anything else useful for the COST Action, not mentioned below | E21: The development of conceptual and methodological tools for establishing when blackbox models are admissible and, to the extent possible, making them more transparent and/or replacing them with interpretable and explainable models., Bridging the gap between practitioners from the finance industry, academics and regulators by setting up a common knowledge exchange platform., Significantly improve the gender equality in the fields of the Action. | F21: Yes | H21: No | J21: Yes | K21: Yes | L21: Yes | M21: 0 | N21: WG 1, WG 2, WG 3 | P21: Yes
A22: 44796.434 | B22: molnarba@inf.elte.hu | C22: Hungary | D22: Anything else useful for the COST Action, not mentioned below | E22: To receive input from regulators and practitioners' communities and to validate results with regard to increasing transparency of artificial intelligence applications., Disseminate to the public and share with regulators the results on investment product performance evaluation., Transfer knowledge in terms of expertise, scientific tools and human resources across the different disciplines and between academia and industry., Establish an inclusive community of researchers on methodological and technological themes in Machine Learning and Artificial Intelligence, to promote Early Career Investigators and increase their visibility., Maximize the job opportunities for PhD students and Early Career Investigators., Disseminate the results of the Action's activities to the scientific community, European institutions and to the general public., Significantly improve the gender equality in the fields of the Action. | F22: Yes | H22: No | J22: Yes | K22: Yes | L22: Yes | M22: 0 | N22: WG 1, WG 2, WG 3 | P22: Yes
A23: 44737.731 | B23: rupelnargunam25@gmail.com | C23: India | D23: A discussion paper on market risk modeling, analysis and management, contributing to the methodological discussion section on risk measures and time series approaches used to obtain forecasts of risk measures. | E23: Anything else useful and related to the below topics | F23: Yes | H23: No | J23: No | K23: No | L23: No | M23: 0 | N23: WG 1 | O23: Presented research paper in Women in Fintech Conference organized by Fintech and Artificial Intelligence in Finance and European Cooperation in Science and Technology (COST), during 22nd - 23rd September 2021. | P23: No
A24: 44744.826 | B24: valerio.poti@ucd.ie | C24: Ireland | D24: A discussion paper for possible approaches to building a statistically valid back-testing framework, Methodological discussion paper on the design of stress tests for the evaluation of AI and ML models under shifting financial conditions to improve the robustness of models, Key software (codes, packages) developed by each of the Working Groups in line with their objectives | E24: To receive input from regulators and practitioners' communities and to validate results with regard to increasing transparency of artificial intelligence applications., Pruning and improvement of the vast array of performance attribution models by contributing to the development of methodologies for reducing the false discovery rate in financial research and applied financial investment management., Create an excellent network of researchers in Europe with lasting collaboration beyond the lifetime of the Action., Bringing technological, quantitative and economic researchers together, to tackle future research that can only be done in an interdisciplinary setting, and getting actively involved in the blockchain and FinTech communities across Europe, to constantly monitor developments, get input and disseminate results., Establish an inclusive community of researchers on methodological and technological themes in Machine Learning and Artificial Intelligence, to promote Early Career Investigators and increase their visibility., Disseminate the results of the Action's activities to the scientific community, European institutions and to the general public., Significantly improve the gender equality in the fields of the Action. | F24: Yes | H24: No | J24: Yes | K24: Yes | L24: No | M24: 0 | N24: WG 1 | P24: Yes
A25: 44754.633 | B25: vassilios.papavassiliou@ucd.ie | C25: Ireland | D25: A discussion paper on sovereign bond return predictability using machine learning methods | E25: Disseminate to the public and share with regulators the results on investment product performance evaluation., Disseminate the results of the Action's activities to the scientific community, European institutions and to the general public. | F25: Yes | H25: No | J25: No | K25: Yes | L25: No | M25: 0 | N25: WG 1, WG 3 | P25: No
A26: 44754.815 | B26: valerio.poti@ucd.ie | C26: Ireland | D26: Anything else useful for the COST Action, not mentioned below | E26: To develop blended approaches to evaluate innovative financial services and their providers, especially in the FinTech domain, building on Machine Learning methods, focussing on prediction (early warning) of operational fragility, fraudulent and illegal behaviour ranging from appropriation of loaned funds to money-laundering activities., Pruning and improvement of the vast array of performance attribution models by contributing to the development of methodologies for reducing the false discovery rate in financial research and applied financial investment management., Disseminate the results of the Action's activities to the scientific community, European institutions and to the general public., Significantly improve the gender equality in the fields of the Action. | F26: Yes | H26: Yes | J26: Yes | K26: Yes | L26: No | M26: 0 | N26: WG 1 | P26: Yes
A27: 44735.43 | B27: alessandra.tanda@unipv.it | C27: Italy | D27: Anything else useful for the COST Action, not mentioned below, An internal database of collected (scraped) financial time series from exchanges and regional consolidation platforms optimised for accessibility to all partners, Strategy to engage stakeholders in the Action (including revisions in month 24 and 36) | E27: Disseminate to the public and share with regulators the results on investment product performance evaluation., Create an excellent network of researchers in Europe with lasting collaboration beyond the lifetime of the Action., Transfer knowledge in terms of expertise, scientific tools and human resources across the different disciplines and between academia and industry., Maximize the job opportunities for PhD students and Early Career Investigators., Significantly improve the gender equality in the fields of the Action. | F27: No | H27: No | I27: Yes | J27: Yes | K27: Yes | L27: No | M27: 0 | N27: WG 1, WG 3
A28: 44735.451 | B28: daniele.marazzina@polimi.it | C28: Italy | D28: Anything else useful for the COST Action, not mentioned below, A database which contains pre-ICO documentation and post-ICO performance (ROI and, A database which contains data on crowdfunding/P2P platform features useful for rating platform integrity and to predict fraud | E28: Create an excellent network of researchers in Europe with lasting collaboration beyond the lifetime of the Action., Transfer knowledge in terms of expertise, scientific tools and human resources across the different disciplines and between academia and industry., Disseminate the results of the Action's activities to the scientific community, European institutions and to the general public., Significantly improve the gender equality in the fields of the Action. | F28: No | H28: Yes | I28: Yes | J28: No | K28: Yes | L28: No | M28: 0 | N28: WG 1, WG 2, WG 3
A29: 44741.569 | B29: daniele.marazzina@polimi.it | C29: Italy | D29: Anything else useful for the COST Action, not mentioned below, A database which contains pre-ICO documentation and post-ICO performance (ROI and, A database which contains data on crowdfunding/P2P platform features useful for rating platform integrity and to predict fraud | E29: Anything else useful and related to the below topics, Create an excellent network of researchers in Europe with lasting collaboration beyond the lifetime of the Action., Bridging the gap between practitioners from the finance industry, academics and regulators by setting up a common knowledge exchange platform., Maximize the job opportunities for PhD students and Early Career Investigators., Disseminate the results of the Action's activities to the scientific community, European institutions and to the general public., Significantly improve the gender equality in the fields of the Action. | F29: Yes | H29: Yes | J29: No | K29: Yes | L29: Yes | M29: 0 | N29: WG 1, WG 2, WG 3 | P29: No
A30: 44749.629 | B30: maria.iannario@unina.it | C30: Italy | D30: A discussion paper for possible approaches to building a statistically valid back-testing framework | E30: Disseminate to the public and share with regulators the results on investment product performance evaluation., Create an excellent network of researchers in Europe with lasting collaboration beyond the lifetime of the Action., Bridging the gap between practitioners from the finance industry, academics and regulators by setting up a common knowledge exchange platform., Transfer knowledge in terms of expertise, scientific tools and human resources across the different disciplines and between academia and industry., Overcome the siloing of research topics by country and achieve geographical and demographical diversity, with special attention to COST Inclusiveness Target countries., Maximize the job opportunities for PhD students and Early Career Investigators., Disseminate the results of the Action's activities to the scientific community, European institutions and to the general public., Significantly improve the gender equality in the fields of the Action. | F30: Yes | H30: Yes | J30: Yes | K30: Yes | L30: No | M30: 0 | N30: WG 2 | O30: Women in Fintech Datathon is a data mining event (data analysis) organized by the Women in Fintech Conference Committee represented by several researchers of the Cost Action FinAI CA19130, University of Tirana and University of Naples Federico II (for more details, please see the following link: https://fin-ai.eu/datathon/). It aims to promote the analysis of data on the goals of the Women in Fintech II Conference, and more general in the field of the FinAI Action. Among the main topics to be developed by means of (open access and real) data analysis: Gender diversity in Fintech corporate world, Fintech gender diversity in different EU countries, Gender pay gap in Fintech roles. It involves teams from every European country. The team should be made up of maximum 5 members (male or female), which can be enrolled in bachelor, master or PhD programmes. High-performing teams are composed of individuals with specialized expertise and complementary skills. It creates cooperation and improves qualification of next generation. | P30: Yes
A31: 44738.512 | B31: rr@lu.lv | C31: Latvia | D31: No | E31: Create an excellent network of researchers in Europe with lasting collaboration beyond the lifetime of the Action., Bringing technological, quantitative and economic researchers together, to tackle future research that can only be done in an interdisciplinary setting, and getting actively involved in the blockchain and FinTech communities across Europe, to constantly monitor developments, get input and disseminate results., Transfer knowledge in terms of expertise, scientific tools and human resources across the different disciplines and between academia and industry., Prepare competitive European researchers for a fruitful career in an international environment through intensive use of Short Term Scientific Missions (STSM) and joint educational programs with industrial partners., Disseminate the results of the Action's activities to the scientific community, European institutions and to the general public. | F31: No | H31: No | J31: Yes | K31: Yes | L31: No | M31: 0 | N31: WG 1 | P31: No
A32: 44729.577 | B32: audkaba@ktu.lt | C32: Lithuania | D32: Methodological discussion papers on AI models to generate “failed trials” of investment product producers and on quantitative strategies with the usage of the promising field of network data analysis exchanges and regional consolidation platforms optimised for accessibility to all partners | E32: Pruning and improvement of the vast array of performance attribution models by contributing to the development of methodologies for reducing the false discovery rate in financial research and applied financial investment management., Disseminate to the public and share with regulators the results on investment product performance evaluation., Disseminate the results of the Action's activities to the scientific community, European institutions and to the general public. | F32: Yes | G32: Yes | H32: No | I32: Yes | J32: Yes | K32: No | L32: Yes | M32: 0 | N32: WG 2
A33: 44735.45 | B33: kristina.sutiene@ktu.lt | C33: Lithuania | D33: Report on good examples and best practices for a transparent finance industry with guidelines to improve transparency | E33: Disseminate to the public and share with regulators the results on investment product performance evaluation., Disseminate the results of the Action's activities to the scientific community, European institutions and to the general public. | F33: Yes | G33: No | H33: No | I33: Yes | J33: Yes | K33: No | L33: No | M33: 0 | N33: WG 2 | O33: A reviewer in TINFIN conference https://sites.google.com/net.efzg.hr/tinfinconference/home/programme-committee | P33: Yes
A34: 44753.588 | B34: audkaba@ktu.lt | C34: Lithuania | D34: Methodological discussion paper on the design of stress tests for the evaluation of AI and ML models under shifting financial conditions to improve the robustness of models, Report on good examples and best practices for a transparent finance industry with guidelines to improve transparency | E34: The development of conceptual and methodological tools for establishing when blackbox models are admissible and, to the extent possible, making them more transparent and/or replacing them with interpretable and explainable models., Disseminate to the public and share with regulators the results on investment product performance evaluation., Create an excellent network of researchers in Europe with lasting collaboration beyond the lifetime of the Action., Bridging the gap between practitioners from the finance industry, academics and regulators by setting up a common knowledge exchange platform., Transfer knowledge in terms of expertise, scientific tools and human resources across the different disciplines and between academia and industry., Prepare competitive European researchers for a fruitful career in an international environment through intensive use of Short Term Scientific Missions (STSM) and joint educational programs with industrial partners., Disseminate the results of the Action's activities to the scientific community, European institutions and to the general public. | F34: Yes | H34: Yes | J34: Yes | K34: Yes | L34: Yes | M34: 0 | N34: WG 2 | O34: Network expansion performed | P34: Yes
A35: 44754.545 | B35: angele@acrosslimits.com | C35: Malta | D35: Anything else useful for the COST Action, not mentioned below | E35: Create an excellent network of researchers in Europe with lasting collaboration beyond the lifetime of the Action., Bringing technological, quantitative and economic researchers together, to tackle future research that can only be done in an interdisciplinary setting, and getting actively involved in the blockchain and FinTech communities across Europe, to constantly monitor developments, get input and disseminate results. | F35: No | H35: No | J35: No | K35: Yes | L35: Yes | M35: 0 | N35: WG 2 | O35: We are trying to form consortia for various European proposals for funding and involving other partners of the Cost Action | P35: Yes
A36: 44757.638 | B36: dbevan@stmartins.edu | C36: Malta | D36: Anything else useful for the COST Action, not mentioned below | E36: To develop blended approaches to evaluate innovative financial services and their providers, especially in the FinTech domain, building on Machine Learning methods, focussing on prediction (early warning) of operational fragility, fraudulent and illegal behaviour ranging from appropriation of loaned funds to money-laundering activities., The development of conceptual and methodological tools for establishing when blackbox models are admissible and, to the extent possible, making them more transparent and/or replacing them with interpretable and explainable models., Create an excellent network of researchers in Europe with lasting collaboration beyond the lifetime of the Action., Transfer knowledge in terms of expertise, scientific tools and human resources across the different disciplines and between academia and industry., Overcome the siloing of research topics by country and achieve geographical and demographical diversity, with special attention to COST Inclusiveness Target countries., Disseminate the results of the Action's activities to the scientific community, European institutions and to the general public. | F36: No | H36: Yes | J36: Yes | K36: Yes | L36: No | M36: 0 | N36: WG 1, WG 2, WG 3 | O36: 1. Significant contribution in 2022 through publication and conference presentations (ISBEE July 2022) to making academic / professional business-ethics community aware of prevalent current ethical attitudes (and discourses/contexts) operating in the Fintech community with particular reference to (i) the potentially dysfunctional application of 'black box' amorality and as contrasted with the complexity (ii) 'all tech is human'. 2. Acting as deputy network co-ordinator to support the continuing energy in the Action and both its longevity and interdisciplinary interactions, by improving professional and scholarly understanding and communication of AI ethics. | P36: Yes
A37: 44732.91 | B37: lameski@finki.ukim.mk | C37: N. Macedonia | D37: Discussion papers (DP) on the methodology for evaluating/rating ICOs and crowdfunding/P2P platforms and for detection/early warning about fraud/illegal behaviour with emphasis on the application of AI tools, A position paper and roadmap on mitigating risks connected with the increased use of digital assets, A discussion paper for possible approaches to building a statistically valid back-testing framework, Position papers, aimed at regulators and policy-makers, on methodology (with examples of formal criteria) for testing AI techniques in real-time, Report on good examples and best practices for a transparent finance industry with guidelines to improve transparency | E37: The development of conceptual and methodological tools for establishing when blackbox models are admissible and, to the extent possible, making them more transparent and/or replacing them with interpretable and explainable models., To receive input from regulators and practitioners' communities and to validate results with regard to increasing transparency of artificial intelligence applications., Disseminate to the public and share with regulators the results on investment product performance evaluation., Create an excellent network of researchers in Europe with lasting collaboration beyond the lifetime of the Action., Bringing technological, quantitative and economic researchers together, to tackle future research that can only be done in an interdisciplinary setting, and getting actively involved in the blockchain and FinTech communities across Europe, to constantly monitor developments, get input and disseminate results., Establish an inclusive community of researchers on methodological and technological themes in Machine Learning and Artificial Intelligence, to promote Early Career Investigators and increase their visibility., Disseminate the results of the Action's activities to the scientific community, European institutions and to the general public. | F37: No | G37: No | H37: Yes | I37: Yes | J37: Yes | K37: Yes | L37: No | M37: 0 | N37: WG 2
A38: 44748.568 | B38: r.j.kleverlaan@uu.nl | C38: Netherlands | D38: Anything else useful for the COST Action, not mentioned below, Strategy to engage stakeholders in the Action (including revisions in month 24 and 36) | E38: Create an excellent network of researchers in Europe with lasting collaboration beyond the lifetime of the Action., Bringing technological, quantitative and economic researchers together, to tackle future research that can only be done in an interdisciplinary setting, and getting actively involved in the blockchain and FinTech communities across Europe, to constantly monitor developments, get input and disseminate results., Bridging the gap between practitioners from the finance industry, academics and regulators by setting up a common knowledge exchange platform., Transfer knowledge in terms of expertise, scientific tools and human resources across the different disciplines and between academia and industry., Overcome the siloing of research topics by country and achieve geographical and demographical diversity, with special attention to COST Inclusiveness Target countries., Disseminate the results of the Action's activities to the scientific community, European institutions and to the general public. | F38: No | H38: No | J38: No | K38: Yes | L38: Yes | M38: 0 | N38: WG 1 | P38: Yes
A39: 44741.902 | B39: olivijaf@gmail.com | C39: North Macedonia | D39: Anything else useful for the COST Action, not mentioned below, Strategy to engage stakeholders in the Action (including revisions in month 24 and 36) | E39: To receive input from regulators and practitioners' communities and to validate results with regard to increasing transparency of artificial intelligence applications., Create an excellent network of researchers in Europe with lasting collaboration beyond the lifetime of the Action., Bridging the gap between practitioners from the finance industry, academics and regulators by setting up a common knowledge exchange platform., Establish an inclusive community of researchers on methodological and technological themes in Machine Learning and Artificial Intelligence, to promote Early Career Investigators and increase their visibility., Overcome the siloing of research topics by country and achieve geographical and demographical diversity, with special attention to COST Inclusiveness Target countries., Prepare competitive European researchers for a fruitful career in an international environment through intensive use of Short Term Scientific Missions (STSM) and joint educational programs with industrial partners., Maximize the job opportunities for PhD students and Early Career Investigators., Disseminate the results of the Action's activities to the scientific community, European institutions and to the general public., Significantly improve the gender equality in the fields of the Action. | F39: No | H39: No | J39: Yes | K39: Yes | L39: No | M39: 0 | N39: WG 1, WG 2, WG 3 | P39: Yes
A40: 44743.708 | B40: rita.pimentel@ntnu.no | C40: Norway | D40: Position papers, aimed at regulators and policy-makers, on methodology (with examples of formal criteria) for testing AI techniques in real-time | E40: Create an excellent network of researchers in Europe with lasting collaboration beyond the lifetime of the Action., Significantly improve the gender equality in the fields of the Action. | F40: No | H40: Yes | J40: Yes | K40: No | L40: No | M40: 0 | N40: WG 2 | P40: No
A41: 44752.961 | B41: kbolesta96@gmail.com | C41: Poland | D41: Anything else useful for the COST Action, not mentioned below, Methodological discussion papers on AI models to generate “failed trials” of investment product producers and on quantitative strategies with the usage of the promising field of network data analysis exchanges and regional consolidation platforms optimised for accessibility to all partners, Strategy to engage stakeholders in the Action (including revisions in month 24 and 36) | E41: To develop blended approaches to evaluate innovative financial services and their providers, especially in the FinTech domain, building on Machine Learning methods, focussing on prediction (early warning) of operational fragility, fraudulent and illegal behaviour ranging from appropriation of loaned funds to money-laundering activities., To receive input from regulators and practitioners' communities and to validate results with regard to increasing transparency of artificial intelligence applications., Significantly improve the gender equality in the fields of the Action. | F41: No | H41: No | J41: Yes | K41: Yes | L41: Yes | M41: 0 | N41: WG 1, WG 3 | P41: Yes
A42: 44757.787 | B42: pwojcik@wne.uw.edu.pl | C42: Poland | D42: Anything else useful for the COST Action, not mentioned below, Discussion papers (DP) on the methodology for evaluating/rating ICOs and crowdfunding/P2P platforms and for detection/early warning about fraud/illegal behaviour with emphasis on the application of AI tools | E42: The development of conceptual and methodological tools for establishing when blackbox models are admissible and, to the extent possible, making them more transparent and/or replacing them with interpretable and explainable models., Transfer knowledge in terms of expertise, scientific tools and human resources across the different disciplines and between academia and industry., Disseminate the results of the Action's activities to the scientific community, European institutions and to the general public., Significantly improve the gender equality in the fields of the Action. | F42: No | H42: No | J42: No | K42: Yes | L42: No | M42: 0 | N42: WG 2, WG 3 | P42: Yes
A43: 44733.712 | B43: catarina@dei.uc.pt | C43: Portugal | D43: No | E43: To develop blended approaches to evaluate innovative financial services and their providers, especially in the FinTech domain, building on Machine Learning methods, focussing on prediction (early warning) of operational fragility, fraudulent and illegal behaviour ranging from appropriation of loaned funds to money-laundering activities., Bringing technological, quantitative and economic researchers together, to tackle future research that can only be done in an interdisciplinary setting, and getting actively involved in the blockchain and FinTech communities across Europe, to constantly monitor developments, get input and disseminate results., Disseminate the results of the Action's activities to the scientific community, European institutions and to the general public. | F43: Yes | G43: No | H43: No | I43: Yes | J43: Yes | K43: Yes | L43: No | M43: 0 | N43: WG 1, WG 2
A44: 44743.78 | B44: catarina@dei.uc.pt | C44: Portugal | D44: No | E44: Create an excellent network of researchers in Europe with lasting collaboration beyond the lifetime of the Action., Disseminate the results of the Action's activities to the scientific community, European institutions and to the general public. | F44: Yes | H44: Yes | J44: Yes | K44: Yes | L44: No | M44: 0 | N44: WG 1, WG 2 | P44: Yes
A45: 44749.674 | B45: albulena.shala@uni-pr.edu | C45: Republic of Kosovo | D45: Anything else useful for the COST Action, not mentioned below | E45: Create an excellent network of researchers in Europe with lasting collaboration beyond the lifetime of the Action., Bringing technological, quantitative and economic researchers together, to tackle future research that can only be done in an interdisciplinary setting, and getting actively involved in the blockchain and FinTech communities across Europe, to constantly monitor developments, get input and disseminate results., Bridging the gap between practitioners from the finance industry, academics and regulators by setting up a common knowledge exchange platform., Transfer knowledge in terms of expertise, scientific tools and human resources across the different disciplines and between academia and industry., Prepare competitive European researchers for a fruitful career in an international environment through intensive use of Short Term Scientific Missions (STSM) and joint educational programs with industrial partners., Significantly improve the gender equality in the fields of the Action. | F45: No | H45: Yes | J45: Yes | K45: Yes | L45: Yes | M45: 0 | N45: WG 1, WG 2, WG 3 | O45: Thank you for this excellent opportunity. We have created new opportunities for collaboration with colleagues from other countries, new knowledge and practices. I hope that Kosovo will be a part of COST action one day. | P45: Yes
A46: 44740.832 | B46: coita.iflorina@gmail.com | C46: Romania | D46: Discussion papers (DP) on the methodology for evaluating/rating ICOs and crowdfunding/P2P platforms and for detection/early warning about fraud/illegal behaviour with emphasis on the application of AI tools, An internal database of collected (scraped) financial time series from exchanges and regional consolidation platforms optimised for accessibility to all partners, Key software (codes, packages) developed by each of the Working Groups in line with their objectives | E46: To develop blended approaches to evaluate innovative financial services and their providers, especially in the FinTech domain, building on Machine Learning methods, focussing on prediction (early warning) of operational fragility, fraudulent and illegal behaviour ranging from appropriation of loaned funds to money-laundering activities., To receive input from regulators and practitioners' communities and to validate results with regard to increasing transparency of artificial intelligence applications., Bringing technological, quantitative and economic researchers together, to tackle future research that can only be done in an interdisciplinary setting, and getting actively involved in the blockchain and FinTech communities across Europe, to constantly monitor developments, get input and disseminate results., Bridging the gap between practitioners from the finance industry, academics and regulators by setting up a common knowledge exchange platform., Transfer knowledge in terms of expertise, scientific tools and human resources across the different disciplines and between academia and industry., Establish an inclusive community of researchers on methodological and technological themes in Machine Learning and Artificial Intelligence, to promote Early Career Investigators and increase their visibility., Disseminate the results of the Action's activities to the scientific community, European institutions and to the general public., Significantly improve the gender equality in the fields of the Action. | F46: No | H46: Yes | J46: Yes | K46: Yes | L46: Yes | M46: 0 | N46: WG 1, WG 2 | O46: writing joint papers and European funded projects | P46: Yes
A47: 44741.823 | B47: stefana.cioban@ubbcluj.ro | C47: Romania | D47: Key software (codes, packages) developed by each of the Working Groups in line with their objectives | E47: Create an excellent network of researchers in Europe with lasting collaboration beyond the lifetime of the Action., Establish an inclusive community of researchers on methodological and technological themes in Machine Learning and Artificial Intelligence, to promote Early Career Investigators and increase their visibility., Overcome the siloing of research topics by country and achieve geographical and demographical diversity, with special attention to COST Inclusiveness Target countries., Maximize the job opportunities for PhD students and Early Career Investigators., Disseminate the results of the Action's activities to the scientific community, European institutions and to the general public., Significantly improve the gender equality in the fields of the Action. | F47: Yes | H47: Yes | J47: No | K47: Yes | L47: No | M47: 0 | N47: WG 1, WG 2 | O47: So far, I have contributed to the literature review on sentiment analysis in finance within the Working Group 2, with focus on the Romanian and English languages. Also, I have co-authored the paper "Is Trust a Valid Indicator of Tax Compliance Behaviour? A Study on Taxpayers’ Public Perception Using Sentiment Analysis Tool" which was presented in the 4th International Conference on Economics and Social Sciences and published in the corresponding Conference Proceedings volume. | P47: Yes
A48: 44742.392 | B48: codruta.mare@gmail.com | C48: Romania | D48: Discussion papers (DP) on the methodology for evaluating/rating ICOs and crowdfunding/P2P platforms and for detection/early warning about fraud/illegal behaviour with emphasis on the application of AI tools, Report on good examples and best practices for a transparent finance industry with guidelines to improve transparency, Four annual reports (for lay audience) distributed via local and national media, Key software (codes, packages) developed by each of the Working Groups in line with their objectives, Strategy to engage stakeholders in the Action (including revisions in month 24 and 36) | E48: To receive input from regulators and practitioners' communities and to validate results with regard to increasing transparency of artificial intelligence applications., Disseminate to the public and share with regulators the results on investment product performance evaluation., Create an excellent network of researchers in Europe with lasting collaboration beyond the lifetime of the Action., Bringing technological, quantitative and economic researchers together, to tackle future research that can only be done in an interdisciplinary setting, and getting actively involved in the blockchain and FinTech communities across Europe, to constantly monitor developments, get input and disseminate results., Bridging the gap between practitioners from the finance industry, academics and regulators by setting up a common knowledge exchange platform., Transfer knowledge in terms of expertise, scientific tools and human resources across the different disciplines and between academia and industry., Establish an inclusive community of researchers on methodological and technological themes in Machine Learning and Artificial Intelligence, to promote Early Career Investigators and increase their visibility., Overcome the siloing of research topics by country and achieve geographical and demographical diversity, with special attention to COST Inclusiveness Target countries., Prepare competitive European researchers for a fruitful career in an international environment through intensive use of Short Term Scientific Missions (STSM) and joint educational programs with industrial partners., Maximize the job opportunities for PhD students and Early Career Investigators., Disseminate the results of the Action's activities to the scientific community, European institutions and to the general public., Significantly improve the gender equality in the fields of the Action. | F48: Yes | G48: Yes, applications for joint research with FinTech sector | H48: No | I48: First national report on the Romanian FinTech sector | J48: Yes | K48: Yes | L48: No | M48: 0 | N48: WG 1, WG 2 | O48: Cooperation with stakeholders for research applications, First Romanian FinTech Sector report, adding new members to the Action, co-authored papers, supervision of deliverables | P48: No
A49: 44752.786 | B49: danpele@ase.ro | C49: Romania | D49: Anything else useful for the COST Action, not mentioned below | E49: The development of conceptual and methodological tools for establishing when blackbox models are admissible and, to the extent possible, making them more transparent and/or replacing them with interpretable and explainable models., To receive input from regulators and practitioners' communities and to validate results with regard to increasing transparency of artificial intelligence applications., Disseminate to the public and share with regulators the results on investment product performance evaluation., Create an excellent network of researchers in Europe with lasting collaboration beyond the lifetime of the Action., Transfer knowledge in terms of expertise, scientific tools and human resources across the different disciplines and between academia and industry., Establish an inclusive community of researchers on methodological and technological themes in Machine Learning and Artificial Intelligence, to promote Early Career Investigators and increase their visibility., Disseminate the results of the Action's activities to the scientific community, European institutions and to the general public. | F49: Yes | H49: Yes | J49: Yes | K49: Yes | L49: No | M49: 0 | N49: WG 1, WG 2, WG 3 | P49: Yes
A50: 44753.437 | B50: ciprian.sipos@e-uvt.ro | C50: Romania | D50: Anything else useful for the COST Action, not mentioned below, A database which contains pre-ICO documentation and post-ICO performance (ROI and, A database which contains data on crowdfunding/P2P platform features useful for rating platform integrity and to predict fraud, Discussion papers (DP) on the methodology for evaluating/rating ICOs and crowdfunding/P2P platforms and for detection/early warning about fraud/illegal behaviour with emphasis on the application of AI tools, A position paper and roadmap on mitigating risks connected with the increased use of digital assets, A discussion paper for possible approaches to building a statistically valid back-testing framework, Methodological discussion paper on the design of stress tests for the evaluation of AI and ML models under shifting financial conditions to improve the robustness of models, Position papers, aimed at regulators and policy-makers, on methodology (with examples of formal criteria) for testing AI techniques in real-time, Report on good examples and best practices for a transparent finance industry with guidelines to improve transparency, An internal database of collected (scraped) financial time series from exchanges and regional consolidation platforms optimised for accessibility to all partners, Methodological discussion papers on AI models to generate “failed trials” of investment product producers and on quantitative strategies with the usage of the promising field of network data analysis exchanges and regional consolidation platforms optimised for accessibility to all partners, Four annual reports (for lay audience) distributed via local and national media, Key software (codes, packages) developed by each of the Working Groups in line with their objectives, Handbook and/or wiki page describing potential approaches to tackle risk management issues related to blockchain assets and crowdfunding/P2P lending, An edited volume containing scientific achievements of the Action, Strategy to engage stakeholders in the Action (including revisions in month 24 and 36) | E50: Anything else useful and related to the below topics, To develop blended approaches to evaluate innovative financial services and their providers, especially in the FinTech domain, building on Machine Learning methods, focussing on prediction (early warning) of operational fragility, fraudulent and illegal behaviour ranging from appropriation of loaned funds to money-laundering activities., The development of conceptual and methodological tools for establishing when blackbox models are admissible and, to the extent possible, making them more transparent and/or replacing them with interpretable and explainable models., To receive input from regulators and practitioners' communities and to validate results with regard to increasing transparency of artificial intelligence applications., Pruning and improvement of the vast array of performance attribution models by contributing to the development of methodologies for reducing the false discovery rate in financial research and applied financial investment management., Disseminate to the public and share with regulators the results on investment product performance evaluation., Creation of the first European platform comparing the out-of-sample performance of banks' investment products, insurance-linked investment products and asset management products available to the general public., Create an excellent network of researchers in Europe with lasting collaboration beyond the lifetime of the Action., Bringing technological, quantitative and economic researchers together, to tackle future research that can only be done in an interdisciplinary setting, and getting actively involved in the blockchain and FinTech communities across Europe, to constantly monitor developments, get input and disseminate results., Bridging the gap between practitioners from the finance industry, academics and regulators by setting up a common knowledge exchange platform., Transfer knowledge in terms of expertise, scientific tools and human resources across the different disciplines and between academia and industry., Establish an inclusive community of researchers on methodological and technological themes in Machine Learning and Artificial Intelligence, to promote Early Career Investigators and increase their visibility., Overcome the siloing of research topics by country and achieve geographical and demographical diversity, with special attention to COST Inclusiveness Target countries., Prepare competitive European researchers for a fruitful career in an international environment through intensive use of Short Term Scientific Missions (STSM) and joint educational programs with industrial partners., Maximize the job opportunities for PhD students and Early Career Investigators., Disseminate the results of the Action's activities to the scientific community, European institutions and to the general public., Significantly improve the gender equality in the fields of the Action. | F50: Yes | H50: Yes | J50: Yes | K50: Yes | L50: Yes | M50: 0 | N50: WG 2 | P50: Yes
A51: 44796.411 | B51: ciprian.sipos@e-uvt.ro | C51: Romania | D51: Anything else useful for the COST Action, not mentioned below, A database which contains pre-ICO documentation and post-ICO performance (ROI and, A database which contains data on crowdfunding/P2P platform features useful for rating platform integrity and to predict fraud, Discussion papers (DP) on the methodology for evaluating/rating ICOs and crowdfunding/P2P platforms and for detection/early warning about fraud/illegal behaviour with emphasis on the application of AI tools, A position paper and roadmap on mitigating risks connected with the increased use of digital assets, A discussion paper for possible approaches to building a statistically valid back-testing framework, Methodological discussion paper on the design of stress tests for the evaluation of AI and ML models under shifting financial conditions to improve the robustness of models, Position papers, aimed at regulators and policy-makers, on methodology (with examples of formal criteria) for testing AI techniques in real-time, Report on good examples and best practices for a transparent finance industry with guidelines to improve transparency, An internal database of collected (scraped) financial time series from exchanges and regional consolidation platforms optimised for accessibility to all partners, Methodological discussion papers on AI models to generate “failed trials” of investment product producers and on quantitative strategies with the usage of the promising field of network data analysis exchanges and regional consolidation platforms optimised for accessibility to all partners, Four annual reports (for lay audience) distributed via local and national media, Key software (codes, packages) developed by each of the Working Groups in line with their objectives, Handbook and/or wiki page describing potential approaches to tackle risk management issues related to blockchain assets and crowdfunding/P2P lending, An edited volume containing scientific achievements of the Action, Strategy to engage stakeholders in the Action (including revisions in month 24 and 36) | E51: Anything else useful and related to the below topics, To develop blended approaches to evaluate innovative financial services and their providers, especially in the FinTech domain, building on Machine Learning methods, focussing on prediction (early warning) of operational fragility, fraudulent and illegal behaviour ranging from appropriation of loaned funds to money-laundering activities., The development of conceptual and methodological tools for establishing when blackbox models are admissible and, to the extent possible, making them more transparent and/or replacing them with interpretable and explainable models., To receive input from regulators and practitioners' communities and to validate results with regard to increasing transparency of artificial intelligence applications., Pruning and improvement of the vast array of performance attribution models by contributing to the development of methodologies for reducing the false discovery rate in financial research and applied financial investment management., Disseminate to the public and share with regulators the results on investment product performance evaluation., Creation of the first European platform comparing the out-of-sample performance of banks' investment products, insurance-linked investment products and asset management products available to the general public., Create an excellent network of researchers in Europe with lasting collaboration beyond the lifetime of the Action., Bringing technological, quantitative and economic researchers together, to tackle future research that can only be done in an interdisciplinary setting, and getting actively involved in the blockchain and FinTech communities across Europe, to constantly monitor developments, get input and disseminate results., Bridging the gap between practitioners from the finance industry, academics and regulators by setting up a common knowledge exchange platform., Transfer knowledge in terms of expertise, scientific tools and human resources across the different disciplines and between academia and industry., Establish an inclusive community of researchers on methodological and technological themes in Machine Learning and Artificial Intelligence, to promote Early Career Investigators and increase their visibility., Overcome the siloing of research topics by country and achieve geographical and demographical diversity, with special attention to COST Inclusiveness Target countries., Prepare competitive European researchers for a fruitful career in an international environment through intensive use of Short Term Scientific Missions (STSM) and joint educational programs with industrial partners., Maximize the job opportunities for PhD students and Early Career Investigators., Disseminate the results of the Action's activities to the scientific community, European institutions and to the general public., Significantly improve the gender equality in the fields of the Action. | F51: Yes | H51: Yes | J51: Yes | K51: Yes | L51: Yes | M51: 0 | N51: WG 2 | P51: Yes
A52: 44806.583 | B52: coita.iflorina@gmail.com | C52: Romania | D52: A database which contains data on crowdfunding/P2P platform features useful for rating platform integrity and to predict fraud, Discussion papers (DP) on the methodology for evaluating/rating ICOs and crowdfunding/P2P platforms and for detection/early warning about fraud/illegal behaviour with emphasis on the application of AI tools, Report on good examples and best practices for a transparent finance industry with guidelines to improve transparency, Key software (codes, packages) developed by each of the Working Groups in line with their objectives, Strategy to engage stakeholders in the Action (including revisions in month 24 and 36) | E52: To develop blended approaches to evaluate innovative financial services and their providers, especially in the FinTech domain, building on Machine Learning methods, focussing on prediction (early warning) of operational fragility, fraudulent and illegal behaviour ranging from appropriation of loaned funds to money-laundering activities., The development of conceptual and methodological tools for establishing when blackbox models are admissible and, to the extent possible, making them more transparent and/or replacing them with interpretable and explainable models., To receive input from regulators and practitioners' communities and to validate results with regard to increasing transparency of artificial intelligence applications., Create an excellent network of researchers in Europe with lasting collaboration beyond the lifetime of the Action., Bringing technological, quantitative and economic researchers together, to tackle future research that can only be done in an interdisciplinary setting, and getting actively involved in the blockchain and FinTech communities across Europe, to constantly monitor developments, get input and disseminate results., Transfer knowledge in terms of expertise, scientific tools and human resources across the different disciplines and between academia and industry., Overcome the siloing of research topics by country and achieve geographical and demographical diversity, with special attention to COST Inclusiveness Target countries., Maximize the job opportunities for PhD students and Early Career Investigators., Disseminate the results of the Action's activities to the scientific community, European institutions and to the general public., Significantly improve the gender equality in the fields of the Action. | F52: Yes | H52: Yes | J52: Yes | K52: Yes | L52: No | M52: 0 | N52: WG 1, WG 2 | O52: Cooperation with Finech companies on developing AI tools for fraud detection | P52: Yes
A53: 44736.338 | B53: miljan.vucetic@vlatacom.com | C53: Serbia | D53: Methodological discussion paper on the design of stress tests for the evaluation of AI and ML models under shifting financial conditions to improve the robustness of models, Methodological discussion papers on AI models to generate “failed trials” of investment product producers and on quantitative strategies with the usage of the promising field of network data analysis exchanges and regional consolidation platforms optimised for accessibility to all partners, Key software (codes, packages) developed by each of the Working Groups in line with their objectives | E53: To develop blended approaches to evaluate innovative financial services and their providers, especially in the FinTech domain, building on Machine Learning methods, focussing on prediction (early warning) of operational fragility, fraudulent and illegal behaviour ranging from appropriation of loaned funds to money-laundering activities. | F53: Yes | H53: Yes | J53: Yes | K53: No | L53: No | M53: 0 | N53: WG 2 | P53: Yes
A54: 44736.396 | B54: denis.trcek@guest.arnes.si | C54: Slovenia | D54: No | E54: Anything else useful and related to the below topics, The development of conceptual and methodological tools for establishing when blackbox models are admissible and, to the extent possible, making them more transparent and/or replacing them with interpretable and explainable models. | F54: No | H54: No | J54: No | K54: No | L54: No | M54: 0 | N54: WG 1, WG 3 | O54: Thank you for all the excellent coordiantion of this large network. | P54: Yes
A55: 44743.302 | B55: saso.karakatic@um.si | C55: Slovenia | D55: Report on good examples and best practices for a transparent finance industry with guidelines to improve transparency | E55: The development of conceptual and methodological tools for establishing when blackbox models are admissible and, to the extent possible, making them more transparent and/or replacing them with interpretable and explainable models., Significantly improve the gender equality in the fields of the Action. | F55: No | H55: No | J55: No | K55: No | L55: No | M55: 0 | N55: WG 2 | P55: No
A56: 44753.593 | B56: javier.arroyo@fdi.ucm.es | C56: Spain | D56: A discussion paper for possible approaches to building a statistically valid back-testing framework | E56: No, The development of conceptual and methodological tools for establishing when blackbox models are admissible and, to the extent possible, making them more transparent and/or replacing them with interpretable and explainable models., Establish an inclusive community of researchers on methodological and technological themes in Machine Learning and Artificial Intelligence, to promote Early Career Investigators and increase their visibility. | F56: Yes | H56: No | J56: No | K56: No | L56: No | M56: 0 | N56: WG 2 | P56: No
A57: 44727.732 | B57: brankahm@gmail.com | C57: Switzerland | D57: A database which contains data on crowdfunding/P2P platform features useful for rating platform integrity and to predict fraud, Discussion papers (DP) on the methodology for evaluating/rating ICOs and crowdfunding/P2P platforms and for detection/early warning about fraud/illegal behaviour with emphasis on the application of AI tools, Key software (codes, packages) developed by each of the Working Groups in line with their objectives, An edited volume containing scientific achievements of the Action, Strategy to engage stakeholders in the Action (including revisions in month 24 and 36) | E57: The development of conceptual and methodological tools for establishing when blackbox models are admissible and, to the extent possible, making them more transparent and/or replacing them with interpretable and explainable models., Create an excellent network of researchers in Europe with lasting collaboration beyond the lifetime of the Action., Bringing technological, quantitative and economic researchers together, to tackle future research that can only be done in an interdisciplinary setting, and getting actively involved in the blockchain and FinTech communities across Europe, to constantly monitor developments, get input and disseminate results., Bridging the gap between practitioners from the finance industry, academics and regulators by setting up a common knowledge exchange platform., Disseminate the results of the Action's activities to the scientific community, European institutions and to the general public., Significantly improve the gender equality in the fields of the Action. | F57: Yes | G57: Yes | H57: Yes | I57: Yes | J57: Yes | K57: Yes | L57: Yes | M57: 0 | N57: WG 1, WG 2, WG 3
A58: 44735.346 | B58: brankahm@gmail.com | C58: Switzerland | D58: A database which contains data on crowdfunding/P2P platform features useful for rating platform integrity and to predict fraud, Discussion papers (DP) on the methodology for evaluating/rating ICOs and crowdfunding/P2P platforms and for detection/early warning about fraud/illegal behaviour with emphasis on the application of AI tools, Report on good examples and best practices for a transparent finance industry with guidelines to improve transparency, Four annual reports (for lay audience) distributed via local and national media, Key software (codes, packages) developed by each of the Working Groups in line with their objectives, Handbook and/or wiki page describing potential approaches to tackle risk management issues related to blockchain assets and crowdfunding/P2P lending, An edited volume containing scientific achievements of the Action | E58: The development of conceptual and methodological tools for establishing when blackbox models are admissible and, to the extent possible, making them more transparent and/or replacing them with interpretable and explainable models., To receive input from regulators and practitioners' communities and to validate results with regard to increasing transparency of artificial intelligence applications., Disseminate to the public and share with regulators the results on investment product performance evaluation., Create an excellent network of researchers in Europe with lasting collaboration beyond the lifetime of the Action., Bridging the gap between practitioners from the finance industry, academics and regulators by setting up a common knowledge exchange platform., Transfer knowledge in terms of expertise, scientific tools and human resources across the different disciplines and between academia and industry., Establish an inclusive community of researchers on methodological and technological themes in Machine Learning and Artificial Intelligence, to promote Early Career Investigators and increase their visibility., Disseminate the results of the Action's activities to the scientific community, European institutions and to the general public., Significantly improve the gender equality in the fields of the Action. | F58: Yes | H58: Yes | I58: Yes | J58: Yes | K58: Yes | L58: Yes | M58: 0 | N58: WG 1, WG 2, WG 3
A59: 44846.711 | B59: scwp@zhaw.ch | C59: CH | D59: Anything else useful for the COST Action, not mentioned below, A discussion paper for possible approaches to building a statistically valid back-testing framework, Report on good examples and best practices for a transparent finance industry with guidelines to improve transparency, Key software (codes, packages) developed by each of the Working Groups in line with their objectives | E59: Anything else useful and related to the below topics, The development of conceptual and methodological tools for establishing when blackbox models are admissible and, to the extent possible, making them more transparent and/or replacing them with interpretable and explainable models., Pruning and improvement of the vast array of performance attribution models by contributing to the development of methodologies for reducing the false discovery rate in financial research and applied financial investment management., Disseminate to the public and share with regulators the results on investment product performance evaluation., Create an excellent network of researchers in Europe with lasting collaboration beyond the lifetime of the Action., Bringing technological, quantitative and economic researchers together, to tackle future research that can only be done in an interdisciplinary setting, and getting actively involved in the blockchain and FinTech communities across Europe, to constantly monitor developments, get input and disseminate results., Bridging the gap between practitioners from the finance industry, academics and regulators by setting up a common knowledge exchange platform., Transfer knowledge in terms of expertise, scientific tools and human resources across the different disciplines and between academia and industry., Establish an inclusive community of researchers on methodological and technological themes in Machine Learning and Artificial Intelligence, to promote Early Career Investigators and increase their visibility., Prepare competitive European researchers for a fruitful career in an international environment through intensive use of Short Term Scientific Missions (STSM) and joint educational programs with industrial partners., Maximize the job opportunities for PhD students and Early Career Investigators., Disseminate the results of the Action's activities to the scientific community, European institutions and to the general public. | F59: Yes | H59: Yes | I59: Yes | J59: Yes | K59: Yes | L59: Yes | M59: 0 | N59: WG 3 | O59: Papers acknowledging the action: 2 published in JFDS, 1 SUERF policy brief. Special issue on MDPI Mathematics https://www.mdpi.com/journal/mathematics/special_issues/applications_mathematical_foundations_machine_learning_investments Conferences acknowledging the action: three instances of the conference in Winterthur on AI in industry and finance (2020, 2021, 2022); special session at EURO2022 in July 2022 in Espoo and onsite WG3 and core group meeting in Espoo. Contributed to summer training school in Constanta / Romania | P59: Yes
A60: 44735.971 | B60: josterri@googlemail.com | C60: Switzerland | D60: Strategy to engage stakeholders in the Action (including revisions in month 24 and 36) | E60: Significantly improve the gender equality in the fields of the Action. | F60: No | H60: No | J60: No | K60: No | L60: No | M60: 0 | N60: WG 1, WG 2, WG 3 | P60: Yes
A61: 44753.499 | B61: lbarjaktarovic@singidunum.ac.rs | C61: Switzerland | D61: Report on good examples and best practices for a transparent finance industry with guidelines to improve transparency, Handbook and/or wiki page describing potential approaches to tackle risk management issues related to blockchain assets and crowdfunding/P2P lending, Strategy to engage stakeholders in the Action (including revisions in month 24 and 36) | E61: To develop blended approaches to evaluate innovative financial services and their providers, especially in the FinTech domain, building on Machine Learning methods, focussing on prediction (early warning) of operational fragility, fraudulent and illegal behaviour ranging from appropriation of loaned funds to money-laundering activities., Disseminate to the public and share with regulators the results on investment product performance evaluation., Create an excellent network of researchers in Europe with lasting collaboration beyond the lifetime of the Action., Maximize the job opportunities for PhD students and Early Career Investigators., Disseminate the results of the Action's activities to the scientific community, European institutions and to the general public. | F61: Yes | H61: No | J61: Yes | K61: Yes | L61: No | M61: 0 | N61: WG 3 | O61: I have become independent supervisory board member of UniCredit Bank Serbia - Belgrade. | P61: No
A62: 44764.637 | B62: josterri@googlemail.com | C62: Switzerland | D62: No, Anything else useful for the COST Action, not mentioned below | E62: No | F62: Yes | H62: Yes | J62: Yes | K62: Yes | L62: Yes | M62: 0 | N62: WG 3 | P62: Yes
A63: 44796.415 | B63: heb1@bfh.ch | C63: Switzerland | D63: A database which contains data on crowdfunding/P2P platform features useful for rating platform integrity and to predict fraud, Discussion papers (DP) on the methodology for evaluating/rating ICOs and crowdfunding/P2P platforms and for detection/early warning about fraud/illegal behaviour with emphasis on the application of AI tools, Report on good examples and best practices for a transparent finance industry with guidelines to improve transparency | E63: To develop blended approaches to evaluate innovative financial services and their providers, especially in the FinTech domain, building on Machine Learning methods, focussing on prediction (early warning) of operational fragility, fraudulent and illegal behaviour ranging from appropriation of loaned funds to money-laundering activities., The development of conceptual and methodological tools for establishing when blackbox models are admissible and, to the extent possible, making them more transparent and/or replacing them with interpretable and explainable models., To receive input from regulators and practitioners' communities and to validate results with regard to increasing transparency of artificial intelligence applications., Pruning and improvement of the vast array of performance attribution models by contributing to the development of methodologies for reducing the false discovery rate in financial research and applied financial investment management., Disseminate to the public and share with regulators the results on investment product performance evaluation., Create an excellent network of researchers in Europe with lasting collaboration beyond the lifetime of the Action., Bringing technological, quantitative and economic researchers together, to tackle future research that can only be done in an interdisciplinary setting, and getting actively involved in the blockchain and FinTech communities across Europe, to constantly monitor developments, get input and disseminate results., Bridging the gap between practitioners from the finance industry, academics and regulators by setting up a common knowledge exchange platform., Transfer knowledge in terms of expertise, scientific tools and human resources across the different disciplines and between academia and industry., Establish an inclusive community of researchers on methodological and technological themes in Machine Learning and Artificial Intelligence, to promote Early Career Investigators and increase their visibility., Overcome the siloing of research topics by country and achieve geographical and demographical diversity, with special attention to COST Inclusiveness Target countries., Disseminate the results of the Action's activities to the scientific community, European institutions and to the general public. | F63: Yes | H63: Yes | J63: Yes | K63: Yes | L63: Yes | M63: 0 | N63: WG 2 | P63: Yes
A64: 44736.345 | B64: belma.ozturkkal@khas.edu.tr | C64: Turkey | D64: Position papers, aimed at regulators and policy-makers, on methodology (with examples of formal criteria) for testing AI techniques in real-time, Report on good examples and best practices for a transparent finance industry with guidelines to improve transparency | E64: To develop blended approaches to evaluate innovative financial services and their providers, especially in the FinTech domain, building on Machine Learning methods, focussing on prediction (early warning) of operational fragility, fraudulent and illegal behaviour ranging from appropriation of loaned funds to money-laundering activities., To receive input from regulators and practitioners' communities and to validate results with regard to increasing transparency of artificial intelligence applications., Disseminate to the public and share with regulators the results on investment product performance evaluation., Creation of the first European platform comparing the out-of-sample performance of banks' investment products, insurance-linked investment products and asset management products available to the general public., Create an excellent network of researchers in Europe with lasting collaboration beyond the lifetime of the Action., Bringing technological, quantitative and economic researchers together, to tackle future research that can only be done in an interdisciplinary setting, and getting actively involved in the blockchain and FinTech communities across Europe, to constantly monitor developments, get input and disseminate results., Bridging the gap between practitioners from the finance industry, academics and regulators by setting up a common knowledge exchange platform., Transfer knowledge in terms of expertise, scientific tools and human resources across the different disciplines and between academia and industry., Disseminate the results of the Action's activities to the scientific community, European institutions and to the general public., Significantly improve the gender equality in the fields of the Action. | F64: Yes | H64: No | J64: Yes | K64: Yes | L64: No | M64: 0 | N64: WG 2, WG 3 | P64: Yes
A65: 44741.546 | B65: etalasli@selcuk.edu.tr | C65: Turkey | D65: Position papers, aimed at regulators and policy-makers, on methodology (with examples of formal criteria) for testing AI techniques in real-time | E65: Disseminate the results of the Action's activities to the scientific community, European institutions and to the general public., Significantly improve the gender equality in the fields of the Action. | F65: No | H65: Yes | J65: Yes | K65: Yes | L65: Yes | M65: 0 | N65: WG 1, WG 3 | P65: Yes
A66: 44749.619 | B66: belma.ozturkkal@khas.edu.tr | C66: Turkey | D66: Report on good examples and best practices for a transparent finance industry with guidelines to improve transparency | E66: To develop blended approaches to evaluate innovative financial services and their providers, especially in the FinTech domain, building on Machine Learning methods, focussing on prediction (early warning) of operational fragility, fraudulent and illegal behaviour ranging from appropriation of loaned funds to money-laundering activities., To receive input from regulators and practitioners' communities and to validate results with regard to increasing transparency of artificial intelligence applications., Disseminate to the public and share with regulators the results on investment product performance evaluation., Create an excellent network of researchers in Europe with lasting collaboration beyond the lifetime of the Action., Bridging the gap between practitioners from the finance industry, academics and regulators by setting up a common knowledge exchange platform., Transfer knowledge in terms of expertise, scientific tools and human resources across the different disciplines and between academia and industry., Maximize the job opportunities for PhD students and Early Career Investigators., Disseminate the results of the Action's activities to the scientific community, European institutions and to the general public., Significantly improve the gender equality in the fields of the Action. | F66: Yes | H66: Yes | J66: Yes | K66: Yes | L66: No | M66: 0 | N66: WG 2, WG 3 | P66: Yes
A67: 44782.705 | B67: etalasli@selcuk.edu.tr | C67: Turkey | D67: Discussion papers (DP) on the methodology for evaluating/rating ICOs and crowdfunding/P2P platforms and for detection/early warning about fraud/illegal behaviour with emphasis on the application of AI tools, A discussion paper for possible approaches to building a statistically valid back-testing framework, Methodological discussion paper on the design of stress tests for the evaluation of AI and ML models under shifting financial conditions to improve the robustness of models, Report on good examples and best practices for a transparent finance industry with guidelines to improve transparency | E67: To develop blended approaches to evaluate innovative financial services and their providers, especially in the FinTech domain, building on Machine Learning methods, focussing on prediction (early warning) of operational fragility, fraudulent and illegal behaviour ranging from appropriation of loaned funds to money-laundering activities., The development of conceptual and methodological tools for establishing when blackbox models are admissible and, to the extent possible, making them more transparent and/or replacing them with interpretable and explainable models., To receive input from regulators and practitioners' communities and to validate results with regard to increasing transparency of artificial intelligence applications., Pruning and improvement of the vast array of performance attribution models by contributing to the development of methodologies for reducing the false discovery rate in financial research and applied financial investment management., Disseminate to the public and share with regulators the results on investment product performance evaluation., Creation of the first European platform comparing the out-of-sample performance of banks' investment products, insurance-linked investment products and asset management products available to the general public., Create an excellent network of researchers in Europe with lasting collaboration beyond the lifetime of the Action., Bringing technological, quantitative and economic researchers together, to tackle future research that can only be done in an interdisciplinary setting, and getting actively involved in the blockchain and FinTech communities across Europe, to constantly monitor developments, get input and disseminate results., Bridging the gap between practitioners from the finance industry, academics and regulators by setting up a common knowledge exchange platform., Transfer knowledge in terms of expertise, scientific tools and human resources across the different disciplines and between academia and industry., Establish an inclusive community of researchers on methodological and technological themes in Machine Learning and Artificial Intelligence, to promote Early Career Investigators and increase their visibility., Overcome the siloing of research topics by country and achieve geographical and demographical diversity, with special attention to COST Inclusiveness Target countries., Prepare competitive European researchers for a fruitful career in an international environment through intensive use of Short Term Scientific Missions (STSM) and joint educational programs with industrial partners., Disseminate the results of the Action's activities to the scientific community, European institutions and to the general public., Significantly improve the gender equality in the fields of the Action. | F67: Yes | H67: Yes | J67: Yes | K67: Yes | L67: Yes | M67: 0 | N67: WG 1, WG 3 | P67: Yes
A68: 44736.483 | B68: luciana.dallavalle@plymouth.ac.uk | C68: United Kingdom | D68: Position papers, aimed at regulators and policy-makers, on methodology (with examples of formal criteria) for testing AI techniques in real-time | E68: The development of conceptual and methodological tools for establishing when blackbox models are admissible and, to the extent possible, making them more transparent and/or replacing them with interpretable and explainable models., Create an excellent network of researchers in Europe with lasting collaboration beyond the lifetime of the Action., Overcome the siloing of research topics by country and achieve geographical and demographical diversity, with special attention to COST Inclusiveness Target countries., Significantly improve the gender equality in the fields of the Action. | F68: No | H68: No | J68: Yes | K68: No | L68: No | M68: 0 | N68: WG 2 | P68: No
A69: 44736.587 | B69: a.zalewska@bath.ac.uk | C69: United Kingdom | D69: Anything else useful for the COST Action, not mentioned below, A position paper and roadmap on mitigating risks connected with the increased use of digital assets | E69: Anything else useful and related to the below topics, Transfer knowledge in terms of expertise, scientific tools and human resources across the different disciplines and between academia and industry., Disseminate the results of the Action's activities to the scientific community, European institutions and to the general public. | F69: Yes | H69: No | J69: No | K69: Yes | L69: No | M69: 0 | N69: WG 1 | P69: Yes
A70: 44749.905 | B70: CathyYi-Hsuan.Chen@glasgow.ac.uk | C70: United Kingdom | D70: Methodological discussion paper on the design of stress tests for the evaluation of AI and ML models under shifting financial conditions to improve the robustness of models, Report on good examples and best practices for a transparent finance industry with guidelines to improve transparency | E70: To develop blended approaches to evaluate innovative financial services and their providers, especially in the FinTech domain, building on Machine Learning methods, focussing on prediction (early warning) of operational fragility, fraudulent and illegal behaviour ranging from appropriation of loaned funds to money-laundering activities., The development of conceptual and methodological tools for establishing when blackbox models are admissible and, to the extent possible, making them more transparent and/or replacing them with interpretable and explainable models., Create an excellent network of researchers in Europe with lasting collaboration beyond the lifetime of the Action., Bridging the gap between practitioners from the finance industry, academics and regulators by setting up a common knowledge exchange platform. | F70: Yes | H70: Yes | J70: Yes | K70: No | L70: No | M70: 0 | N70: WG 1 | P70: Yes
A71: 44737.321 | B71: sam.goundar@gmail.com | C71: Vietnam | D71: Discussion papers (DP) on the methodology for evaluating/rating ICOs and crowdfunding/P2P platforms and for detection/early warning about fraud/illegal behaviour with emphasis on the application of AI tools, Methodological discussion papers on AI models to generate “failed trials” of investment product producers and on quantitative strategies with the usage of the promising field of network data analysis exchanges and regional consolidation platforms optimised for accessibility to all partners, Handbook and/or wiki page describing potential approaches to tackle risk management issues related to blockchain assets and crowdfunding/P2P lending | E71: No, Transfer knowledge in terms of expertise, scientific tools and human resources across the different disciplines and between academia and industry., Establish an inclusive community of researchers on methodological and technological themes in Machine Learning and Artificial Intelligence, to promote Early Career Investigators and increase their visibility., Maximize the job opportunities for PhD students and Early Career Investigators., Significantly improve the gender equality in the fields of the Action. | F71: No | H71: No | J71: Yes | K71: Yes | L71: Yes | M71: 0 | N71: WG 1, WG 2 | P71: No
A72: 44827.6 | B72: veniarakelian@yahoo.com | C72: Greece | D72: Methodological discussion paper on the design of stress tests for the evaluation of AI and ML models under shifting financial conditions to improve the robustness of models, Key software (codes, packages) developed by each of the Working Groups in line with their objectives | E72: To develop blended approaches to evaluate innovative financial services and their providers, especially in the FinTech domain, building on Machine Learning methods, focussing on prediction (early warning) of operational fragility, fraudulent and illegal behaviour ranging from appropriation of loaned funds to money-laundering activities., The development of conceptual and methodological tools for establishing when blackbox models are admissible and, to the extent possible, making them more transparent and/or replacing them with interpretable and explainable models., To receive input from regulators and practitioners' communities and to validate results with regard to increasing transparency of artificial intelligence applications., Pruning and improvement of the vast array of performance attribution models by contributing to the development of methodologies for reducing the false discovery rate in financial research and applied financial investment management., Disseminate to the public and share with regulators the results on investment product performance evaluation., Create an excellent network of researchers in Europe with lasting collaboration beyond the lifetime of the Action., Bringing technological, quantitative and economic researchers together, to tackle future research that can only be done in an interdisciplinary setting, and getting actively involved in the blockchain and FinTech communities across Europe, to constantly monitor developments, get input and disseminate results., Bridging the gap between practitioners from the finance industry, academics and regulators by setting up a common knowledge exchange platform., Transfer knowledge in terms of expertise, scientific tools and human resources across the different disciplines and between academia and industry., Establish an inclusive community of researchers on methodological and technological themes in Machine Learning and Artificial Intelligence, to promote Early Career Investigators and increase their visibility., Disseminate the results of the Action's activities to the scientific community, European institutions and to the general public. | F72: Yes | H72: No | J72: Yes | K72: Yes | L72: Yes | M72: 0 | N72: WG 3 | P72: Yes
A73: 44823.631 | B73: baalsl@tcd.ie | C73: Ireland | D73: A discussion paper raising new research ideas on the financial economics of non-fungible token (NFT) in form of a research agenda | E73: No | F73: Yes | G73: No | H73: No | I73: No | J73: Yes | K73: No | L73: No | N73: WG1, WG3 | P73: No

Sheet Pivot Table 2

Sheet All Countries
B1: Responded to GP1 GP2 report
A2: Albania | B2: =vlookup(A2,'Form responses 1'!$C$2:$C$129,1,false) -> Albania
A3: Austria | B3: =vlookup(A3,'Form responses 1'!$C$2:$C$129,1,false) -> Austria
A4: Belgium | B4: =vlookup(A4,'Form responses 1'!$C$2:$C$129,1,false) -> #N/A
A5: Bosnia and Herzegovina | B5: =vlookup(A5,'Form responses 1'!$C$2:$C$129,1,false) -> #N/A
A6: Bulgaria | B6: =vlookup(A6,'Form responses 1'!$C$2:$C$129,1,false) -> #N/A
A7: Croatia | B7: =vlookup(A7,'Form responses 1'!$C$2:$C$129,1,false) -> Croatia
A8: Cyprus | B8: =vlookup(A8,'Form responses 1'!$C$2:$C$129,1,false) -> Cyprus
A9: Czech Republic | B9: =vlookup(A9,'Form responses 1'!$C$2:$C$129,1,false) -> Czech Republic
A10: Denmark | B10: =vlookup(A10,'Form responses 1'!$C$2:$C$129,1,false) -> #N/A
A11: Estonia | B11: =vlookup(A11,'Form responses 1'!$C$2:$C$129,1,false) -> Estonia
A12: Finland | B12: =vlookup(A12,'Form responses 1'!$C$2:$C$129,1,false) -> #N/A
A13: France | B13: =vlookup(A13,'Form responses 1'!$C$2:$C$129,1,false) -> France
... A40: United Kingdom | B40: =vlookup(A40,'Form responses 1'!$C$2:$C$129,1,false) -> United Kingdom

Sheet MembersByCountry
A1: COST FinAI | B1: Last Name | D1: Email | E1: Country | F1: MC Membership Status | G1: Country | I1: responded to GP 1 and GP 2 Progress report
A2: Petraq | B2: Papajorgji | D2: petraq@gmail.com | E2: Albania (AL) | F2: not nominated | G2: =IFERROR(__xludf.DUMMYFUNCTION("split(E2,"" "")"),"Albania") -> Albania | H2: =IFERROR(__xludf.DUMMYFUNCTION("""COMPUTED_VALUE"""),"(AL)") -> (AL) | I2: =vlookup(G2,'All Countries'!$A$1:$B$40,2,false) -> Albania
A3: Altin | B3: Idrizi | D3: altin.idrizi@uniel.edu.al | E3: Albania (AL) | F3: not nominated | G3: =IFERROR(__xludf.DUMMYFUNCTION("split(E3,"" "")"),"Albania") -> Albania | H3: =IFERROR(__xludf.DUMMYFUNCTION("""COMPUTED_VALUE"""),"(AL)") -> (AL) | I3: =vlookup(G3,'All Countries'!$A$1:$B$40,2,false) -> Albania
A4: Endrit | B4: Xhina | D4: endri.xhina@fshn.edu.al | E4: Albania (AL) | F4: not nominated | G4: =IFERROR(__xludf.DUMMYFUNCTION("split(E4,"" "")"),"Albania") -> Albania | H4: =IFERROR(__xludf.DUMMYFUNCTION("""COMPUTED_VALUE"""),"(AL)") -> (AL) | I4: =vlookup(G4,'All Countries'!$A$1:$B$40,2,false) -> Albania
A5: Rezarta | B5: Shkurti (Perri) | D5: rezartaperri@feut.edu.al | E5: Albania (AL) | F5: Member | G5: =IFERROR(__xludf.DUMMYFUNCTION("split(E5,"" "")"),"Albania") -> Albania | H5: =IFERROR(__xludf.DUMMYFUNCTION("""COMPUTED_VALUE"""),"(AL)") -> (AL) | I5: =vlookup(G5,'All Countries'!$A$1:$B$40,2,false) -> Albania
A6: Ardita | B6: Todri | D6: ardita.todri@gmail.com | E6: Albania (AL) | F6: not nominated | G6: =IFERROR(__xludf.DUMMYFUNCTION("split(E6,"" "")"),"Albania") -> Albania | H6: =IFERROR(__xludf.DUMMYFUNCTION("""COMPUTED_VALUE"""),"(AL)") -> (AL) | I6: =vlookup(G6,'All Countries'!$A$1:$B$40,2,false) -> Albania
A7: Suela | B7: Maxhelaku | D7: suela.maxhelaku@fshn.edu.al | E7: Albania (AL) | F7: not nominated | G7: =IFERROR(__xludf.DUMMYFUNCTION("split(E7,"" "")"),"Albania") -> Albania | H7: =IFERROR(__xludf.DUMMYFUNCTION("""COMPUTED_VALUE"""),"(AL)") -> (AL) | I7: =vlookup(G7,'All Countries'!$A$1:$B$40,2,false) -> Albania
A8: Giovanni | B8: Lagioia | D8: giovanni.lagioia@uniba.it | E8: Albania (AL) | F8: Member | G8: =IFERROR(__xludf.DUMMYFUNCTION("split(E8,"" "")"),"Albania") -> Albania | H8: =IFERROR(__xludf.DUMMYFUNCTION("""COMPUTED_VALUE"""),"(AL)") -> (AL) | I8: =vlookup(G8,'All Countries'!$A$1:$B$40,2,false) -> Albania
A9: Elda | B9: Xhumari | D9: eldaxhumari@gmail.com | E9: Albania (AL) | F9: not nominated | G9: =IFERROR(__xludf.DUMMYFUNCTION("split(E9,"" "")"),"Albania") -> Albania | H9: =IFERROR(__xludf.DUMMYFUNCTION("""COMPUTED_VALUE"""),"(AL)") -> (AL) | I9: =vlookup(G9,'All Countries'!$A$1:$B$40,2,false) -> Albania
A10: Eliona | B10: Gremi | D10: Eliona.Gremi@uniel.edu.al | E10: Albania (AL) | F10: not nominated | G10: =IFERROR(__xludf.DUMMYFUNCTION("split(E10,"" "")"),"Albania") -> Albania | H10: =IFERROR(__xludf.DUMMYFUNCTION("""COMPUTED_VALUE"""),"(AL)") -> (AL) | I10: =vlookup(G10,'All Countries'!$A$1:$B$40,2,false) -> Albania
A11: LLESH | B11: LLESHAJ | D11: lleshlleshaj@feut.edu.al | E11: Albania (AL) | F11: not nominated | G11: =IFERROR(__xludf.DUMMYFUNCTION("split(E11,"" "")"),"Albania") -> Albania | H11: =IFERROR(__xludf.DUMMYFUNCTION("""COMPUTED_VALUE"""),"(AL)") -> (AL) | I11: =vlookup(G11,'All Countries'!$A$1:$B$40,2,false) -> Albania
A12: Valbona | B12: Ballkoci | D12: valbona.ballkoci@uniel.edu.al | E12: Albania (AL) | F12: not nominated | G12: =IFERROR(__xludf.DUMMYFUNCTION("split(E12,"" "")"),"Albania") -> Albania | H12: =IFERROR(__xludf.DUMMYFUNCTION("""COMPUTED_VALUE"""),"(AL)") -> (AL) | I12: =vlookup(G12,'All Countries'!$A$1:$B$40,2,false) -> Albania
A13: Anila | B13: Çekrezi | D13: vocianila@yahoo.com | E13: Albania (AL) | F13: not nominated | G13: =IFERROR(__xludf.DUMMYFUNCTION("split(E13,"" "")"),"Albania") -> Albania | H13: =IFERROR(__xludf.DUMMYFUNCTION("""COMPUTED_VALUE"""),"(AL)") -> (AL) | I13: =vlookup(G13,'All Countries'!$A$1:$B$40,2,false) -> Albania
A14: Chemseddine | B14: TIDJANI | D14: tidjani.chemseddine@gmail.com | E14: Algeria (DZ) | F14: not nominated | G14: =IFERROR(__xludf.DUMMYFUNCTION("split(E14,"" "")"),"Algeria") -> Algeria | H14: =IFERROR(__xludf.DUMMYFUNCTION("""COMPUTED_VALUE"""),"(DZ)") -> (DZ) | I14: =vlookup(G14,'All Countries'!$A$1:$B$40,2,false) -> #N/A
A15: Ronald | B15: Hochreiter | D15: ronald.hochreiter@wu.ac.at | E15: Austria (AT) | F15: Member | G15: =IFERROR(__xludf.DUMMYFUNCTION("split(E15,"" "")"),"Austria") -> Austria | H15: =IFERROR(__xludf.DUMMYFUNCTION("""COMPUTED_VALUE"""),"(AT)") -> (AT) | I15: =vlookup(G15,'All Countries'!$A$1:$B$40,2,false) -> Austria
A16: Christian | B16: Ochs | D16: christian.ochs@fincredible.at | E16: Austria (AT) | F16: Member | G16: =IFERROR(__xludf.DUMMYFUNCTION("split(E16,"" "")"),"Austria") -> Austria | H16: =IFERROR(__xludf.DUMMYFUNCTION("""COMPUTED_VALUE"""),"(AT)") -> (AT) | I16: =vlookup(G16,'All Countries'!$A$1:$B$40,2,false) -> Austria
A17: Christian | B17: Hafner | D17: christian.hafner@uclouvain.be | E17: Belgium (BE) | F17: Member | G17: =IFERROR(__xludf.DUMMYFUNCTION("split(E17,"" "")"),"Belgium") -> Belgium | H17: =IFERROR(__xludf.DUMMYFUNCTION("""COMPUTED_VALUE"""),"(BE)") -> (BE) | I17: =vlookup(G17,'All Countries'!$A$1:$B$40,2,false) -> #N/A
A18: Igor | B18: Todorović | D18: igor.todorovic@ef.unibl.org | E18: Bosnia and Herzegovina (BA) | F18: Member | G18: Bosnia and Herzegovina | I18: =vlookup(G18,'All Countries'!$A$1:$B$40,2,false) -> #N/A
A19: Jelena | B19: Poljašević | D19: jelena.poljasevic@ef.unibl.org | E19: Bosnia and Herzegovina (BA) | F19: Member | G19: Bosnia and Herzegovina | I19: =vlookup(G19,'All Countries'!$A$1:$B$40,2,false) -> #N/A
A20: Rossitza | B20: Goleva | D20: rgoleva@gmail.com | E20: Bulgaria (BG) | F20: not nominated | G20: =IFERROR(__xludf.DUMMYFUNCTION("split(E20,"" "")"),"Bulgaria") -> Bulgaria | H20: =IFERROR(__xludf.DUMMYFUNCTION("""COMPUTED_VALUE"""),"(BG)") -> (BG) | I20: =vlookup(G20,'All Countries'!$A$1:$B$40,2,false) -> #N/A
A21: Stoyan | B21: Mishev | D21: stoyan.mishev@iaps.institute | E21: Bulgaria (BG) | F21: Member | G21: =IFERROR(__xludf.DUMMYFUNCTION("split(E21,"" "")"),"Bulgaria") -> Bulgaria | H21: =IFERROR(__xludf.DUMMYFUNCTION("""COMPUTED_VALUE"""),"(BG)") -> (BG) | I21: =vlookup(G21,'All Countries'!$A$1:$B$40,2,false) -> #N/A
A22: Yassen | B22: Gorbounov | D22: ygorbounov@nbu.bg | E22: Bulgaria (BG) | F22: Member | G22: =IFERROR(__xludf.DUMMYFUNCTION("split(E22,"" "")"),"Bulgaria") -> Bulgaria | H22: =IFERROR(__xludf.DUMMYFUNCTION("""COMPUTED_VALUE"""),"(BG)") -> (BG) | I22: Bulgaria
A23: Hristina | B23: Kostadinova | D23: hkostadinova@gmail.com | E23: Bulgaria (BG) | F23: not nominated | G23: =IFERROR(__xludf.DUMMYFUNCTION("split(E23,"" "")"),"Bulgaria") -> Bulgaria | H23: =IFERROR(__xludf.DUMMYFUNCTION("""COMPUTED_VALUE"""),"(BG)") -> (BG)
A24: Silvija | B24: Vlah Jerić | D24: svlah@net.efzg.hr | E24: Croatia (HR) | F24: not nominated | G24: =IFERROR(__xludf.DUMMYFUNCTION("split(E24,"" "")"),"Croatia") -> Croatia | H24: =IFERROR(__xludf.DUMMYFUNCTION("""COMPUTED_VALUE"""),"(HR)") -> (HR) | I24: =vlookup(G24,'All Countries'!$A$1:$B$40,2,false) -> Croatia
A25: Nika | B25: Šimurina | D25: nsimurina@efzg.hr | E25: Croatia (HR) | F25: Member | G25: =IFERROR(__xludf.DUMMYFUNCTION("split(E25,"" "")"),"Croatia") -> Croatia | H25: =IFERROR(__xludf.DUMMYFUNCTION("""COMPUTED_VALUE"""),"(HR)") -> (HR) | I25: =vlookup(G25,'All Countries'!$A$1:$B$40,2,false) -> Croatia
A26: Martina | B26: Solenički | D26: mnakic@efzg.hr | E26: Croatia (HR) | F26: not nominated | G26: =IFERROR(__xludf.DUMMYFUNCTION("split(E26,"" "")"),"Croatia") -> Croatia | H26: =IFERROR(__xludf.DUMMYFUNCTION("""COMPUTED_VALUE"""),"(HR)") -> (HR) | I26: =vlookup(G26,'All Countries'!$A$1:$B$40,2,false) -> Croatia
A27: Ana | B27: Ivanisevic Hernaus | D27: ana.ivanisevic@efzg.hr | E27: Croatia (HR) | F27: Member | G27: =IFERROR(__xludf.DUMMYFUNCTION("split(E27,"" "")"),"Croatia") -> Croatia | H27: =IFERROR(__xludf.DUMMYFUNCTION("""COMPUTED_VALUE"""),"(HR)") -> (HR) | I27: =vlookup(G27,'All Countries'!$A$1:$B$40,2,false) -> Croatia
A28: Domagoj | B28: Sajter | D28: domagoj.sajter+cost@gmail.com | E28: Croatia (HR) | F28: not nominated | G28: =IFERROR(__xludf.DUMMYFUNCTION("split(E28,"" "")"),"Croatia") -> Croatia | H28: =IFERROR(__xludf.DUMMYFUNCTION("""COMPUTED_VALUE"""),"(HR)") -> (HR) | I28: =vlookup(G28,'All Countries'!$A$1:$B$40,2,false) -> Croatia
A29: Mile | B29: Bošnjak | D29: mile.bosnjak76@gmail.com | E29: Croatia (HR) | F29: not nominated | G29: =IFERROR(__xludf.DUMMYFUNCTION("split(E29,"" "")"),"Croatia") -> Croatia | H29: =IFERROR(__xludf.DUMMYFUNCTION("""COMPUTED_VALUE"""),"(HR)") -> (HR) | I29: =vlookup(G29,'All Countries'!$A$1:$B$40,2,false) -> Croatia
A30: Andreas | B30: Gregoriades | D30: andreas.gregoriades@cut.ac.cy | E30: Cyprus (CY) | F30: Member | G30: =IFERROR(__xludf.DUMMYFUNCTION("split(E30,"" "")"),"Cyprus") -> Cyprus | H30: =IFERROR(__xludf.DUMMYFUNCTION("""COMPUTED_VALUE"""),"(CY)") -> (CY) | I30: =vlookup(G30,'All Countries'!$A$1:$B$40,2,false) -> Cyprus
A31: Loizos | B31: Michael | D31: loizos@ouc.ac.cy | E31: Cyprus (CY) | F31: not nominated | G31: =IFERROR(__xludf.DUMMYFUNCTION("split(E31,"" "")"),"Cyprus") -> Cyprus | H31: =IFERROR(__xludf.DUMMYFUNCTION("""COMPUTED_VALUE"""),"(CY)") -> (CY) | I31: =vlookup(G31,'All Countries'!$A$1:$B$40,2,false) -> Cyprus
A32: Ifigenia | B32: Georgiou | D32: georgiou.i@unic.ac.cy | E32: Cyprus (CY) | F32: Member | G32: =IFERROR(__xludf.DUMMYFUNCTION("split(E32,"" "")"),"Cyprus") -> Cyprus | H32: =IFERROR(__xludf.DUMMYFUNCTION("""COMPUTED_VALUE"""),"(CY)") -> (CY) | I32: =vlookup(G32,'All Countries'!$A$1:$B$40,2,false) -> Cyprus
A33: Oleg | B33: Deev | D33: oleg@mail.muni.cz | E33: Czech Republic (CZ) | F33: Member | G33: Czech Republic | I33: =vlookup(G33,'All Countries'!$A$1:$B$40,2,false) -> Czech Republic
A34: Dagmar | B34: Vagnerova Linnertova | D34: dagmar.linnertova@mail.muni.cz | E34: Czech Republic (CZ) | F34: Member | G34: Czech Republic | I34: =vlookup(G34,'All Countries'!$A$1:$B$40,2,false) -> Czech Republic
A35: Petr | B35: Hajek | D35: petr.hajek@upce.cz | E35: Czech Republic (CZ) | F35: not nominated | G35: Czech Republic | I35: =vlookup(G35,'All Countries'!$A$1:$B$40,2,false) -> Czech Republic
A36: Ladislav | B36: Krištoufek | D36: LK@fsv.cuni.cz | E36: Czech Republic (CZ) | F36: not nominated | G36: Czech Republic | I36: =vlookup(G36,'All Countries'!$A$1:$B$40,2,false) -> Czech Republic
A37: Jan | B37: Vlachy | D37: jan.vlachy@vscht.cz | E37: Czech Republic (CZ) | F37: not nominated | G37: Czech Republic | I37: =vlookup(G37,'All Countries'!$A$1:$B$40,2,false) -> Czech Republic
A38: Maria Dolores | B38: Romero Morales | D38: drm.eco@cbs.dk | E38: Denmark (DK) | F38: Member | G38: =IFERROR(__xludf.DUMMYFUNCTION("split(E38,"" "")"),"Denmark") -> Denmark | H38: =IFERROR(__xludf.DUMMYFUNCTION("""COMPUTED_VALUE"""),"(DK)") -> (DK) | I38: =vlookup(G38,'All Countries'!$A$1:$B$40,2,false) -> #N/A
A39: Alexandros | B39: Iosifidis | D39: ai@ece.au.dk | E39: Denmark (DK) | F39: Member | G39: =IFERROR(__xludf.DUMMYFUNCTION("split(E39,"" "")"),"Denmark") -> Denmark | H39: =IFERROR(__xludf.DUMMYFUNCTION("""COMPUTED_VALUE"""),"(DK)") -> (DK) | I39: =vlookup(G39,'All Countries'!$A$1:$B$40,2,false) -> #N/A
A40: Innar | B40: Liiv | D40: innar.liiv@ttu.ee | E40: Estonia (EE) | F40: Member | G40: =IFERROR(__xludf.DUMMYFUNCTION("split(E40,"" "")"),"Estonia") -> Estonia | H40: =IFERROR(__xludf.DUMMYFUNCTION("""COMPUTED_VALUE"""),"(EE)") -> (EE) | I40: =vlookup(G40,'All Countries'!$A$1:$B$40,2,false) -> Estonia
A41: Jaan | B41: Übi | D41: jaan.ubi@ut.ee | E41: Estonia (EE) | F41: not nominated | G41: =IFERROR(__xludf.DUMMYFUNCTION("split(E41,"" "")"),"Estonia") -> Estonia | H41: =IFERROR(__xludf.DUMMYFUNCTION("""COMPUTED_VALUE"""),"(EE)") -> (EE) | I41: =vlookup(G41,'All Countries'!$A$1:$B$40,2,false) -> Estonia
A42: Laivi | B42: Laidroo | D42: laivi.laidroo@taltech.ee | E42: Estonia (EE) | F42: not nominated | G42: =IFERROR(__xludf.DUMMYFUNCTION("split(E42,"" "")"),"Estonia") -> Estonia | H42: =IFERROR(__xludf.DUMMYFUNCTION("""COMPUTED_VALUE"""),"(EE)") -> (EE) | I42: =vlookup(G42,'All Countries'!$A$1:$B$40,2,false) -> Estonia
A43: Susanne | B43: Durst | D43: susanne.durst@taltech.ee | E43: Estonia (EE) | F43: Member | G43: =IFERROR(__xludf.DUMMYFUNCTION("split(E43,"" "")"),"Estonia") -> Estonia | H43: =IFERROR(__xludf.DUMMYFUNCTION("""COMPUTED_VALUE"""),"(EE)") -> (EE) | I43: =vlookup(G43,'All Countries'!$A$1:$B$40,2,false) -> Estonia
A44: Esteban | B44: Guerrero | D44: esteban.guerrero@uwasa.fi | E44: Finland (FI) | F44: not nominated | G44: =IFERROR(__xludf.DUMMYFUNCTION("split(E44,"" "")"),"Finland") -> Finland | H44: =IFERROR(__xludf.DUMMYFUNCTION("""COMPUTED_VALUE"""),"(FI)") -> (FI) | I44: =vlookup(G44,'All Countries'!$A$1:$B$40,2,false) -> #N/A
A45: Agnes | B45: Guerraz | D45: agnes.guerraz@skopai.com | E45: France (FR) | F45: Member | G45: =IFERROR(__xludf.DUMMYFUNCTION("split(E45,"" "")"),"France") -> France | H45: =IFERROR(__xludf.DUMMYFUNCTION("""COMPUTED_VALUE"""),"(FR)") -> (FR) | I45: =vlookup(G45,'All Countries'!$A$1:$B$40,2,false) -> France
A46: Emmanuel | B46: EYIAH-DONKOR | D46: emmanuel.eyiah-donkor@rennes-sb.com | E46: France (FR) | F46: Member | G46: =IFERROR(__xludf.DUMMYFUNCTION("split(E46,"" "")"),"France") -> France | H46: =IFERROR(__xludf.DUMMYFUNCTION("""COMPUTED_VALUE"""),"(FR)") -> (FR) | I46: =vlookup(G46,'All Countries'!$A$1:$B$40,2,false) -> France
A47: Roman | B47: Matkovsky | D47: roman.matkovskyy@rennes-sb.com | E47: France (FR) | F47: not nominated | G47: =IFERROR(__xludf.DUMMYFUNCTION("split(E47,"" "")"),"France") -> France | H47: =IFERROR(__xludf.DUMMYFUNCTION("""COMPUTED_VALUE"""),"(FR)") -> (FR) | I47: =vlookup(G47,'All Countries'!$A$1:$B$40,2,false) -> France
A48: Galena | B48: Pisoni | D48: galena.pisoni@gmail.com | E48: France (FR) | F48: not nominated | G48: =IFERROR(__xludf.DUMMYFUNCTION("split(E48,"" "")"),"France") -> France | H48: =IFERROR(__xludf.DUMMYFUNCTION("""COMPUTED_VALUE"""),"(FR)") -> (FR) | I48: =vlookup(G48,'All Countries'!$A$1:$B$40,2,false) -> France
A49: Marianna | B49: Russo | D49: marianna.russo@neoma-bs.fr | E49: France (FR) | F49: not nominated | G49: =IFERROR(__xludf.DUMMYFUNCTION("split(E49,"" "")"),"France") -> France | H49: =IFERROR(__xludf.DUMMYFUNCTION("""COMPUTED_VALUE"""),"(FR)") -> (FR) | I49: =vlookup(G49,'All Countries'!$A$1:$B$40,2,false) -> France
A50: Akanksha | B50: Jalan | D50: akanksha.jalan@rennes-sb.com | E50: France (FR) | F50: not nominated | G50: =IFERROR(__xludf.DUMMYFUNCTION("split(E50,"" "")"),"France") -> France | H50: =IFERROR(__xludf.DUMMYFUNCTION("""COMPUTED_VALUE"""),"(FR)") -> (FR) | I50: =vlookup(G50,'All Countries'!$A$1:$B$40,2,false) -> France
A51: Alexandre | B51: Boulenger | D51: alexandre.boulenger@gmail.com | E51: France (FR) | F51: not nominated | G51: =IFERROR(__xludf.DUMMYFUNCTION("split(E51,"" "")"),"France") -> France | H51: =IFERROR(__xludf.DUMMYFUNCTION("""COMPUTED_VALUE"""),"(FR)") -> (FR) | I51: =vlookup(G51,'All Countries'!$A$1:$B$40,2,false) -> France
A52: Alla | B52: Petukhina | D52: allapetukhina@icloud.com | E52: Germany (DE) | F52: Member | G52: =IFERROR(__xludf.DUMMYFUNCTION("split(E52,"" "")"),"Germany") -> Germany | H52: =IFERROR(__xludf.DUMMYFUNCTION("""COMPUTED_VALUE"""),"(DE)") -> (DE) | I52: =vlookup(G52,'All Countries'!$A$1:$B$40,2,false) -> Germany
A53: Wolfgang | B53: Härdle | D53: haerdle@hu-berlin.de | E53: Germany (DE) | F53: Member | G53: =IFERROR(__xludf.DUMMYFUNCTION("split(E53,"" "")"),"Germany") -> Germany | H53: =IFERROR(__xludf.DUMMYFUNCTION("""COMPUTED_VALUE"""),"(DE)") -> (DE) | I53: =vlookup(G53,'All Countries'!$A$1:$B$40,2,false) -> Germany
A54: Natalie | B54: Packham | D54: packham@hwr-berlin.de | E54: Germany (DE) | F54: not nominated | G54: =IFERROR(__xludf.DUMMYFUNCTION("split(E54,"" "")"),"Germany") -> Germany | H54: =IFERROR(__xludf.DUMMYFUNCTION("""COMPUTED_VALUE"""),"(DE)") -> (DE) | I54: =vlookup(G54,'All Countries'!$A$1:$B$40,2,false) -> Germany
A55: Danial | B55: Saef | D55: danial.saef@hu-berlin.de | E55: Germany (DE) | F55: not nominated | G55: =IFERROR(__xludf.DUMMYFUNCTION("split(E55,"" "")"),"Germany") -> Germany | H55: =IFERROR(__xludf.DUMMYFUNCTION("""COMPUTED_VALUE"""),"(DE)") -> (DE) | I55: =vlookup(G55,'All Countries'!$A$1:$B$40,2,false) -> Germany
A56: Rui | B56: Ren | D56: rui.ren@hu-berlin.de | E56: Germany (DE) | F56: not nominated | G56: =IFERROR(__xludf.DUMMYFUNCTION("split(E56,"" "")"),"Germany") -> Germany | H56: =IFERROR(__xludf.DUMMYFUNCTION("""COMPUTED_VALUE"""),"(DE)") -> (DE) | I56: =vlookup(G56,'All Countries'!$A$1:$B$40,2,false) -> Germany
A57: Min-Bin | B57: Lin | D57: min-bin.lin@hu-berlin.de | E57: Germany (DE) | F57: not nominated | G57: =IFERROR(__xludf.DUMMYFUNCTION("split(E57,"" "")"),"Germany") -> Germany | H57: =IFERROR(__xludf.DUMMYFUNCTION("""COMPUTED_VALUE"""),"(DE)") -> (DE) | I57: =vlookup(G57,'All Countries'!$A$1:$B$40,2,false) -> Germany
A58: Ioannis | B58: Emiris | D58: emiris@di.uoa.gr | E58: Greece (EL) | F58: not nominated | G58: =IFERROR(__xludf.DUMMYFUNCTION("split(E58,"" "")"),"Greece") -> Greece | H58: =IFERROR(__xludf.DUMMYFUNCTION("""COMPUTED_VALUE"""),"(EL)") -> (EL) | I58: =vlookup(G58,'All Countries'!$A$1:$B$40,2,false) -> Greece
A59: Veni | B59: Arakelian | D59: veniarakelian@yahoo.com | E59: Greece (EL) | F59: Member | G59: =IFERROR(__xludf.DUMMYFUNCTION("split(E59,"" "")"),"Greece") -> Greece | H59: =IFERROR(__xludf.DUMMYFUNCTION("""COMPUTED_VALUE"""),"(EL)") -> (EL) | I59: =vlookup(G59,'All Countries'!$A$1:$B$40,2,false) -> Greece
A60: Vasiliki | B60: Skintzi | D60: vikiski@uop.gr | E60: Greece (EL) | F60: not nominated | G60: =IFERROR(__xludf.DUMMYFUNCTION("split(E60,"" "")"),"Greece") -> Greece | H60: =IFERROR(__xludf.DUMMYFUNCTION("""COMPUTED_VALUE"""),"(EL)") -> (EL) | I60: =vlookup(G60,'All Countries'!$A$1:$B$40,2,false) -> Greece
A61: Thomas | B61: DASAKLIS | D61: dasaklis@unipi.gr | E61: Greece (EL) | F61: not nominated | G61: =IFERROR(__xludf.DUMMYFUNCTION("split(E61,"" "")"),"Greece") -> Greece | H61: =IFERROR(__xludf.DUMMYFUNCTION("""COMPUTED_VALUE"""),"(EL)") -> (EL) | I61: =vlookup(G61,'All Countries'!$A$1:$B$40,2,false) -> Greece
A62: Apostolos | B62: Chalkis | D62: tolis.chal@gmail.com | E62: Greece (EL) | F62: not nominated | G62: =IFERROR(__xludf.DUMMYFUNCTION("split(E62,"" "")"),"Greece") -> Greece | H62: =IFERROR(__xludf.DUMMYFUNCTION("""COMPUTED_VALUE"""),"(EL)") -> (EL) | I62: =vlookup(G62,'All Countries'!$A$1:$B$40,2,false) -> Greece
A63: Paraskevi | B63: Tsoutsa | D63: tsoutsa@teilar.gr | E63: Greece (EL) | F63: not nominated | G63: =IFERROR(__xludf.DUMMYFUNCTION("split(E63,"" "")"),"Greece") -> Greece | H63: =IFERROR(__xludf.DUMMYFUNCTION("""COMPUTED_VALUE"""),"(EL)") -> (EL) | I63: =vlookup(G63,'All Countries'!$A$1:$B$40,2,false) -> Greece
A64: Anh Tuan | B64: Trinh | D64: trinhanhtuan247@gmail.com | E64: Hungary (HU) | F64: Member | G64: =IFERROR(__xludf.DUMMYFUNCTION("split(E64,"" "")"),"Hungary") -> Hungary | H64: =IFERROR(__xludf.DUMMYFUNCTION("""COMPUTED_VALUE"""),"(HU)") -> (HU) | I64: =vlookup(G64,'All Countries'!$A$1:$B$40,2,false) -> Hungary
A65: Anita | B65: Pelle | D65: pelle@eco.u-szeged.hu | E65: Hungary (HU) | F65: Member | G65: =IFERROR(__xludf.DUMMYFUNCTION("split(E65,"" "")"),"Hungary") -> Hungary | H65: =IFERROR(__xludf.DUMMYFUNCTION("""COMPUTED_VALUE"""),"(HU)") -> (HU) | I65: =vlookup(G65,'All Countries'!$A$1:$B$40,2,false) -> Hungary
A66: Bálint | B66: Molnár | D66: molnarba@inf.elte.hu | E66: Hungary (HU) | F66: substitute MC member | G66: =IFERROR(__xludf.DUMMYFUNCTION("split(E66,"" "")"),"Hungary") -> Hungary | H66: =IFERROR(__xludf.DUMMYFUNCTION("""COMPUTED_VALUE"""),"(HU)") -> (HU) | I66: =vlookup(G66,'All Countries'!$A$1:$B$40,2,false) -> Hungary
A67: Meriem | B67: Kherbouche | D67: meriemkherbouche@inf.elte.hu | E67: Hungary (HU) | F67: not nominated | G67: =IFERROR(__xludf.DUMMYFUNCTION("split(E67,"" "")"),"Hungary") -> Hungary | H67: =IFERROR(__xludf.DUMMYFUNCTION("""COMPUTED_VALUE"""),"(HU)") -> (HU) | I67: =vlookup(G67,'All Countries'!$A$1:$B$40,2,false) -> Hungary
A68: Rita | B68: Bán | D68: banbernadett@inf.elte.hu | E68: Hungary (HU) | F68: not nominated | G68: =IFERROR(__xludf.DUMMYFUNCTION("split(E68,"" "")"),"Hungary") -> Hungary | H68: =IFERROR(__xludf.DUMMYFUNCTION("""COMPUTED_VALUE"""),"(HU)") -> (HU)
A69: Mohammad | B69: Hamdaqa | D69: mhamdaqa@ru.is | E69: Iceland (IS) | F69: not nominated | G69: =IFERROR(__xludf.DUMMYFUNCTION("split(E69,"" "")"),"Iceland") -> Iceland | H69: =IFERROR(__xludf.DUMMYFUNCTION("""COMPUTED_VALUE"""),"(IS)") -> (IS) | I69: =vlookup(G69,'All Countries'!$A$1:$B$40,2,false) -> #N/A
A70: Hanna Kristín | B70: Skaftadóttir | D70: hks7@hi.is | E70: Iceland (IS) | F70: Member | G70: =IFERROR(__xludf.DUMMYFUNCTION("split(E70,"" "")"),"Iceland") -> Iceland | H70: =IFERROR(__xludf.DUMMYFUNCTION("""COMPUTED_VALUE"""),"(IS)") -> (IS) | I70: =vlookup(G70,'All Countries'!$A$1:$B$40,2,false) -> #N/A
A71: María | B71: Óskarsdóttir | D71: mariaoskars@ru.is | E71: Iceland (IS) | F71: Member | G71: =IFERROR(__xludf.DUMMYFUNCTION("split(E71,"" "")"),"Iceland") -> Iceland | H71: =IFERROR(__xludf.DUMMYFUNCTION("""COMPUTED_VALUE"""),"(IS)") -> (IS) | I71: =vlookup(G71,'All Countries'!$A$1:$B$40,2,false) -> #N/A
A72: Rupel | B72: Nargunam | D72: rupelnargunam25@gmail.com | E72: India (IN) | F72: not nominated | G72: =IFERROR(__xludf.DUMMYFUNCTION("split(E72,"" "")"),"India") -> India | H72: =IFERROR(__xludf.DUMMYFUNCTION("""COMPUTED_VALUE"""),"(IN)") -> (IN) | I72: =vlookup(G72,'All Countries'!$A$1:$B$40,2,false) -> #N/A
A73: Valerio | B73: Poti | D73: valerio.poti@ucd.ie | E73: Ireland (IE) | F73: Member | G73: =IFERROR(__xludf.DUMMYFUNCTION("split(E73,"" "")"),"Ireland") -> Ireland | H73: =IFERROR(__xludf.DUMMYFUNCTION("""COMPUTED_VALUE"""),"(IE)") -> (IE) | I73: =vlookup(G73,'All Countries'!$A$1:$B$40,2,false) -> Ireland
A74: Maria | B74: Moloney | D74: maria.moloney@ucd.ie | E74: Ireland (IE) | F74: not nominated | G74: =IFERROR(__xludf.DUMMYFUNCTION("split(E74,"" "")"),"Ireland") -> Ireland | H74: =IFERROR(__xludf.DUMMYFUNCTION("""COMPUTED_VALUE"""),"(IE)") -> (IE) | I74: =vlookup(G74,'All Countries'!$A$1:$B$40,2,false) -> Ireland
A75: Don | B75: Bredin | D75: don.bredin@ucd.ie | E75: Ireland (IE) | F75: Member | G75: =IFERROR(__xludf.DUMMYFUNCTION("split(E75,"" "")"),"Ireland") -> Ireland | H75: =IFERROR(__xludf.DUMMYFUNCTION("""COMPUTED_VALUE"""),"(IE)") -> (IE) | I75: =vlookup(G75,'All Countries'!$A$1:$B$40,2,false) -> Ireland
A76: Vassilios | B76: Papavassiliou | D76: vassilios.papavassiliou@ucd.ie | E76: Ireland (IE) | F76: not nominated | G76: =IFERROR(__xludf.DUMMYFUNCTION("split(E76,"" "")"),"Ireland") -> Ireland | H76: =IFERROR(__xludf.DUMMYFUNCTION("""COMPUTED_VALUE"""),"(IE)") -> (IE) | I76: =vlookup(G76,'All Countries'!$A$1:$B$40,2,false) -> Ireland
A77: Jamal | B77: Abdul Nasir | D77: jamal.nasir@nuigalway.ie | E77: Ireland (IE) | F77: not nominated | G77: =IFERROR(__xludf.DUMMYFUNCTION("split(E77,"" "")"),"Ireland") -> Ireland | H77: =IFERROR(__xludf.DUMMYFUNCTION("""COMPUTED_VALUE"""),"(IE)") -> (IE) | I77: =vlookup(G77,'All Countries'!$A$1:$B$40,2,false) -> Ireland
A78: Lennart John | B78: Baals | D78: baalsl@tcd.ie | E78: Ireland (IE) | F78: not nominated | G78: =IFERROR(__xludf.DUMMYFUNCTION("split(E78,"" "")"),"Ireland") -> Ireland | H78: =IFERROR(__xludf.DUMMYFUNCTION("""COMPUTED_VALUE"""),"(IE)") -> (IE) | I78: =vlookup(G78,'All Countries'!$A$1:$B$40,2,false) -> Ireland
A79: Yosi | B79: KELLER | D79: yosi.keller@gmail.com | E79: Israel (IL) | F79: Member | G79: =IFERROR(__xludf.DUMMYFUNCTION("split(E79,"" "")"),"Israel") -> Israel | H79: =IFERROR(__xludf.DUMMYFUNCTION("""COMPUTED_VALUE"""),"(IL)") -> (IL) | I79: =vlookup(G79,'All Countries'!$A$1:$B$40,2,false) -> #N/A
A80: Aviv | B80: Gibali | D80: avivg@braude.ac.il | E80: Israel (IL) | F80: Member | G80: =IFERROR(__xludf.DUMMYFUNCTION("split(E80,"" "")"),"Israel") -> Israel | H80: =IFERROR(__xludf.DUMMYFUNCTION("""COMPUTED_VALUE"""),"(IL)") -> (IL) | I80: =vlookup(G80,'All Countries'!$A$1:$B$40,2,false) -> #N/A
A81: Abraham | B81: Weinberg | D81: abraham-itzhak.weinberg@biu.ac.il | E81: Israel (IL) | F81: not nominated | G81: =IFERROR(__xludf.DUMMYFUNCTION("split(E81,"" "")"),"Israel") -> Israel | H81: =IFERROR(__xludf.DUMMYFUNCTION("""COMPUTED_VALUE"""),"(IL)") -> (IL) | I81: =vlookup(G81,'All Countries'!$A$1:$B$40,2,false) -> #N/A
A82: Paolo | B82: Giudici | D82: giudici@unipv.it | E82: Italy (IT) | F82: not nominated | G82: =IFERROR(__xludf.DUMMYFUNCTION("split(E82,"" "")"),"Italy") -> Italy | H82: =IFERROR(__xludf.DUMMYFUNCTION("""COMPUTED_VALUE"""),"(IT)") -> (IT) | I82: =vlookup(G82,'All Countries'!$A$1:$B$40,2,false) -> Italy
A83: Luca | B83: Di Persio | D83: luca.dipersio@univr.it | E83: Italy (IT) | F83: not nominated | G83: =IFERROR(__xludf.DUMMYFUNCTION("split(E83,"" "")"),"Italy") -> Italy | H83: =IFERROR(__xludf.DUMMYFUNCTION("""COMPUTED_VALUE"""),"(IT)") -> (IT) | I83: =vlookup(G83,'All Countries'!$A$1:$B$40,2,false) -> Italy
A84: Daniele | B84: Marazzina | D84: daniele.marazzina@polimi.it | E84: Italy (IT) | F84: not nominated | G84: =IFERROR(__xludf.DUMMYFUNCTION("split(E84,"" "")"),"Italy") -> Italy | H84: =IFERROR(__xludf.DUMMYFUNCTION("""COMPUTED_VALUE"""),"(IT)") -> (IT) | I84: =vlookup(G84,'All Countries'!$A$1:$B$40,2,false) -> Italy
A85: NadiaConcetta | B85: Fabrizio | D85: nadia.fabrizio@cefriel.com | E85: Italy (IT) | F85: not nominated | G85: =IFERROR(__xludf.DUMMYFUNCTION("split(E85,"" "")"),"Italy") -> Italy | H85: =IFERROR(__xludf.DUMMYFUNCTION("""COMPUTED_VALUE"""),"(IT)") -> (IT) | I85: =vlookup(G85,'All Countries'!$A$1:$B$40,2,false) -> Italy
A86: Claudia | B86: Tarantola | D86: claudia.tarantola@unipv.it | E86: Italy (IT) | F86: Member | G86: =IFERROR(__xludf.DUMMYFUNCTION("split(E86,"" "")"),"Italy") -> Italy | H86: =IFERROR(__xludf.DUMMYFUNCTION("""COMPUTED_VALUE"""),"(IT)") -> (IT) | I86: =vlookup(G86,'All Countries'!$A$1:$B$40,2,false) -> Italy
A87: Federica | B87: Miglietta | D87: federica.miglietta@uniba.it | E87: Italy (IT) | F87: not nominated | G87: =IFERROR(__xludf.DUMMYFUNCTION("split(E87,"" "")"),"Italy") -> Italy | H87: =IFERROR(__xludf.DUMMYFUNCTION("""COMPUTED_VALUE"""),"(IT)") -> (IT) | I87: =vlookup(G87,'All Countries'!$A$1:$B$40,2,false) -> Italy
A88: Barbara | B88: Alemanni | D88: alemanni@economia.unige.it | E88: Italy (IT) | F88: Member | G88: =IFERROR(__xludf.DUMMYFUNCTION("split(E88,"" "")"),"Italy") -> Italy | H88: =IFERROR(__xludf.DUMMYFUNCTION("""COMPUTED_VALUE"""),"(IT)") -> (IT) | I88: =vlookup(G88,'All Countries'!$A$1:$B$40,2,false) -> Italy
A89: Alessandra | B89: Tanda | D89: alessandra.tanda@unipv.it | E89: Italy (IT) | F89: not nominated | G89: =IFERROR(__xludf.DUMMYFUNCTION("split(E89,"" "")"),"Italy") -> Italy | H89: =IFERROR(__xludf.DUMMYFUNCTION("""COMPUTED_VALUE"""),"(IT)") -> (IT) | I89: =vlookup(G89,'All Countries'!$A$1:$B$40,2,false) -> Italy
A90: Luca | B90: Trapin | D90: luca.trapin@unibo.it | E90: Italy (IT) | F90: not nominated | G90: =IFERROR(__xludf.DUMMYFUNCTION("split(E90,"" "")"),"Italy") -> Italy | H90: =IFERROR(__xludf.DUMMYFUNCTION("""COMPUTED_VALUE"""),"(IT)") -> (IT) | I90: =vlookup(G90,'All Countries'!$A$1:$B$40,2,false) -> Italy
A91: Maria | B91: Iannario | D91: maria.iannario@unina.it | E91: Italy (IT) | F91: not nominated | G91: =IFERROR(__xludf.DUMMYFUNCTION("split(E91,"" "")"),"Italy") -> Italy | H91: =IFERROR(__xludf.DUMMYFUNCTION("""COMPUTED_VALUE"""),"(IT)") -> (IT) | I91: =vlookup(G91,'All Countries'!$A$1:$B$40,2,false) -> Italy
A92: Simona | B92: Cosma | D92: simona.cosma@unisalento.it | E92: Italy (IT) | F92: not nominated | G92: =IFERROR(__xludf.DUMMYFUNCTION("split(E92,"" "")"),"Italy") -> Italy | H92: =IFERROR(__xludf.DUMMYFUNCTION("""COMPUTED_VALUE"""),"(IT)") -> (IT) | I92: =vlookup(G92,'All Countries'!$A$1:$B$40,2,false) -> Italy
A93: Francesca | B93: Grassetti | D93: francesca.grassetti@polimi.it | E93: Italy (IT) | F93: not nominated | G93: =IFERROR(__xludf.DUMMYFUNCTION("split(E93,"" "")"),"Italy") -> Italy | H93: =IFERROR(__xludf.DUMMYFUNCTION("""COMPUTED_VALUE"""),"(IT)") -> (IT) | I93: =vlookup(G93,'All Countries'!$A$1:$B$40,2,false) -> Italy
A94: Luisa | B94: Anderloni | D94: luisa.anderloni@unimi.it | E94: Italy (IT) | F94: not nominated | G94: =IFERROR(__xludf.DUMMYFUNCTION("split(E94,"" "")"),"Italy") -> Italy | H94: =IFERROR(__xludf.DUMMYFUNCTION("""COMPUTED_VALUE"""),"(IT)") -> (IT) | I94: =vlookup(G94,'All Countries'!$A$1:$B$40,2,false) -> Italy
A95: Kadri | B95: Sylejmani | D95: kadri.sylejmani@uni-pr.edu | E95: Kosovo* (KV) | F95: not nominated | G95: =IFERROR(__xludf.DUMMYFUNCTION("split(E95,"" "")"),"Kosovo*") -> Kosovo* | H95: =IFERROR(__xludf.DUMMYFUNCTION("""COMPUTED_VALUE"""),"(KV)") -> (KV) | I95: =vlookup(G95,'All Countries'!$A$1:$B$40,2,false) -> #N/A
A96: Albulena | B96: Shala | D96: albulena.shala@uni-pr.edu | E96: Kosovo* (KV) | F96: not nominated | G96: =IFERROR(__xludf.DUMMYFUNCTION("split(E96,"" "")"),"Kosovo*") -> Kosovo* | H96: =IFERROR(__xludf.DUMMYFUNCTION("""COMPUTED_VALUE"""),"(KV)") -> (KV) | I96: =vlookup(G96,'All Countries'!$A$1:$B$40,2,false) -> #N/A
A97: Dashmir | B97: Istrefi | D97: dashmir.istrefi@hoyo.tech | E97: Kosovo* (KV) | F97: not nominated | G97: =IFERROR(__xludf.DUMMYFUNCTION("split(E97,"" "")"),"Kosovo*") -> Kosovo* | H97: =IFERROR(__xludf.DUMMYFUNCTION("""COMPUTED_VALUE"""),"(KV)") -> (KV) | I97: =vlookup(G97,'All Countries'!$A$1:$B$40,2,false) -> #N/A
A98: Ramona | B98: Rupeika-Apoga | D98: rr@lu.lv | E98: Latvia (LV) | F98: Member | G98: =IFERROR(__xludf.DUMMYFUNCTION("split(E98,"" "")"),"Latvia") -> Latvia | H98: =IFERROR(__xludf.DUMMYFUNCTION("""COMPUTED_VALUE"""),"(LV)") -> (LV) | I98: =vlookup(G98,'All Countries'!$A$1:$B$40,2,false) -> Latvia
A99: Kristina | B99: Šutienė | D99: kristina.sutiene@ktu.lt | E99: Lithuania (LT) | F99: Member | G99: =IFERROR(__xludf.DUMMYFUNCTION("split(E99,"" "")"),"Lithuania") -> Lithuania | H99: =IFERROR(__xludf.DUMMYFUNCTION("""COMPUTED_VALUE"""),"(LT)") -> (LT) | I99: =vlookup(G99,'All Countries'!$A$1:$B$40,2,false) -> Lithuania
A100: Audrius | B100: Kabašinskas | D100: audrius.kabasinskas@ktu.lt | E100: Lithuania (LT) | F100: not nominated | G100: =IFERROR(__xludf.DUMMYFUNCTION("split(E100,"" "")"),"Lithuania") -> Lithuania | H100: =IFERROR(__xludf.DUMMYFUNCTION("""COMPUTED_VALUE"""),"(LT)") -> (LT) | I100: =vlookup(G100,'All Countries'!$A$1:$B$40,2,false) -> Lithuania
...

Sheet Country coordinator for Progres
A1: Country Coordinator for the progress report. At least one per country
A2: Country | B2: Responsible | C2: email to fill in report sent | D2: reminder sent | E2: 2nd reminder sent | F2: 3rd reminder sent | G2: Coordinator 1 | H2: Coordinator 2 | I2: Coordinator 3 | J2: Link | K2: Please add the link to your copy of the report
A3: https://docs.google.com/document/d/1Y0w27959kx0P0g-7Fgd3cu4Yd46gZ2OFnh4FJUsgIS8/edit# | G3: email | H3: email | I3: email | J3: Link to country report | K3: Template report to be copied: https://docs.google.com/document/d/1Y0w27959kx0P0g-7Fgd3cu4Yd46gZ2OFnh4FJUsgIS8/edit#heading=h.2mpvn8bbm5w6
A4: Albania (AL) | B4: joerg | C4: y | G4: rezartaperri@feut.edu.al | J4: https://docs.google.com/document/d/1iOZrM7AnjALr_yjkkJOtuyzlYeNvi_Xs4ehVZQZNGaA/edit#heading=h.32e7gxn6ztmt
A5: Algeria (DZ) | B5: n
A6: Austria (AT) | B6: joerg | C6: y | D6: y | E6: y | G6: ronald.hochreiter@wu.ac.at | J6: AUSTRIA COST FinAI Progress Report GP1 and GP2
A7: Belgium (BE) | B7: joerg | C7: y | E7: y | G7: christian.hafner@uclouvain.be | J7: https://docs.google.com/document/d/1y36UVVrMeOXD3s3liJ7ecwAvajoizWXoAe_Bli9Wys8/edit#heading=h.32e7gxn6ztmt
A8: Bosnia and Herzegovina (BA) | B8: joerg | C8: y | E8: y | G8: jelena.poljasevic@ef.unibl.org | H8: igor.todorovic@ef.unibl.org | J8: dont want to write a report
A9: Bulgaria (BG) | B9: joerg | C9: y | D9: y | E9: y | G9: ygorbounov@nbu.bg | J9: https://docs.google.com/document/d/1oO7bb8LGn88X4S9V7P6NAFD765PrfGRM/edit?usp=sharing&ouid=105279148080483818425&rtpof=true&sd=true
A10: Croatia (HR) | B10: joerg | C10: y | E10: y | G10: aivanisev@net.efzg.hr | J10: https://docs.google.com/document/d/1lrRwi7e_8bFQB39NKm4DgD-tgEZI6hcY/edit#
A11: Cyprus (CY) | B11: joerg | C11: y | D11: y | E11: y | F11: y | G11: georgiou.i@unic.ac.cy | H11: loizos@ouc.ac.cy | I11: andreas.gregoriades@cut.ac.cy | J11: https://docs.google.com/document/d/18jME8nOvpYpCJZtKBuItQSCE33jCXDtyfpp5GE9rN8s/edit#
A12: Czech Republic (CZ) | B12: joerg | C12: y | E12: y | F12: y | G12: oleg@muni.cz | J12: https://docs.google.com/document/d/1YPxHBY2v8zGAL2bDBYXSWlD74VCGJwS7FduI8T_YJ6c/edit#heading=h.3l5zvva7l0gu
A13: Denmark (DK) | B13: joerg | C13: y | D13: y | G13: drm.eco@cbs.dk | H13: ai@ece.au.dk | J13: https://docs.google.com/document/d/10xC_zEA3APqy0OqtIWPDivF9XtI20Y16Vy2BLWqqvQM/edit#heading=h.32e7gxn6ztmt
A14: Estonia (EE) | B14: Branka | D14: y | G14: innar.liiv@taltech.ee
A15: Finland (FI) | B15: Branka | D15: y
A16: France (FR) | B16: Valerio | C16: y | D16: y | J16: https://docs.google.com/document/d/1s2FJdQyUJl4b_POWwJvYLueVupqzezUc2EGpuq5Zpy0/edit?usp=sharing
A17: Germany (DE) | B17: Valerio | C17: y | D17: y | G17: alla.petukhina@htw-berlin.de | H17: haerdle@hu-berlin.de | J17: https://docs.google.com/document/d/140mQ2ePur80UbqIjNI2w4RpgqtqLjWTlspFwqMBxqAY/edit?usp=sharing
A18: Greece (EL) | B18: Valerio | C18: y | D18: y | G18: Veniarakelian@yahoo.com
A19: Hungary (HU) | B19: Valerio | C19: y | D19: y | G19: tuan.trinh@eitdigital.eu | H19: pelle@eco.u-szeged.hu | I19: molnarba@inf.elte.hu | J19: https://docs.google.com/document/d/1zCJ0b3kScjtx6c3xAdEpjorVLjTmPsBdOCqavMGs1OA/edit?usp=sharing
A20: Iceland (IS) | B20: Valerio | D20: y | G20: hks7@hi.is | J20: https://docs.google.com/document/d/1Rw1CF21ASPSzI_Q7HIjCUI-RS1wizLlwmND2ob-cgeg/edit#heading=h.32e7gxn6ztmt
A21: India (IN) | B21: Valerio | C21: y | D21: y | G21: rupelnargunam25@gmail.com | J21: https://docs.google.com/document/d/1cIIZXssqNfgArRh5nNxZxjot95C4U3X7wKvnAZSLoHc/edit?usp=sharing
A22: Ireland (IE) | B22: Valerio | D22: y | G22: alessia.paccagnini@ucd.ie | J22: https://docs.google.com/document/d/1puJMR1go9Ff5Zce1XB4nOD6c4XMiyMgva0Ximavhcx0/edit
A23: Israel (IL) | B23: Valerio | D23: y
A24: Italy (IT) | B24: Valerio | D24: y | G24: daniele.marazzina@polimi.it | J24: https://docs.google.com/document/d/1NFE0Qk8SF_guVBBbSwM5ReFXamp0f5FVPs7lceulR5c/edit?usp=sharing
A25: Kosovo* (KV) | B25: Petre | D25: y
A26: Latvia (LV) | B26: Petre | D26: y
A27: Lithuania (LT) | B27: Petre | D27: y | G27: kristina
A28: Luxembourg (LU) | B28: Petre | D28: y
A29: Malta (MT) | B29: Petre | G29: dbevan@stmartins.edu
A30: Moldova (MD) | B30: Petre | D30: y
A31: Montenegro (ME) | B31: Ioana | D31: y | E31: y
A32: Netherlands (NL) | B32: Ioana | D32: y | E32: y
A33: New Zealand (NZ) | B33: Ioana | D33: y | E33: y
A34: North Macedonia (MK) | B34: Ioana | D34: n | E34: y | G34: lameski@finki.ukim.mk | J34: https://docs.google.com/document/d/1TxnRdadvV30loGWMaMJ5HyooUFrIfRZdFVoSFqDQeRA/edit?usp=sharing
A35: Norway (NO) | B35: Ioana | D35: y | E35: y | G35: per.b.solibakke@ntnu.no | J35: https://docs.google.com/document/d/15aJpyctdKGChmTmZvojNtLrPXKc0UHXT0P2g6azpWos/edit?usp=sharing
A36: Palestine** (PS) | B36: n | D36: y
A37: Poland (PL) | B37: Ana | D37: y | G37: pwojcik@wne.uw.edu.pl | J37: https://docs.google.com/document/d/1g0peRJ3XNgu30mCtF8ryr7RWUX1eSjAe/edit?usp=sharing&ouid=100307204068834796883&rtpof=true&sd=true
A38: Portugal (PT) | B38: Ana | D38: y | G38: joana@fe.uc.pt | H38: bribeiro@dei.uc.pt | I38: catarina@dei.uc.pt | J38: https://docs.google.com/document/d/165BiTMN2cpdH9UaH1EoZ4gcPsFYYHuL6T6L7TAy2sZw/edit#heading=h.32e7gxn6ztmt
A39: Romania (RO) | B39: Ana | G39: danpele@ase.ro | J39: https://docs.google.com/document/d/154fyD4OXUepnaxETMyAcJDFOiPuJhIv2/edit?usp=sharing&ouid=114838286075587525311&rtpof=true&sd=true
A40: Serbia (RS) | B40: Ana | D40: y | G40: vladimir.simovic@ien.bg.ac.rs | J40: https://docs.google.com/document/d/1CwocoD6YQq1Nz_XIavnC81e92psgkVAR/edit#heading=h.gjdgxs
A41: Singapore (SG) | B41: n
A42: Slovakia (SK) | B42: Ana | D42: y | G42: jana.peliova@euba.sk | J42: https://docs.google.com/document/d/1RXh0FtykIGpPB9L7O8TSTJ8tTOjXQcSB/edit
A43: Slovenia (SI) | B43: Ana | G43: denis.trcek@fri.uni-lj.si | J43: https://docs.google.com/document/d/13H0x92x_1CnXmz1W38Yyl9RgCUuEa9gjrkmjVvU92qE/edit?usp=sharing
A44: Spain (ES) | B44: Ana | D44: y | G44: javier.arroyo@fdi.ucm.es | J44: https://docs.google.com/document/d/1YIExduOhquNsFWPWwnBZg9Tn2GQ8SevvT-MU68x97cQ/edit#
A45: Sweden (SE) | B45: Branka | D45: y
A46: Switzerland (CH) | B46: Branka | G46: all CH members
A47: Switzerland (CH) | B47: Peter | G47: scwp@zhaw.ch | J47: https://docs.google.com/document/d/1uYG9HhIzCTZ1EDZC3G-eH4Yia8KFFpk2dScGNVDIA_Y/edit#heading=h.gjdgxs
A48: Taiwan (TW) | B48: n
A49: Turkey (TR) | B49: Branka | D49: y | G49: belma.ozturkkal@khas.edu.tr | J49: https://docs.google.com/document/d/1Av8VJLbeUocD7klHcIvLvVr_JCGFxjap/edit?usp=sharing&ouid=116591962908536436994&rtpof=true&sd=true | K49: https://docs.google.com/presentation/d/1vNClf1_yMVSIljvjaHS49utYK4Py0Juh/edit?usp=sharing&ouid=116591962908536436994&rtpof=true&sd=true
A50: Turkey (TR) | B50: Branka | I50: etalasli@selcuk.edu.tr | J50: https://docs.google.com/document/d/1-opk_sBx_lDHkVqf8APVDfvIh3mvlj10/edit#
A51: United Arab Emirates (AE) | B51: n
A52: United Kingdom (UK) | B52: Branka | D52: y
A53: Vietnam (VN) | B53: n | G53: sam.goundar@gmail.com | J53: https://docs.google.com/document/d/1Xbc1HA5kamGsx31WRNKZDYFTOwyMCiYduwVKA2mNWsE/edit#heading=h.32e7gxn6ztmt
A54: Working Group (WG) | J54: https://docs.google.com/document/d/1gCX7wuxcol0bB34DWD_VhJ0it7Aww1algEeVeVDCWrw/edit?usp=sharing
A55: Diversity | B55: Alessandra | G55: alessandra.tanda@unipv.it | J55: https://docs.google.com/document/d/1nQUCSv0YWMkRowrQU44uzVweUoCf0Cl8aUw78bj0V9o/edit#heading=h.32e7gxn6ztmt
J56: https://docs.google.com/document/d/1nQUCSv0YWMkRowrQU44uzVweUoCf0Cl8aUw78bj0V9o/edit
A58: Scienctifi Communication | B58: Alessia | D58: y | E58: y | G58: Alessia Paccagnini <alessia.paccagnini@ucd.ie> | H58: daniele.marazzina@polimi.it

Sheet DOIs
A1: Country | B1: DOI of work (paper or anything else) | C1: Added to e-cost tools? | D1: Email of Contact person | E1: Added to online report? (Yiting) | F1: COST Acknowledgement | G1: Citation (ONLY IF NO DOI up to now, otherwise, not needed)
A2: Albania | B2: 10.13189/ujaf.2020.080402 | C2: No | D2: llesh.lleshaj@unitir.edu.al | E2: N | F2: no | G2: Llesh Lleshaj , Alban Korbi (2020). Portfolio Selection and VaR Estimation: Evidence from Western Balkan Countries. Universal Journal of Accounting and Finance, 8(4), 92 - 102. DOI: 10.13189/ujaf.2020.080402.
A3: Albania | B3: 10.34109/ijefs.20220026 | C3: No | D3: anila.voci@uniel.edu.al | E3: N | F3: no | G3: Çekrezi, A. V. (2022). Determinants of Bank Deposits in Albania. International Journal of Economics and Finance Studies, 14 (02), 101-121. doi:10.34111/ijefs. 20220026
A4: Albania | B4: 10.37394/23207.2021.18.102 | C4: No | D4: rezarta.perri@unitir.edu.al | E4: N | F4: no | G4: Rezarta Shkurti, Elfrida Manoku, "Factors of Success in Implementation of Enterprise Resource Planning Systems," WSEAS Transactions on Business and Economics, vol. 18, pp. 1084-1093, 2021
A5: Albania | B5: N/A | D5: eldaxhumari@gmail.com | F5: no | G5: Xhumari, E., Maxhelaku, S., & Xhina, E. (2022, July). A review of Knowledge Graph and Graph Neural Network application. In Proceedings of Economics and Finance Conferences (No. 13615626). International Institute of Social and Economic Sciences.
A6: Albania | D6: eldaxhumari@gmail.com | F6: no | G6: Xhumari E. COMPARING THE TECHNOLOGIES USED FOR THE APPLICATION OF ARTIFICIAL NEURAL NETWORKS. European Journal of Computer Science and Information Technology Vol.9, No.2, pp.21-28, 2021
A7: Belgium | B7: https://link.springer.com/article/10.1007/s42521-022-00054-w | C7: No | D7: christian.hafner@uclouvain.be | E7: N | F7: no | G7: Hafner, C.M., Majeri, S. Analysis of cryptocurrency connectedness based on network to transaction volume ratios. Digit Finance (2022). https://doi.org/10.1007/s42521-022-00054-w
A8: Belgium | B8: https://academic.oup.com/jfec/article/18/2/233/5133597 | C8: No | D8: christian.hafner@uclouvain.be | E8: N | F8: no | G8: Christian M Hafner, Testing for Bubbles in Cryptocurrencies with Time-Varying Volatility, Journal of Financial Econometrics, Volume 18, Issue 2, Spring 2020, Pages 233–249, https://doi.org/10.1093/jjfinec/nby023
A9: Belgium | B9: https://www.mdpi.com/1911-8074/12/2/53 | C9: No | D9: christian.hafner@uclouvain.be | E9: N | F9: no | G9: Chen, C.Y.-H.; Hafner, C.M. Sentiment-Induced Bubbles in the Cryptocurrency Market. J. Risk Financial Manag. 2019, 12, 53. https://doi.org/10.3390/jrfm12020053
A10: Belgium | B10: https://link.springer.com/content/pdf/10.1007/978-3-030-51093-0.pdf | C10: No | D10: christian.hafner@uclouvain.be | E10: Y | F10: no | G10: Van der Auwera, E., Schoutens, W., Giudici, M. P., & Alessi, L. (2020). Financial Risk Management for Cryptocurrencies. Springer International Publishing.
A11: Belgium | B11: not yet available | D11: christian.hafner@uclouvain.be | F11: yes | G11: Lin, Wang, Bocart, Hafner, Haerdle (2022) DAI: Digital Art Index, forthcoming
A12: Croatia | B12: N/A | D12: domagoj.sajter@efos.hr | F12: yes | G12: Sajter, D. (2022, May 5–6). Overseas Transaction Fees: Sending Money via Bitcoin vs. Banks [Paper presentation]. Technology, Innovation and Stability: New Directions in Finance (TINFIN), Zagreb, Croatia.
A13: Croatia | B13: N/A | D13: bozena.gulija@outlook.com | F13: yes | G13: Gulija, B., Kammel, A., & Payr, T. (2022, May 5–6). Prudential Regulation of Fintechs [Paper presentation]. Technology, Innovation and Stability: New Directions in Finance (TINFIN), Zagreb, Croatia.
A14: Croatia | B14: N/A | D14: nsimurina@efzg.hr | F14: yes | G14: Simurina, N., Kurnoga, N., & Fuckan, F. (2022, May 5–6). Performance differences between ESG indices and traditional indices [Paper presentation]. Technology, Innovation and Stability: New Directions in Finance (TINFIN), Zagreb, Croatia.
A15: Croatia | B15: N/A | D15: aivanisev@net.efzg.hr | F15: yes | G15: Dzelalija, P., & Ivanisevic Hernaus, A. (2022, August 22–24). From perceived mobility to the intention to use mobile payments: A moderated mediation analysis [Paper presentation]. FinanceCom 2022: 11th International Workshop, Enterprise Applications, Markets and Services in the Finance Industry, University of Twente, the Netherlands.
A16: Croatia | B16: N/A | D16: aivanisev@net.efzg.hr | F16: yes | G16: Ivanisevic Hernaus, A., Kristo, J., & Rako, R. (2022, May 5–6). ESG-Related Challenges in the Insurance Industry: A Multi-stakeholder Perspective [Paper presentation]. Technology, Innovation and Stability: New Directions in Finance (TINFIN), Zagreb, Croatia.
A17: Croatia | B17: https://doi.org/10.2478/crebss-2020-0007 | C17: No | D17: svlah@net.efzg.hr
A18: Croatia | B18: https://doi.org/10.4324/9781003144410-8 | C18: No | D18: svlah@net.efzg.hr
A19: Croatia | B19: https://doi.org/10.4018/978-1-7998-5083-0.ch010 | C19: No | D19: svlah@net.efzg.hr
A20: Croatia | B20: N/A | D20: svlah@net.efzg.hr | G20: Vlah Jeric, S. (2022, March 10–11). Time interval choices in forecasting direction of stock price changes using technical indicators [Paper presentation]. 29th Symposium of the Society for Nonlinear Dynamics & Econometrics, SNDE online.
A21: Croatia | B21: N/A | D21: svlah@net.efzg.hr | G21: Vlah Jeric, S. (2022, May 5–6). Time Interval Choices in The Performance Estimation of Forecasting Direction Of Stock Price Changes [Paper presentation]. Technology, Innovation and Stability: New Directions in Finance (TINFIN), Zagreb, Croatia.
A22: Croatia | B22: N/A | D22: svlah@net.efzg.hr | G22: Vlah Jeric, S. (2020, September 23–25). Evaluation of Classification Algorithms for Prediction of Stock Market Index in Day Trading [Paper presentation]. The 28th Annual Symposium of the Society for Nonlinear Dynamics and Econometrics, Zagreb, Croatia.
A23: Croatia | B23: N/A | D23: svlah@net.efzg.hr | G23: Vlah Jeric, S. (2020, October 15–16). Comparing classification algorithms for prediction on CROBEX data [Paper presentation]. The 3rd International Statistical Conference in Croatia – ISCCRO'20, Zagreb, Croatia.
A24: Croatia | B24: N/A | D24: domagoj.sajter@efos.hr | G24: Sajter, D., & Binder, B. (2020). Market Risks of the Cryptocurrency Index CRIX in Relation to S&P 500. In: J. Tica & K. Bacic (Eds.) Ekonomska politika Hrvatske u 2021. (pp. 192-206). Hrvatsko drustvo ekonomista, Zagreb, Croatia. [in Croatian]
A25: Croatia | B25: N/A | D25: bozena.gulija@outlook.com | G25: Gulija, B. (2022, June 4). Global Initiatives Regarding Prudential Treatment Of Banks’ Cryptoasset Exposures. Financial Regulation International, 25 (3). https://www.financialregulationintl.com/financial-industry/global-initiatives-regarding-prudential-treatment-of-banks-cryptoasset-exposures--1.htm
A26: Denmark | B26: doi.org/10.1007/s11634-022-00508-4 | C26: No | D26: drm.eco@cbs.dk | E26: Y | F26: no
A27: Denmark | B27: doi.org/10.1016/j.eswa.2022.117423 | C27: No | D27: drm.eco@cbs.dk | E27: Y | F27: no
A28: Denmark | B28: doi.org/10.1016/j.ejor.2021.12.022 | C28: No | D28: drm.eco@cbs.dk | E28: Y | F28: no
A29: Denmark | B29: doi.org/10.1016/j.omega.2021.102543 | C29: No | D29: drm.eco@cbs.dk | E29: Y | F29: no
A30: Denmark | B30: doi.org/10.1016/j.eswa.2021.115245 | C30: No | D30: drm.eco@cbs.dk | E30: Y | F30: no
A31: Denmark | B31: doi.org/10.1016/j.ejor.2021.04.016 | C31: No | D31: drm.eco@cbs.dk | E31: Y | F31: no
A32: Denmark | B32: doi.org/10.1016/j.cor.2021.105281 | C32: No | D32: drm.eco@cbs.dk | E32: Y | F32: no
A33: Denmark | B33: doi.org/10.1007/s11750-021-00594-1 | C33: No | D33: drm.eco@cbs.dk | E33: Y | F33: no
A34: Denmark | B34: doi.org/10.1080/00273171.2019.1677208 | C34: No | D34: drm.eco@cbs.dk | E34: N | F34: no
A35: Denmark | B35: doi.org/10.1016/j.omega.2019.05.004 | C35: No | D35: drm.eco@cbs.dk | E35: Y | F35: no
A36: Denmark | B36: doi.org/10.1016/j.ejor.2019.12.002 | C36: No | D36: drm.eco@cbs.dk | E36: Y | F36: no
A37: Estonia | B37: https://doi.org/10.1007/978-981-16-2418-6 | C37: Yes | D37: innar.liiv@taltech.ee | F37: yes | G37: * not included in the last reporting period
A38: France | B38: https://doi.org/10.1016/j.intfin.2021.101321 | C38: No | D38: roman.matkovskyy@rennes-sb.com | E38: Y | F38: no
A39: France | B39: https://doi.org/10.1016/j.irfa.2021.101958 | C39: No | D39: roman.matkovskyy@rennes-sb.com | E39: Y | F39: no
A40: France | B40: https://doi.org/10.1080/1351847X.2020.1869992 | C40: No | D40: roman.matkovskyy@rennes-sb.com | E40: Y | F40: no
A41: France | B41: https://doi.org/10.1080/00036846.2020.1854671 | C41: No | D41: roman.matkovskyy@rennes-sb.com | E41: N | F41: no
A42: France | B42: https://doi.org/10.1016/j.frl.2019.101405 | C42: No | D42: roman.matkovskyy@rennes-sb.com | E42: N | F42: no
A43: France | B43: https://doi.org/10.1016/j.qref.2020.02.004 | C43: No | D43: roman.matkovskyy@rennes-sb.com | E43: N | F43: no
A44: France | B44: https://www.jstor.org/stable/48618930 | C44: No | D44: roman.matkovskyy@rennes-sb.com | E44: N | F44: no
A45: France, Ireland | B45: https://doi.org/10.1016/j.frl.2021.102162 | C45: Yes | D45: roman.matkovskyy@rennes-sb.com | F45: yes | G45: Jalan, A., Matkovskyy, R., and Poti, V. (2022). "Shall the winning last? A study of recent bubbles and persistence." Finance Research Letters 45, 102162
A46: France | B46: https://doi.org/10.1016/j.econlet.2022.110877 | C46: Yes | D46: roman.matkovskyy@rennes-sb.com | F46: yes | G46: Jalan, A., Matkovskyy, R., Urquhart, A. (2022) Demand elasticities of Bitcoin and Ethereum. Economics Letters
A47: France, Ireland | B47: https://doi.org/10.1007/s42521-021-00045-3 | C47: Yes | D47: valerio.poti@ucd.ie | F47: yes | G47: Chen, Y., Bredin, D., Potì, V. and R. Matkovskyy, COVID risk narratives: a computational linguistic approach to the econometric identification of narrative risk during a pandemic, Digital Finance 4, pages 17-61, 2022.
A48: Germany | B48: https://doi.org/10.1214/20-AOS2019 | C48: No | D48: alla.petukhina@htw-berlin.de | E48: Y | F48: no
A49: Germany | B49: https://doi.org/10.1080/14697688.2021.1880023 | C49: No | D49: alla.petukhina@htw-berlin.de | E49: Y | F49: no
A50: Germany | B50: https://doi.org/10.1016/j.jspi.2020.10.007 | C50: No | D50: alla.petukhina@htw-berlin.de | E50: N | F50: no
A51: Germany | B51: https://doi.org/10.1111/rssc.12499 | C51: No | D51: alla.petukhina@htw-berlin.de | E51: N | F51: no
A52: Germany | B52: https://doi.org/10.1016/j.jedc.2021.104290 | C52: No | D52: alla.petukhina@htw-berlin.de | E52: Y | F52: no
A53: Germany | B53: https://doi.org/10.1016/j.irfa.2021.101915 | C53: No | D53: alla.petukhina@htw-berlin.de | E53: Y | F53: no
A54: Germany | B54: http://dx.doi.org/10.2139/ssrn.3724814 | C54: No | D54: alla.petukhina@htw-berlin.de | E54: N | F54: no
A55: Germany | B55: https://doi.org/10.1007/s42521-021-00031-9 | C55: No | D55: alla.petukhina@htw-berlin.de | E55: N | F55: no
A56: Germany | B56: https://doi.org/10.1007/s42521-021-00043-5 | C56: No | D56: alla.petukhina@htw-berlin.de | E56: N | F56: no
A57: Germany | B57: https://doi.org/10.1007/s43546-021-00057-6 | C57: No | D57: alla.petukhina@htw-berlin.de | E57: N | F57: no
A58: Germany | B58: https://doi.org/10.1007/978-3-030-73443-5_94-1 | C58: Yes | D58: alla.petukhina@htw-berlin.de | F58: yes
A59: Germany | B59: https://doi.org/10.48550/arXiv.2208.12614 | C59: Yes | D59: alla.petukhina@htw-berlin.de | F59: yes
A60: Germany | B60: https://doi.org/10.1016/j.ribaf.2021.101594 | C60: Yes | D60: alla.petukhina@htw-berlin.de | F60: yes
A61: Germany | B61: http://dx.doi.org/10.2139/ssrn.3809329 | C61: Yes | D61: alla.petukhina@htw-berlin.de | F61: yes
A62: Germany | B62: https://doi.org/10.48550/arXiv.2107.08808 | C62: Yes | D62: alla.petukhina@htw-berlin.de | F62: yes
A63: Germany | B63: https://dx.doi.org/10.2139/ssrn.3911490 | C63: Yes | D63: alla.petukhina@htw-berlin.de | F63: yes
A64: Germany | B64: https://doi.org/10.1007/s42521-022-00048-8 | C64: Yes | D64: alla.petukhina@htw-berlin.de | F64: yes
A65: Germany | B65: https://doi.org/10.1007/s10614-021-10113-w | C65: Yes | D65: alla.petukhina@htw-berlin.de | F65: yes
A66: Germany | B66: http://dx.doi.org/10.2139/ssrn.3987941 | C66: Yes | D66: alla.petukhina@htw-berlin.de | F66: yes
A67: Germany | B67: http://dx.doi.org/10.2139/ssrn.4209433 | C67: Yes | D67: alla.petukhina@htw-berlin.de | F67: yes
A68: Germany | B68: https://doi.org/10.1142/S0217590822480010 | C68: Yes | D68: alla.petukhina@htw-berlin.de | F68: yes
A69: Germany | B69: https://doi.org/10.48550/arXiv.2108.05721 | C69: Yes | D69: alla.petukhina@htw-berlin.de | F69: yes
... A76: Germany | B76: https://doi.org/10.48550/arXiv.2108.11921 | C76: Yes | D76: alla.petukhina@htw-berlin.de | F76: yes
A77: Germany | B77: 10.6293/AQAFA.202112_(18).0006 | C77: Yes | D77: alla.petukhina@htw-berlin.de | F77: yes | G77: MB Lin, K. Khowaja, CYH Chen, WK Härdle (2021) Blockchain mechanism and distributional characteristics of cryptos , Advances in Quantitative Analysis of Finance & Accounting (AQAFA), Vol. 18, DOI：10.6293/AQAFA.202112_(18).0006
A78: Germany | B78: http://dx.doi.org/10.2139/ssrn.3912753 | C78: Yes | D78: alla.petukhina@htw-berlin.de | F78: yes
A79: Germany | B79: http://dx.doi.org/10.2139/ssrn.4150849 | C79: Yes | D79: alla.petukhina@htw-berlin.de | F79: yes
A80: Germany | B80: https://doi.org/10.48550/arXiv.2103.08447 | C80: Yes | D80: alla.petukhina@htw-berlin.de | F80: yes
A81: Germany | B81: https://doi.org/10.1007/s42521-022-00064-8 | C81: Yes | D81: alla.petukhina@htw-berlin.de | F81: yes
A82: Germany | B82: https://doi.org/10.1016/j.jcomm.2021.100189 | C82: Yes | D82: alla.petukhina@htw-berlin.de | F82: yes
A83: Germany | B83: https://doi.org/10.48550/arXiv.2101.10189 | C83: Yes | D83: alla.petukhina@htw-berlin.de | F83: yes | G83: K Khowaja, M Shcherbatyy, WK Härdle (2021) Surrogate Models for Optimization of Dynamical Systems, "Foundations of Modern Statistics", Springer Proceedings in Mathematics & Statistics, to appear 2022
A84: Germany | B84: https://doi.org/10.48550/arXiv.2108.11915 | C84: Yes | D84: alla.petukhina@htw-berlin.de | F84: yes
A85: Germany | B85: https://doi.org/10.1016/j.jmva.2021.104881 | C85: Yes | D85: alla.petukhina@htw-berlin.de | F85: yes
A86: Germany | D86: alla.petukhina@htw-berlin.de | F86: yes | G86: J Bender, A Petukhina (2022) Portfolio Diversification based on Risk Profile Clustering, submitted
A87: Germany | B87: http://dx.doi.org/10.2139/ssrn.3699345 | C87: Yes | D87: alla.petukhina@htw-berlin.de | F87: yes
A88: Germany/Romania | B88: https://doi.org/10.1080/1351847X.2021.1960403 | C88: Yes | D88: alla.petukhina@htw-berlin.de | F88: yes
A89: Hungary | B89: https://doi.org/10.1007/978-3-031-15743-1_11 | C89: Yes | D89: molnarba@inf.elte.hu | F89: yes
A90: Hungary | D90: molnarba@inf.elte.hu | F90: yes | G90: @InProceedings{PisoniKherboucheMolnar2022, author = {Galena Pisoni and Meriem Kherbouche and Bálint Molnár}, booktitle = {4th International Congress on Blockchain and Applications}, title = {Blockchain-based business process management (BPM) for finance: the case of loan-application}, year = {2022}, address = {University of L'Aquila Department of Human Sciences Viale Nizza, 14, 67100 L'Aquila AQ, Italy}, month = jul, publisher = {Springer International Publishing}, comments = {accepted}, eprint = {https://www.researchgate.net/publication/362223415_Blockchain-based_business_process_management_BPM_for_finance_the_case_of_loan-application}, modificationdate = {2022-09-11T11:19:10}, url = {https://link.springer.com/conference/blockchain}, }
A91: India | B91: https://doi.org/10.1007/s42521-022-00066-6 | C91: No | D91: rupelnargunam25@gmail.com | E91: N | F91: no
A92: Ireland | B92: https://doi.org/10.1016/j.ijforecast.2022.01.005 | C92: No | D92: alessia.paccagnini@ucd.ie | F92: no | G92: Coroneo, L., Iacone, F., Paccagnini, A., & Monteiro, P. S. (2022). Testing the predictive accuracy of COVID-19 forecasts. International journal of forecasting.
A93: Ireland | B93: https://doi.org/10.1016/j.jcomm.2021.100240 | C93: No | D93: alessia.paccagnini@ucd.ie | F93: no | G93: Kwas, M., Paccagnini, A., & Rubaszek, M. (2022). Common factors and the dynamics of cereal prices. A forecasting perspective. Journal of Commodity Markets, 100240.
A94: Ireland | B94: https://doi.org/10.1016/j.resourpol.2021.102319 | C94: No | D94: alessia.paccagnini@ucd.ie | F94: no | G94: Kwas, M., Paccagnini, A., & Rubaszek, M. (2021). Common factors and the dynamics of industrial metal prices. A forecasting perspective. Resources Policy, 74, 102319.
A95: Ireland | B95: https://doi.org/10.1016/j.ijforecast.2020.10.002 | C95: No | D95: valerio.poti@ucd.ie | F95: no | G95: Arvanitis, S., Post, T. Potì, V. and S. Karabati, Nonparametric tests for Optimal Predictive Ability, International Journal of Forecasting, Volume 37, Issue 2, 2021, Pages 881-898.
A96: Ireland | B96: https://doi.org/10.1016/j.ijforecast.2021.11.001 | C96: Yes | D96: alessia.paccagnini@ucd.ie | F96: yes | G96: Petropoulos, Fotios, et al. "Forecasting: theory and practice." International Journal of Forecasting (2022).
A97: Ireland | B97: https://doi.org/10.3390/forecast3030030 | C97: Yes | D97: alessia.paccagnini@ucd.ie | F97: yes | G97: Paccagnini, A. (2021). Editorial for Special Issue “New Frontiers in Forecasting the Business Cycle and Financial Markets”. Forecasting, 3(3), 498-500.
A98: Ireland | B98: https://doi.org/10.1007/s10551-021-04842-z | C98: Yes | D98: valerio.poti@ucd.ie | F98: yes | G98: Bredin, D., Potì, V. & Salvador, E. Food Prices, Ethics and Forms of Speculation. J Bus Ethics 179, 495–509 (2022).
A99: Ireland | B99: https://doi.org/10.1016/j.econlet.2022.110734 | C99: Yes | D99: valerio.poti@ucd.ie | F99: yes | G99: Caferra, R., Morone, A. and V. Potì, Crypto-environment network connectivity and Bitcoin returns distribution tail behaviour, Economics Letters, Volume 218, 2022.
A100: Ireland | B100: https://doi.org/10.1007/s42521-021-00045-3 | C100: Yes | D100: valerio.poti@ucd.ie | F100: yes | G100: Chen, Y., Bredin, D., Potì, V. and R. Matkovskyy, COVID risk narratives: a computational linguistic approach to the econometric identification of narrative risk during a pandemic, Digital Finance 4, pages 17-61, 2022.
A101: Ireland | B101: https://doi.org/10.1007/s42521-022-00060-y | C101: Yes | D101: alla.petukhina@htw-berlin.de | F101: yes
A102: Italy | B102: https://dx.doi.org/10.2139/ssrn.4173890 | C102: Yes | D102: alessandra.tanda@unipv.it | F102: yes | G102: Bussmann, N., Tanda, A., & Yu, E. P. Y. (2022). Can ESG Shape Cost of Capital? A Bibliometric Review and Empirical Analysis Through ML. A Bibliometric Review and Empirical Analysis Through ML (July 27, 2022).
A103: Italy | B103: https://doi.org/10.1016/j.frl.2022.103411 | C103: Yes | D103: alberto.citterio@uninsubria.it | F103: yes | G103: Citterio A., King T. (2022) The role of Environmental, Social, and Governance (ESG) in predicting bank financial distress
A104: italy | B104: https://doi.org/10.1007/s42521-022-00055-9 | C104: Yes | D104: daniele.marazzina@polimi.it | F104: yes
A105: italy | B105: https://doi.org/10.1016/j.eswa.2021.116261 | C105: Yes | D105: daniele.marazzina@polimi.it | F105: yes
A106: italy | B106: https://doi.org/10.1016/j.frl.2022.102941 | C106: Yes | D106: giudici@unipv.it
...

Sheet DOIs_updated_oct22
A1: Country | B1: DOI | C1: email | D1: COST acknowledgement | E1: Citation (ONLY IF NO DOI up to now, otherwise, not needed)
A2: Albania | B2: 10.13189/ujaf.2020.080402 | C2: llesh.lleshaj@unitir.edu.al | D2: no | E2: Llesh Lleshaj , Alban Korbi (2020). Portfolio Selection and VaR Estimation: Evidence from Western Balkan Countries. Universal Journal of Accounting and Finance, 8(4), 92 - 102. DOI: 10.13189/ujaf.2020.080402.
A3: Albania | B3: 10.34109/ijefs.20220026 | C3: anila.voci@uniel.edu.al | D3: no | E3: Çekrezi, A. V. (2022). Determinants of Bank Deposits in Albania. International Journal of Economics and Finance Studies, 14 (02), 101-121. doi:10.34111/ijefs. 20220026
A4: Albania | B4: 10.37394/23207.2021.18.102 | C4: rezarta.perri@unitir.edu.al | D4: no | E4: Rezarta Shkurti, Elfrida Manoku, "Factors of Success in Implementation of Enterprise Resource Planning Systems," WSEAS Transactions on Business and Economics, vol. 18, pp. 1084-1093, 2021
A5: Belgium | B5: not yet available | C5: christian.hafner@uclouvain.be | D5: yes | E5: Lin, Wang, Bocart, Hafner, Haerdle (2022) DAI: Digital Art Index, forthcoming
A6: Croatia | B6: N/A | C6: domagoj.sajter@efos.hr | D6: yes | E6: Sajter, D. (2022, May 5–6). Overseas Transaction Fees: Sending Money via Bitcoin vs. Banks [Paper presentation]. Technology, Innovation and Stability: New Directions in Finance (TINFIN), Zagreb, Croatia.
A7: Croatia | B7: N/A | C7: bozena.gulija@outlook.com | D7: yes | E7: Gulija, B., Kammel, A., & Payr, T. (2022, May 5–6). Prudential Regulation of Fintechs [Paper presentation]. Technology, Innovation and Stability: New Directions in Finance (TINFIN), Zagreb, Croatia.
A8: Croatia | B8: N/A | C8: nsimurina@efzg.hr | D8: yes | E8: Simurina, N., Kurnoga, N., & Fuckan, F. (2022, May 5–6). Performance differences between ESG indices and traditional indices [Paper presentation]. Technology, Innovation and Stability: New Directions in Finance (TINFIN), Zagreb, Croatia.
A9: Croatia | B9: N/A | C9: aivanisev@net.efzg.hr | D9: yes | E9: Dzelalija, P., & Ivanisevic Hernaus, A. (2022, August 22–24). From perceived mobility to the intention to use mobile payments: A moderated mediation analysis [Paper presentation]. FinanceCom 2022: 11th International Workshop, Enterprise Applications, Markets and Services in the Finance Industry, University of Twente, the Netherlands.
A10: Croatia | B10: N/A | C10: aivanisev@net.efzg.hr | D10: yes | E10: Ivanisevic Hernaus, A., Kristo, J., & Rako, R. (2022, May 5–6). ESG-Related Challenges in the Insurance Industry: A Multi-stakeholder Perspective [Paper presentation]. Technology, Innovation and Stability: New Directions in Finance (TINFIN), Zagreb, Croatia.
A11: Croatia | B11: https://doi.org/10.2478/crebss-2020-0007 | C11: svlah@net.efzg.hr
A12: Croatia | B12: https://doi.org/10.4324/9781003144410-8 | C12: svlah@net.efzg.hr
A13: Croatia | B13: https://doi.org/10.4018/978-1-7998-5083-0.ch010 | C13: svlah@net.efzg.hr
A14: Denmark | B14: doi.org/10.1007/s11634-022-00508-4 | C14: drm.eco@cbs.dk | D14: no
A15: Denmark | B15: doi.org/10.1016/j.eswa.2022.117423 | C15: drm.eco@cbs.dk | D15: no
A16: Denmark | B16: doi.org/10.1016/j.ejor.2021.12.022 | C16: drm.eco@cbs.dk | D16: no
A17: Denmark | B17: doi.org/10.1016/j.omega.2021.102543 | C17: drm.eco@cbs.dk | D17: no
A18: Denmark | B18: doi.org/10.1016/j.eswa.2021.115245 | C18: drm.eco@cbs.dk | D18: no
A19: Denmark | B19: doi.org/10.1016/j.ejor.2021.04.016 | C19: drm.eco@cbs.dk | D19: no
A20: Denmark | B20: doi.org/10.1016/j.cor.2021.105281 | C20: drm.eco@cbs.dk | D20: no
A21: Denmark | B21: doi.org/10.1007/s11750-021-00594-1 | C21: drm.eco@cbs.dk | D21: no
A22: Denmark | B22: doi.org/10.1080/00273171.2019.1677208 | C22: drm.eco@cbs.dk | D22: no
A23: Denmark | B23: doi.org/10.1016/j.omega.2019.05.004 | C23: drm.eco@cbs.dk | D23: no
A24: Denmark | B24: doi.org/10.1016/j.ejor.2019.12.002 | C24: drm.eco@cbs.dk | D24: no
A25: Estonia | B25: https://doi.org/10.1007/978-981-16-2418-6 | C25: innar.liiv@taltech.ee | D25: yes | E25: * not included in the last reporting period
A26: France | B26: https://doi.org/10.1016/j.intfin.2021.101321 | C26: roman.matkovskyy@rennes-sb.com | D26: no
A27: France | B27: https://doi.org/10.1016/j.irfa.2021.101958 | C27: roman.matkovskyy@rennes-sb.com | D27: no
A28: France | B28: https://doi.org/10.1080/1351847X.2020.1869992 | C28: roman.matkovskyy@rennes-sb.com | D28: no
A29: France | B29: https://doi.org/10.1080/00036846.2020.1854671 | C29: roman.matkovskyy@rennes-sb.com | D29: no
A30: France | B30: https://doi.org/10.1016/j.frl.2019.101405 | C30: roman.matkovskyy@rennes-sb.com | D30: no
A31: France | B31: https://doi.org/10.1016/j.qref.2020.02.004 | C31: roman.matkovskyy@rennes-sb.com | D31: no
A32: France | B32: https://www.jstor.org/stable/48618930 | C32: roman.matkovskyy@rennes-sb.com | D32: no
A33: France, Ireland | B33: https://doi.org/10.1016/j.frl.2021.102162 | C33: roman.matkovskyy@rennes-sb.com | D33: yes | E33: Jalan, A., Matkovskyy, R., and Poti, V. (2022). "Shall the winning last? A study of recent bubbles and persistence." Finance Research Letters 45, 102162
A34: Germany | B34: https://doi.org/10.1214/20-AOS2019 | C34: alla.petukhina@htw-berlin.de | D34: no
A35: Germany | B35: https://doi.org/10.1080/14697688.2021.1880023 | C35: alla.petukhina@htw-berlin.de | D35: no
A36: Germany | B36: https://doi.org/10.1016/j.jspi.2020.10.007 | C36: alla.petukhina@htw-berlin.de | D36: no
A37: Germany | B37: https://doi.org/10.1111/rssc.12499 | C37: alla.petukhina@htw-berlin.de | D37: no
A38: Germany | B38: https://doi.org/10.1016/j.jedc.2021.104290 | C38: alla.petukhina@htw-berlin.de | D38: no
A39: Germany | B39: https://doi.org/10.1016/j.irfa.2021.101915 | C39: alla.petukhina@htw-berlin.de | D39: no
A40: Germany | B40: http://dx.doi.org/10.2139/ssrn.3724814 | C40: alla.petukhina@htw-berlin.de | D40: no
A41: Germany | B41: https://doi.org/10.1007/s42521-021-00031-9 | C41: alla.petukhina@htw-berlin.de | D41: no
A42: Germany | B42: https://doi.org/10.1007/s42521-021-00043-5 | C42: alla.petukhina@htw-berlin.de | D42: no
A43: Germany | B43: https://doi.org/10.1007/s43546-021-00057-6 | C43: alla.petukhina@htw-berlin.de | D43: no
A44: Germany | B44: https://doi.org/10.1007/978-3-030-73443-5_94-1 | C44: alla.petukhina@htw-berlin.de | D44: yes
A45: Germany | B45: https://doi.org/10.48550/arXiv.2208.12614 | C45: alla.petukhina@htw-berlin.de | D45: yes
... A62: Germany | B62: https://doi.org/10.48550/arXiv.2108.11921 | C62: alla.petukhina@htw-berlin.de | D62: yes
A63: Germany | B63: 10.6293/AQAFA.202112_(18).0006 | C63: alla.petukhina@htw-berlin.de | D63: yes | E63: MB Lin, K. Khowaja, CYH Chen, WK Härdle (2021) Blockchain mechanism and distributional characteristics of cryptos , Advances in Quantitative Analysis of Finance & Accounting (AQAFA), Vol. 18, DOI：10.6293/AQAFA.202112_(18).0006
A64: Germany | B64: http://dx.doi.org/10.2139/ssrn.3912753 | C64: alla.petukhina@htw-berlin.de | D64: yes
A65: Germany | B65: http://dx.doi.org/10.2139/ssrn.4150849 | C65: alla.petukhina@htw-berlin.de | D65: yes
A66: Germany | B66: https://doi.org/10.48550/arXiv.2103.08447 | C66: alla.petukhina@htw-berlin.de | D66: yes
A67: Germany | B67: https://doi.org/10.1007/s42521-022-00064-8 | C67: alla.petukhina@htw-berlin.de | D67: yes
A68: Germany | B68: https://doi.org/10.1016/j.jcomm.2021.100189 | C68: alla.petukhina@htw-berlin.de | D68: yes
A69: Germany | B69: https://doi.org/10.48550/arXiv.2101.10189 | C69: alla.petukhina@htw-berlin.de | D69: yes | E69: K Khowaja, M Shcherbatyy, WK Härdle (2021) Surrogate Models for Optimization of Dynamical Systems, "Foundations of Modern Statistics", Springer Proceedings in Mathematics & Statistics, to appear 2022
A70: Germany | B70: https://doi.org/10.48550/arXiv.2108.11915 | C70: alla.petukhina@htw-berlin.de | D70: yes
A71: Germany | B71: https://doi.org/10.1016/j.jmva.2021.104881 | C71: alla.petukhina@htw-berlin.de | D71: yes
A72: Germany | C72: alla.petukhina@htw-berlin.de | D72: yes | E72: J Bender, A Petukhina (2022) Portfolio Diversification based on Risk Profile Clustering, submitted
A73: Germany | B73: http://dx.doi.org/10.2139/ssrn.3699345 | C73: alla.petukhina@htw-berlin.de | D73: yes
A74: Germany/Romania | B74: https://doi.org/10.1080/1351847X.2021.1960403 | C74: alla.petukhina@htw-berlin.de | D74: yes
A75: Hungary | B75: https://doi.org/10.1007/978-3-031-15743-1_11 | C75: molnarba@inf.elte.hu | D75: yes
A76: Hungary | C76: molnarba@inf.elte.hu | D76: yes | E76: @InProceedings{PisoniKherboucheMolnar2022, author = {Galena Pisoni and Meriem Kherbouche and Bálint Molnár}, booktitle = {4th International Congress on Blockchain and Applications}, title = {Blockchain-based business process management (BPM) for finance: the case of loan-application}, year = {2022}, address = {University of L'Aquila Department of Human Sciences Viale Nizza, 14, 67100 L'Aquila AQ, Italy}, month = jul, publisher = {Springer International Publishing}, comments = {accepted}, eprint = {https://www.researchgate.net/publication/362223415_Blockchain-based_business_process_management_BPM_for_finance_the_case_of_loan-application}, modificationdate = {2022-09-11T11:19:10}, url = {https://link.springer.com/conference/blockchain}, }
A77: India | B77: https://doi.org/10.1007/s42521-022-00066-6 | C77: rupelnargunam25@gmail.com | D77: no
A78: Ireland | B78: https://doi.org/10.1016/j.ijforecast.2022.01.005 | C78: alessia.paccagnini@ucd.ie | D78: no | E78: Coroneo, L., Iacone, F., Paccagnini, A., & Monteiro, P. S. (2022). Testing the predictive accuracy of COVID-19 forecasts. International journal of forecasting.
A79: Ireland | B79: https://doi.org/10.1016/j.jcomm.2021.100240 | C79: alessia.paccagnini@ucd.ie | D79: no | E79: Kwas, M., Paccagnini, A., & Rubaszek, M. (2022). Common factors and the dynamics of cereal prices. A forecasting perspective. Journal of Commodity Markets, 100240.
A80: Ireland | B80: https://doi.org/10.1016/j.resourpol.2021.102319 | C80: alessia.paccagnini@ucd.ie | D80: no | E80: Kwas, M., Paccagnini, A., & Rubaszek, M. (2021). Common factors and the dynamics of industrial metal prices. A forecasting perspective. Resources Policy, 74, 102319.
A81: Ireland | B81: https://doi.org/10.1016/j.ijforecast.2020.10.002 | C81: valerio.poti@ucd.ie | D81: no | E81: Arvanitis, S., Post, T. Potì, V. and S. Karabati, Nonparametric tests for Optimal Predictive Ability, International Journal of Forecasting, Volume 37, Issue 2, 2021, Pages 881-898.
A82: Ireland | B82: https://doi.org/10.1016/j.ijforecast.2021.11.001 | C82: alessia.paccagnini@ucd.ie | D82: yes | E82: Petropoulos, Fotios, et al. "Forecasting: theory and practice." International Journal of Forecasting (2022).
A83: Ireland | B83: https://doi.org/10.3390/forecast3030030 | C83: alessia.paccagnini@ucd.ie | D83: yes | E83: Paccagnini, A. (2021). Editorial for Special Issue “New Frontiers in Forecasting the Business Cycle and Financial Markets”. Forecasting, 3(3), 498-500.
A84: Ireland | B84: https://doi.org/10.1007/s10551-021-04842-z | C84: valerio.poti@ucd.ie | D84: yes | E84: Bredin, D., Potì, V. & Salvador, E. Food Prices, Ethics and Forms of Speculation. J Bus Ethics 179, 495–509 (2022).
A85: Ireland | B85: https://doi.org/10.1016/j.econlet.2022.110734 | C85: valerio.poti@ucd.ie | D85: yes | E85: Caferra, R., Morone, A. and V. Potì, Crypto-environment network connectivity and Bitcoin returns distribution tail behaviour, Economics Letters, Volume 218, 2022.
A86: Ireland | B86: https://doi.org/10.1007/s42521-021-00045-3 | C86: valerio.poti@ucd.ie | D86: yes | E86: Chen, Y., Bredin, D., Potì, V. and R. Matkovskyy, COVID risk narratives: a computational linguistic approach to the econometric identification of narrative risk during a pandemic, Digital Finance 4, pages 17-61, 2022.
A87: Ireland | B87: https://doi.org/10.1007/s42521-022-00060-y | C87: alla.petukhina@htw-berlin.de | D87: yes
A88: Italy | B88: https://dx.doi.org/10.2139/ssrn.4173890 | C88: alessandra.tanda@unipv.it | D88: yes | E88: Bussmann, N., Tanda, A., & Yu, E. P. Y. (2022). Can ESG Shape Cost of Capital? A Bibliometric Review and Empirical Analysis Through ML. A Bibliometric Review and Empirical Analysis Through ML (July 27, 2022).
A89: Italy | B89: na | C89: alberto.citterio@uninsubria.it | D89: yes | E89: Citterio A., King T. (2022) The role of Environmental, Social, and Governance (ESG) in predicting bank financial distress
A90: italy | B90: https://doi.org/10.1007/s42521-022-00055-9 | C90: daniele.marazzina@polimi.it | D90: yes
A91: italy | B91: https://doi.org/10.1016/j.eswa.2021.116261 | C91: daniele.marazzina@polimi.it | D91: yes
A92: italy | B92: https://doi.org/10.1016/j.frl.2022.102941 | C92: giudici@unipv.it
A93: italy | B93: https://doi.org/10.1016/j.eswa.2020.114104 | C93: giudici@unipv.it
A94: Lithuania | B94: https://doi.org/10.1007/s42521-022-00062-w | C94: alla.petukhina@htw-berlin.de | D94: yes
A95: North Macedonia | B95: https://doi.org/10.1007/s42521-022-00065-7 | C95: alla.petukhina@htw-berlin.de | D95: yes
A96: Norway | B96: https://doi.org/10.1016/j.apenergy.2022.119182 | C96: per.b.solibakke@ntnu.no | E96: Ahmad Amine Loutfi, Mengtao Sun, Ijlal Loutfi and Per Bjarte Solibakke, (2022), Empirical study of day-ahead electricity spot-price forecasting: Insights into a novel loss function for training neural networks
A97: Norway | B97: https://doi.org/10.3390/en15103839 | C97: per.b.solibakke@ntnu.no | E97: Solibakke, Per Bjarte, (2022), Projecting and Forecasting Stochastic Volatility Characteristics for the Nasdaq OMX Nordic/Baltic Financial Electricity Markets
A98: Norway | B98: https://doi.org/10.1504/IJCEE.2021.10043332 | C98: per.b.solibakke@ntnu.no | E98: Solibakke, Per Bjarte, (2022), Bootstrapped Nonlinear Impulse-Response Analysis: The FTSE100 (UK) and the NDX100 (US) Indices 2012-2021
A99: Norway | B99: https://doi.org/10.1007/978-3-030-56219-9_9 | C99: per.b.solibakke@ntnu.no | E99: Solibakke, Per Bjarte, (2020), Stochastic Volatility Models Predictive Relevance for Equity Market
A100: Poland | B100: https://doi.org/10.3389/frai.2021.718450 | C100: pwojcik@wne.uw.edu.pl | D100: yes | E100: Karimov Bedil and Wójcik Piotr (2021), Frontiers in Artificial Intelligence, section Artificial Intelligence in Finance
A101: Portugal | B101: https://doi.org/10.1007/978-3-031-16474-3_40 | C101: catarina@dei.uc.pt | E101: C. Silva, B. Ribeiro and A. Morais, A Generic Approach to Extend Interpretability of Deep Networks, in Progress in Artificial Intelligence, pp. 488–499-488–499, 2022
A102: Romania | B102: 10.1007/978-3-030-93286-2_7 | C102: coita.iflorina@gmail.com | D102: yes
A103: Romania | B103: https://doi.org/10.1007/978-981-16-2765-1_6 | C103: coita.iflorina@gmail.com | D103: yes
A104: Romania | B104: https://doi.org/10.1080/1351847X.2021.1960403 | C104: danpele@ase.ro | D104: yes
A105: Romania | B105: https://doi.org/10.3390/risks9060116 | C105: codruta.mare@econ.ubbcluj.ro | D105: yes
A106: Romania | B106: https://doi.org/10.3390/risks9060104 | C106: codruta.mare@econ.ubbcluj.ro | D106: yes
A107: Romania | B107: https://doi.org/10.3390/math10193625 (registering DOI) | C107: codruta.mare@econ.ubbcluj.ro | D107: yes | E107: Mare, C.; Manaţe, D.; Mureşan, G.-M.; Dragoş, S.L.; Dragoş, C.M.; Purcel, A.-A. Machine Learning Models for Predicting Romanian Farmers’ Purchase of Crop Insurance. Mathematics 2022, 10, 3625. https://doi.org/10.3390/math10193625
A108: Romania | B108: https://doi.org/10.1007/s10198-022-01506-1 | C108: codruta.mare@econ.ubbcluj.ro | D108: no, problems in the publishing process, waiting for the journal to correct the mistake | E108: Mureșan, GM., Văidean, VL., Mare, C. et al. Were we happy and we didn’t know it? A subjective dynamic and financial assessment pre-, during and post-COVID-19. Eur J Health Econ (2022). https://doi.org/10.1007/s10198-022-01506-1
A109: Serbia | B109: doi.org/10.15308/finiz-2020-97-102 | C109: lbarjaktarovic@singidunum.ac.rs | D109: yes
A110: Serbia | B110: https://doi.org/10.1016/j.ipm.2021.102848 | C110: miljan.vucetic@vlatacom.com | D110: yes
A111: Slovakia | C111: miroslav.hudec@euba.sk | D111: yes | E111: Hudec M., Mináriková E., Schwarz D., Fivaz J. (2022). Estimating linguistic summaries on the unit interval data. WCCI2022 IEEE World Congress on Computational Intelligence, Padua, July 18-23 (expected in WoS, Scopus and IEEE eXplore),
A112: Slovakia and Serbia | B112: https://doi.org/10.1016/j.ipm.2021.102848 | C112: miroslav.hudec@euba.sk | D112: yes
A113: Spain | B113: https://doi.org/10.1016/j.elerap.2021.101079 | C113: javier.arroyo@fdi.ucm.es | D113: yes | E113: Ariza-Garzón, M.J., Camacho-Miñano, M.M., Segovia-Vargas, M.J., Arroyo, J. (2021) "Risk-return modelling in the p2p lending market: Trends, gaps, recommendations and future directions". Electronic Commerce Research and Applications, Volume 49, 101079.
A114: Spain | B114: https://doi.org/10.1186/s40854-021-00310-9 | C114: javier.arroyo@fdi.ucm.es | D114: yes | E114: Lorenzo, L., Arroyo, J. (2022) "Analysis of the cryptocurrency market using different prototype-based clustering techniques". Financial Innovation 8, 7.
A115: Switzerland | B115: https://doi.org/10.1007/s42521-022-00063-9 | C115: joerg.osterrieder@bfh.ch | D115: yes
A116: Switzerland | B116: https://doi.org/10.2139/ssrn.3796351 | C116: joerg.osterrieder@bfh.ch | D116: yes
...

Sheet Research Proposals
A1: Research proposals Submitted (granted, under evaluation, rejected. Please list all)
A2: Country | B2: Title | C2: Name and country of main proposer | D2: Number of proposers | E2: Action participants listed among the proposers: Name | F2: Action participants listed among the proposers: Country | G2: Proposers outside academia (Yes/ No) | H2: Funder (EU H2020, other EU, Trans-national, National, Industry, Other) | I2: Amount requested/ Granted (in EUR) | J2: Call identifier | K2: Year submitted | L2: Result (Under Evaluation, Not Funded, Funded)
A3: mandatory | B3: mandatory | C3: mandatory | D3: mandatory | E3: mandatory | F3: mandatory | G3: mandatory | H3: mandatory | I3: mandatory | J3: mandatory | K3: mandatory | L3: mandatory
A4: Hungary | B4: Defence and Security of the Nation (Nemzetvédelem, nemzetbiztonság alprogram (NVA)), sub-project for Finance and AI | C4: Hungary, Eötvös Loránd Tudományegyetem | E4: Bálint Molnár | F4: Hungary | G4: No | H4: NATIONAL, NKFIH | I4: 1 200 000 000 FT | J4: TKP2021-NVA-29, https://nkfih.gov.hu/palyazoknak/nkfi-alap/tamogatott-intezmenyek-tkp2021 | K4: 2021 | L4: Funded
A5: Bulgaria | B5: Flying Forest Fires Fighting (4F), EU project, “Emerging industries new value chains boosted by small Flying Objects” (UFO), financed by the INNOSUP component of the HORIZON 2020 programme of the European Commission under Grant Agreement 873411, https://eic.ec.europa.eu/news/ufo-emerging-industries-new-value-chains-boosted-small-flying-objects-2022-02-22_en, smart service creation | C5: Bulgaria, Comicon Ltd., Aleksandar Savov | D5: 5 | E5: Rossitza Goleva | F5: Bulgaria | G5: yes | H5: EU H2020 | I5: 100000 | J5: Grant Agreement 873411 | K5: 2021 | L5: Funded
A6: France | B6: CRYPTO-CURRENCIES AND NORDIC YOUTH | C6: Roman Matkovskyy, France | D6: 2 | E6: Roman Matkovskyy, Akanksha Jalan | F6: France | G6: no | H6: Trans-national, Nasdaq | I6: 25000 | J6: OEE Grand call 2022 | K6: 2022 | L6: funded
A7: France | B7: Youth savings behaviours: CRYPTOCURRENCIES AND THE EUROPEAN YOUTH | C7: Roman Matkovskyy, France | D7: 2 | E7: Roman Matkovskyy, Akanksha Jalan | F7: France | G7: no | H7: National | I7: 22000 | J7: Grand call 2023 | K7: 2022 | L7: under evaluation
A8: France | B8: Gearing up for change (cryptocurrencies) | C8: Roman Matkovskyy, France | D8: 3 | E8: Roman Matkovskyy, Akanksha Jalan and Raouf Boucekkine | F8: France | G8: no | H8: National | I8: 80000 | J8: ANR | K8: 2021 | L8: rejected
A9: Italy | B9: Enhancing Women’s empowerment through Small and Big data (W_STEM) | C9: Claudia Tarantola, Italy | D9: 5 | E9: Claudia Tarantola, Maria Iannario, Alessandra Tanda, Alessia Paccagnini; Codruta Mare | F9: Italy, Ireland, Romania | G9: yes | H9: KA220-HED | I9: 400000 | J9: KA220-HED - Cooperation partnerships in higher education | K9: 2022 | L9: Not Funded
A10: Italy | B10: Latent variable models for complex categorical data structures (LAICS) | C10: Maria Iannario, Italy | D10: 3 | E10: Maria Iannario | F10: Italy | G10: no | H10: National | I10: 39.925,02 € | K10: 2022 | L10: under evaluation
A11: Italy | B11: Latent variable models and dimensionality reduction methods for complex data | C11: Maria Iannario, Italy | D11: 29 | E11: Maria Iannario | G11: no | H11: Italy | I11: 392141 | J11: PRIN2022 | K11: 2022 | L11: under evaluation
A12: Netherlands/Spain/Italy/Belgium | B12: ABC-EU-XVA | C12: Kees Oosterlee, Netherlands | D12: 4 | E12: Kees Oosterlee, Carlos Vázquez | F12: Netherlands,Spain,Italy,Belgium | G12: yes | H12: EU H2020, MSCA EID-ITN Call | I12: 1500000 | J12: HORIZON2020-MCSA-ITN-2018-EID (Grant agreemente 813261) | K12: 2018 | L12: Funded
A13: Romania | B13: Machine Learning and Spatial Econometrics Deevelopments in Finance: the impact of Financial and Digital Literacy. Romania in International Context | C13: Codruta Mare, Romania | D13: 2 | E13: Ioana Coita, Stefana Belbe | F13: Romania | G13: no | H13: National | I13: 93750 | J13: PN-III-P1-1_1-TE-2021 | K13: 2021 | L13: Not Funded
A14: Romania | B14: Using alternative data to buidlind risk scoring tools for the lending sector | C14: Coita Ioana, Romania | D14: 1 | E14: Coita Ioana | F14: Romania | G14: no | H14: EU2020 | I14: 60.000EUR | K14: 2022 | L14: under evaluation
A15: Romania | B15: Building Tax Research platform for risk analysis in the banking secotor | C15: Coita Ioana, Codruta Mare, Romania | D15: 2 | E15: Coita Ioana, Codruta Mare, Romania | F15: Romania | G15: yes | H15: EU funding | I15: 200.000 EUR | K15: 2022 | L15: under evaluation
A16: Romania | B16: Erasmus+ project KA220-HED - Cooperation partnerships in higher education, KA220-HED-0B76953E - Enhancing Women’s empowerment through Small and Big Data (W_STEM), | C16: Codruta Mare, Romania | D16: 5 | E16: Claudia Tarantola, Maria Iannario, Alessandra Tanda, Alessia Paccagnini; Codruta Mare | F16: Italy, Ireland, Romania | G16: yes | H16: KA220-HED | I16: 400000 | J16: KA220-HED - Cooperation partnerships in higher education | K16: 2022 | L16: Not Funded
A17: Germany | B17: Explainable AI methods for riskmanagement of FinTechs | C17: Natalie Packham, Germany | D17: 3 | E17: N Packham, A Petukhina | F17: Germany | G17: yes | H17: National | I17: 290000 | J17: IFAF Berlin call 2022 | K17: 2022 | L17: Funded
A18: Germany | B18: Blockchain Research Center | C18: WK Härdle, Germany | D18: 3 | E18: Daniel Pele, Claudio Tessone | F18: Romania | G18: no | H18: National | I18: 10000 | J18: Berlin Universisty alliance | K18: 2021 | L18: Funded
A19: Germany | B19: IRTG 1792 extension 2022.10-2023.3 | C19: WK Härdle, Germany | D19: 10 | E19: N Packham, A Petukhina | F19: Germany | G19: no | H19: National | I19: 200000 | J19: DFG | K19: 2021 | L19: Funded
A20: Germany | B20: LASSA: discovering aberrant opinions, making minorities visible and reducing gender bias via principal expectiles | C20: WK Härdle, Germany | D20: 2 | E20: Maria Osipenko, HWR | F20: Germany | G20: no | H20: National | I20: 150000 | J20: DFG | K20: 2021 | L20: Not Funded
A21: Germany | B21: Digital Asset Knowledge Proliferation (DAKP) | C21: ZHOU Chao, Singapore | D21: 5 | E21: WK Härdle, V Strat, R Matkovskyy, HW Teng | G21: no | H21: Trans-National | I21: 350000 | J21: NUS Asian Institute of Digital finance | K21: 2022 | L21: Not Funded
A22: Ireland | B22: FinData: Financial data science Doctoral Network | C22: Valerio Poti, Ireland | D22: 5 | E22: Valerio Poti, Joerg Osterrieder, Branka Hadji Misheva, WK Härdle and several others | F22: Ireland, Switzerland, Germany | G22: Yes | H22: EU H2020 | I22: 3000000 | J22: H2020-MSCA-ITN-2020 | K22: 2020 | L22: Not Funded
A23: Ireland | B23: HDFinance: High Dimensional Finance: joint challenge for academia and industry | C23: Valerio Poti, Ireland | D23: 5 | E23: Valerio Poti, Joerg Osterrieder, Branka Hadji Misheva, WK Härdle and several others | F23: Ireland, Switzerland, Germany | G23: Yes | H23: EU Horizon Europe | I23: 3000000 | J23: HORIZON-MSCA-2021-DN-01 | K23: 2021 | L23: Not Funded
A24: Czechia | B24: Accelerating growth and stability of European P2P Lending | C24: Štefan Lyócsa, Czechia | D24: 5 | E24: Oleg Deev, Tomáš Plíhal, Peter Schwendner, Joerg Osterrieder, Branka Hadji Misheva | F24: Switzerland, Czechia | G24: no | H24: Trans-National | J24: Czech Science Foundation and SNSF Lead Agency | K24: 2021 | L24: Not Funded
A25: Czechia | B25: Network-based credit risk models on P2p lending markets | C25: Eduard Baumöhl, Czechia | D25: 5 | E25: Štefan Lyócsa, Oleg Deev, Tomáš Plíhal, Peter Schwendner, Joerg Osterrieder, Branka Hadji Misheva | F25: Switzerland, Czechia | G25: no | H25: Trans-National | I25: 500000 | J25: Czech Science Foundation and SNSF Lead Agency | K25: 2021 | L25: Funded
A26: Czechia | B26: Innovation voucher for CCF Research | C26: Tomáš Plíhal, Czechia | D26: 2 | E26: Štefan Lyócsa, Oleg Deev | F26: Czechia | G26: yes | H26: National | J26: Ministry of Industry and Trade, Czechia | K26: 2022 | L26: Funded
A27: Czechia | B27: Analytical Platform 2.0 | C27: Tomáš Plíhal, Czechia | D27: 2 | E27: Štefan Lyócsa, Oleg Deev | F27: Czechia | G27: yes | H27: National | J27: Technological Agency of the Czech Republic | K27: 2022 | L27: under evaluation
A28: Switzerland | B28: Blockchain Fraud Detection | C28: Joerg Osterrieder, Switzerland | D28: 5 | E28: Branka Hadji Misheva, Joerg Osterrieder, Stephen Chan | F28: Switzerland, UAE | G28: no | H28: Trans-National | I28: 60000 | J28: MENA Leading House | K28: 2022 | L28: under evaluation
A29: Switzerland | B29: The Paradox of Digital Finance: Financial Inclusion vs. Exclusion | C29: Aneta Korosteleva, Poland | E29: WK Härdle, Peter Schwendner, Jörg osterrieder | G29: no | H29: Trans-National | J29: CHANSE ERA-NET | L29: Not Funded
A30: Switzerland | B30: Controllable synthetic scenarios for explainable systematic strategies (SNF COST) | C30: Peter Schwendner, Switzerland | D30: 2 | E30: Peter Schwendner, Marcus Wunsch | F30: Switzerland | G30: no | H30: National | J30: SNF COST | L30: Not Funded
A31: Netherlands | B31: Digital Finance | C31: Joerg Osterrieder, Netherlands, Branka Hadji Misheva, Switzerland | D31: 25 | E31: Sinem Bağçe <sinem.bagce@khas.edu.tr>; Barsotti, F. (Flavia <Flavia.Barsotti@ing.com>; Autar, A. (Anand <Anand.Autar@ing.com>; Akın Karcı <akin.karci@khas.edu.tr>; Andrew Farrugia <andrew.farrugia@umnai.com>; akanksha.jalan@rennes-sb.com; Hadji Misheva Branka <branka.hadjimisheva@bfh.ch>; luciana.dallavalle@plymouth.ac.uk; maria.iannario@unina.it; Machado, Marcos (UT-BMS) <m.r.machado@utwente.nl>; Svetlova, Ekaterina (UT-BMS) <e.svetlova@utwente.nl>; Abhishta, Abhishta (UT-BMS) <s.abhishta@utwente.nl>; Heeswijk, Wouter van (UT-BMS) <w.j.a.vanheeswijk@utwente.nl>; Vijaya Bhaskar, Vijay (UT-BMS) <v.b.marisetty@utwente.nl>; Ioana-Florina Coita <coita.iflorina@gmail.com>; 'Peter SCHWENDNER' <scwp@zhaw.ch>; Hopp Christian <christian.hopp@bfh.ch>; emiris@athenarc.gr; giann@athenarc.gr; dalamag@athenarc.gr; audrius.kabasinskas@ktu.lt; rgoleva@gmail.com; loizos@ouc.ac.cy; belma.ozturkkal@khas.edu.tr; antoni.jaume@uib.es; Ida Ivanová | OVaDŠ EU v Bratislave <ida.ivanova@euba.sk>; kwtrwn@gmail.com; roman.matkovskyy@rennes-sb.com; molnarba@inf.elte.hu; jana.peliova@euba.sk; allapetukhina@icloud.com; haerdle@hu-berlin.de; rui.ren.magic@gmail.com; Tuan Trinh <tuan.trinh@eitdigital.eu>; Codruta Mare <codruta.mare@gmail.com>; danpele@ase.ro; Angele GIULIANO - AcrossLimits <angele@acrosslimits.com>; senfer@acrosslimits.com; Stefan Lessmann <stefan.lessmann@hu-berlin.de>; Christina Erlwein-Sayer <Christina.Erlwein-Sayer@HTW-Berlin.de>; Kristina Sutiene <kristina.sutiene@ktu.lt>; Massimo Preziuso <maxpreziuso@gmail.com>; Mattia Bellotti <mattia.bellotti@eitdigital.eu>; Krisztián Gál <krisztian.gal@eitdigital.eu>; Hochreiter, Ronald <Ronald.Hochreiter@wu.ac.at>; Stefan Lessmann <stefan.lessmann@outlook.de>; barbara.bedowska-sojka@ue.poznan.pl; ronald@kleverlaan.com; Kurpisz Adam Andrzej <adam.kurpisz@bfh.ch> | F31: Netherlands, Switzerland, Germany, Romania, UK, Italy, Malta, France, Spain | G31: yes | H31: EU Horizon Europe | I31: 1500000 | J31: HORIZON-MSCA-2022-DN-01-01 | K31: 2022 | L31: under evaluation
A32: Switzerland | B32: Sustainable Finance | C32: Joerg Osterrieder, Switzerland | D32: 3 | E32: Joerg Osterrieder, Branka Hadji Misheva | F32: Switzerland | G32: yes | H32: National | I32: 15000 | J32: Innosuisse | K32: 2022 | L32: Funded
A33: Switzerland | B33: Digital Finance and Reinforcement Learning | C33: Joerg Osterrieder, Switzerland | D33: 4 | E33: Joerg Osterrieder, Branka Hadji Misheva | F33: Switzerland | G33: yes | H33: National | I33: 400000 | J33: Innosuisse | K33: 2021 | L33: Funded
A34: Switzerland | B34: Currency Hedging | C34: Joerg Osterrieder, Switzerland | D34: 4 | E34: Joerg Osterrieder, Branka Hadji Misheva | F34: Switzerland | G34: yes | H34: National | I34: 150000 | J34: Innosuisse | K34: 2021 | L34: Funded
A35: Switzerland | B35: Blockchain | C35: Joerg Osterrieder, Switzerland | D35: 4 | E35: Joerg Osterrieder, Branka Hadji Misheva | F35: Switzerland | G35: yes | H35: National | I35: 200000 | J35: Innosuisse | K35: 2020 | L35: Funded
A36: Switzerland | B36: Human-machine centered collaboration to crowdsource insights | C36: Joerg Osterrieder, Switzerland | D36: 2 | E36: Joerg Osterrieder, Branka Hadji Misheva | F36: Switzerland | G36: yes | H36: National | I36: 15000 | J36: Innosuisse | K36: 2021 | L36: Funded
A37: Switzerland | B37: Conference Series on AI in Finance | C37: Joerg Osterrieder, Switzerland | D37: 2 | E37: Joerg Osterrieder, Branka Hadji Misheva | F37: Switzerland | G37: yes | H37: National | I37: 80000 | J37: Innosuisse | K37: 2021 | L37: Funded
A38: Switzerland | B38: Blockchain and Fraud Detection | C38: Joerg Osterrieder, Switzerland | D38: 2 | E38: Branka Hadji Misheva, Joerg Osterrieder, Stephen Chan | F38: Switzerland, UAE | G38: yes | H38: Trans-National | I38: 6300 | J38: SNF | K38: 2021 | L38: Funded
A39: Netherlands | B39: AI in Finance | C39: Joerg Osterrieder, Netherlands, Branka Hadji Misheva, Switzerland | D39: 2 | E39: Joerg Osterrieder | F39: Netherlands | G39: yes | H39: National | I39: 320000 | J39: Industry | K39: 2022 | L39: Funded
A40: Switzerland | B40: Network-based credit risk models on P2P lending markets | C40: Branka Hadji Misheva, Switzerland | D40: 5 | E40: Joerg Osterrieder, Branka Hadji Misheva | F40: Switzerland, Czechia | G40: no | H40: Trans-National | I40: 500000 | J40: SNSF Lead Agency | K40: 2021 | L40: Funded
A41: Switzerland | B41: Digital Narratives | C41: Joerg Osterrieder, Switzerland | D41: 2 | E41: Joerg Osterrieder, Branka Hadji Misheva | F41: Switzerland | G41: yes | H41: National | I41: 240000 | J41: SNF | K41: 2022 | L41: under evaluation
A42: Switzerland | B42: XAI in credit risk management | C42: Branka Hadji Misheva, Switzerland | D42: 5 | E42: Branka Hadji Misheva, Joerg Osterrieder, Alex Posth, Marc Wildi | F42: Switzerland | G42: no | H42: National | I42: 350000 | J42: Innosuisse | K42: 2020 | L42: Funded
... A46: Poland | B46: Editorial boards of finance journals: gender and social connectedness | C46: Barbara Będowska-Sójka, Poland | D46: 8 | E46: Barbara Będowska-Sójka, Esra Kabaklarli, Codruta Mare, Belma Ozturkkal,Alessia Paccagnini, Rezarta Perri, Albulena Shala, Hanna Kristín Skaftadóttir,Claudia Tarantola | F46: Poland, Italy, Turkey, Romania, Ireland, Iceland, Albania, Kosovo | G46: no | H46: Trans-National | I46: 10000 | J46: Women and Science Chair at Université Paris Dauphine - PSL | K46: 2022 | L46: Not Funded
A47: Spain | B47: Assessing Blockchain-based Decentralized Autonomous Organizations for managing DeFi, NFTs and Metaverse projects (DAOapplications) | C47: Javier Arroyo, Spain | D47: 2 | E47: Javier Arroyo | F47: Spain | G47: No | H47: National | I47: 131000/93000 | J47: Generación de Conocimiento 2021 | K47: 2021 | L47: Funded
A48: Italy | B48: Financial literacy as an antidote to vulnerability: new measures and methods | C48: Sabrina Giordano, Italy | D48: 1 | E48: Sabrina Giordano | F48: Sabrina Giordano | G48: no | H48: National | I48: 35000 | J48: Fund to Support Research at University of Calabria | K48: 2021 | L48: Not Funded
A49: Norway | B49: Volatility Trading and Information Environment in Financial Markets (VTIEFM). Collaborative and knowledge building project. | C49: Per B Solibakke, Norway | D49: 2 | E49: Akarsh Kainth and Per B Solibakke | F49: Norway | G49: NO | H49: National | I49: 500000 | J49: NFR | K49: 2022 | L49: under evaluation
A50: Norway | B50: Sustainable Investments and Risk Management (SIRM) | C50: Per B Solibakke, Norway | E50: Akarsh Kainth and Per B Solibakke | F50: Norway | G50: NO | H50: National | I50: 500000 | J50: NFR | K50: 2022 | L50: NOT Fundex, new application 2023
A51: Kosovo | B51: Women in Fintech European Datathon | C51: Albulena Shala, Kosovo | D51: 3 | E51: Albulena Shala, Maria Iannario, Rrezerta Perri | F51: Kosovo, Italy, Albania | G51: No | H51: Trans-National | I51: 1500 | J51: Cost Action 13190 | K51: 2022 | L51: Not Funded Yet
A52: Netherland | B52: Digital Finance - Reaching New Frontiers | C52: Joerg Osterrieder, Netherlands | D52: 40 | E52: Jörg Osterrieder, Jos van Hillegersberg, Laura Spierdijk, Martijn Mes,Marcos Machado, Vijay Marisetty, Ekaterina Svetlova, Wouter van Heswijk, Abhistha Abhistha, Bettina Grün, Kurt Hornik, Ronald Hochreiter, Wolfgang Härdle, Stefan Lessmann, Rui Ren, Maria Iannario, Francesco Palumbo, Antonio Pescapè, Alfonso Iodice D'Enza, Kristina Šutienė, Eimutis Valakevičius, Audrius Kabašinskas, Daniel Traian Pele, Adrian Costea, Vasile Strat, Codruța Mare, Monica Violeta Achim, Cristian Mihai Dragos, Gennaro Di Brino, Federico Giudici, Stefano Penazzi, Stefan Theußl, Simon Haller, Franz Xaver Zobl, Aidas Malakauskas, Tadas Gudaitis, Nerijus Mačiulis, Saulius Šimkonis, Marco Bianchetti, Demetrio Maffei, Pietro Nazario Virgili, Alberto Ferrario, Matteo Macera Zappavigna, Maurizio Di Noia, Michael Althof, Julian Winkel, Bruno Spilak, Branka Hadji Misheva, Christian Hopp, Adam Kurpisz, Ioannis Emiris, Theodore Dalamagas, Giorgos Giannopoulos, Mattia Bellotti, Tuan Trinh, Salvatore Moccia, Ralf Korn, Robert Buch, Stefanie Schwaar, Daniela Schackis, Lukasz Kubicki, Theodoros Mastrokostopoulos, Benjamin Sahel, Maia Köhler, Filippo Bartoli | F52: Netherlands, Switzerland, Germany, Italy, Lithuania, Romania | G52: Yes | H52: other EU | I52: 4000 000 | J52: MSCA DN PLEASE ADD | K52: 2022 | L52: Under Evaluation

Sheet updated_25oct 
A1: Country | C1: Needed?(Y/N) | D1: Report | E1: Completed sections | F1: Missing sections | G1: Responsible | H1: Contact email | I1: Observations | J1: Reminder sent | K1: E-mail info updated until
A2: Albania | B2: Albania (AL) | C2: N | D2: yes^ | E2: 5.1 Action Publications | F2: all others | G2: Joerg | H2: rezartaperri@feut.edu.al | I2: ^country coordinator: Daniel Traian Pele (part of RO team) | J2: 44859 | K2: 44866
A3: Algeria | B3: Algeria (DZ) | C3: N | D3: no | G3: ? | K3: 44866
A4: Austria | B4: Austria (AT) | D4: yes | E4: 3. Progress on MoU | F4: all others | G4: Joerg | H4: ronald.hochreiter@wu.ac.at | J4: 44859 | K4: 44866
A5: Belgium | B5: Belgium (BE) | D5: yes | E5: 3; partly 4; 5.1 | F5: 1; 2; 5.3; 6; 7; 8; 9 | G5: Joerg | H5: christian.hafner@uclouvain.be | K5: 44866
A6: Bosnia-Hertegovina | B6: Bosnia and Herzegovina (BA) | C6: N | D6: no | G6: Joerg | H6: jelena.poljasevic@ef.unibl.org; igor.todorovic@ef.unibl.org | K6: 44866
A7: Bulgaria | B7: Bulgaria (BG) | D7: yes | E7: 2; 7 | F7: all others | G7: Joerg | H7: ygorbounov@nbu.bg | K7: 44866
